Workbook

Sheet 8月1日审计
A2: 2026-08-01 MILP审计
A3: 100MW/200MWh，月度份额版。订单由7月31日冻结，8月1日正式执行。
A4: A列为15分钟，B—H价格，I—P状态与选择，Q—W现金，BE—BK为带取值的计算过程。
A8: 时间 Bucharest | B8: DA价格 EUR/MWh | C8: FCR容量价 EUR/(MW·h) | D8: aFRR上容量价 EUR/(MW·h) | E8: aFRR下容量价 EUR/(MW·h) | F8: aFRR上激活价 EUR/MWh | G8: aFRR下激活价 EUR/MWh | H8: FCR激活 未纳入模型 | I8: 起SOC MWh | J8: 末SOC MWh | K8: DA净申报 MW | L8: FCR中标预留 MW | M8: aFRR上中标 MW | N8: aFRR下中标 MW | O8: 上调激活 MWh | P8: 下调激活 MWh | Q8: DA现金 EUR | R8: FCR容量现金 EUR | S8: aFRR上容量现金 EUR | T8: aFRR下容量现金 EUR | U8: aFRR上激活现金 EUR | V8: aFRR下激活现金 EUR | W8: 总现金 EUR | X8: 原账本总现金 EUR | Y8: 现金差异 EUR | Z8: 执行或计划 | AA8: aFRR小时有效 1/0 | AB8: FCR小时有效 1/0 | AC8: 时长h | AD8: FCR月份额 | AE8: aFRR月份额 | AF8: 有效α上 | AG8: 有效α下 | AH8: 系统上采购 MW | AI8: 系统下采购 MW | AJ8: 系统上激活 MWh | AK8: 系统下激活 MWh | AL8: 系统FCR采购 MW | AM8: EFC复算 | AN8: AC充电 MWh | AO8: AC放电 MWh | AP8: 相位复算末SOC MWh | AQ8: SOC差异 MWh | AR8: 汇率 RON/EUR | AS8: 汇率来源日 | AT8: UTC起点 | AU8: DA原生订单ID | AV8: DA原生分钟 | AW8: aFRR门禁原因 | AX8: FCR需求 MW | AY8: aFRR上需求 MW | AZ8: aFRR下需求 MW | BA8: FCR最终容量上限 MW | BB8: aFRR上最终上限 MW | BC8: aFRR下最终上限 MW | BD8: 求解窗口起日 | BE8: DA现金计算过程 | BF8: FCR容量现金计算过程 | BG8: aFRR上容量现金计算过程 | BH8: aFRR下容量现金计算过程 | BI8: aFRR上激活现金计算过程 | BJ8: aFRR下激活现金计算过程 | BK8: 总现金计算过程
A9: =两日求解价格与决策!A9 -> 46235 | B9: =两日求解价格与决策!B9 -> 179.01 | C9: =两日求解价格与决策!C9 -> 66.224535 | D9: =两日求解价格与决策!D9 -> 7.1274751 | E9: =两日求解价格与决策!E9 -> 2.7061536 | F9: =两日求解价格与决策!F9 -> 391.8358 | G9: =两日求解价格与决策!G9 -> 0 | H9: =两日求解价格与决策!H9 -> 未模拟 | ... Y9: =两日求解价格与决策!Y9 -> 0 | Z9: ="正式执行" -> 正式执行 | AA9: =两日求解价格与决策!AA9 -> 1 | AB9: =两日求解价格与决策!AB9 -> 1 | AC9: =两日求解价格与决策!AC9 -> 0.25 | AD9: =两日求解价格与决策!AD9 -> 0.3125 | AE9: =两日求解价格与决策!AE9 -> 0.13714286 | AF9: =两日求解价格与决策!AF9 -> 0.42109714 | AG9: =两日求解价格与决策!AG9 -> 0 | AH9: =两日求解价格与决策!AH9 -> 175 | ... BK9: =两日求解价格与决策!BK9 -> -1074.060000 + 662.245345 + 42.764850 + 16.236922 + 990.005618 + 0.000000 = 637.192736 EUR
A10: =两日求解价格与决策!A10 -> 46235.01 | B10: =两日求解价格与决策!B10 -> 170.12 | C10: =两日求解价格与决策!C10 -> 66.224535 | D10: =两日求解价格与决策!D10 -> 7.1274751 | E10: =两日求解价格与决策!E10 -> 2.7061536 | F10: =两日求解价格与决策!F10 -> 264.63515 | G10: =两日求解价格与决策!G10 -> 0 | H10: =两日求解价格与决策!H10 -> 未模拟 | ... Y10: =两日求解价格与决策!Y10 -> 0 | Z10: ="正式执行" -> 正式执行 | AA10: =两日求解价格与决策!AA10 -> 1 | AB10: =两日求解价格与决策!AB10 -> 1 | AC10: =两日求解价格与决策!AC10 -> 0.25 | AD10: =两日求解价格与决策!AD10 -> 0.3125 | AE10: =两日求解价格与决策!AE10 -> 0.13714286 | AF10: =两日求解价格与决策!AF10 -> 0.35289143 | AG10: =两日求解价格与决策!AG10 -> 0 | AH10: =两日求解价格与决策!AH10 -> 175 | ... BK10: =两日求解价格与决策!BK10 -> 0.000000 + 662.245345 + 42.764850 + 16.236922 + 560.324848 + 0.000000 = 1281.571965 EUR
A11: =两日求解价格与决策!A11 -> 46235.021 | B11: =两日求解价格与决策!B11 -> 167.36 | C11: =两日求解价格与决策!C11 -> 66.224535 | D11: =两日求解价格与决策!D11 -> 7.1274751 | E11: =两日求解价格与决策!E11 -> 2.7061536 | F11: =两日求解价格与决策!F11 -> 422.70215 | G11: =两日求解价格与决策!G11 -> 0 | H11: =两日求解价格与决策!H11 -> 未模拟 | ... Y11: =两日求解价格与决策!Y11 -> 0 | Z11: ="正式执行" -> 正式执行 | AA11: =两日求解价格与决策!AA11 -> 1 | AB11: =两日求解价格与决策!AB11 -> 1 | AC11: =两日求解价格与决策!AC11 -> 0.25 | AD11: =两日求解价格与决策!AD11 -> 0.3125 | AE11: =两日求解价格与决策!AE11 -> 0.13714286 | AF11: =两日求解价格与决策!AF11 -> 0.54525714 | AG11: =两日求解价格与决策!AG11 -> 0 | AH11: =两日求解价格与决策!AH11 -> 175 | ... BK11: =两日求解价格与决策!BK11 -> -1004.160000 + 662.245345 + 42.764850 + 16.236922 + 1382.888205 + 0.000000 = 1099.975322 EUR
A12: =两日求解价格与决策!A12 -> 46235.031 | B12: =两日求解价格与决策!B12 -> 165.13 | C12: =两日求解价格与决策!C12 -> 66.224535 | D12: =两日求解价格与决策!D12 -> 7.1274751 | E12: =两日求解价格与决策!E12 -> 2.7061536 | F12: =两日求解价格与决策!F12 -> 260.51455 | G12: =两日求解价格与决策!G12 -> 76.261125 | H12: =两日求解价格与决策!H12 -> 未模拟 | ... Y12: =两日求解价格与决策!Y12 -> 0 | Z12: ="正式执行" -> 正式执行 | AA12: =两日求解价格与决策!AA12 -> 1 | AB12: =两日求解价格与决策!AB12 -> 1 | AC12: =两日求解价格与决策!AC12 -> 0.25 | AD12: =两日求解价格与决策!AD12 -> 0.3125 | AE12: =两日求解价格与决策!AE12 -> 0.13714286 | AF12: =两日求解价格与决策!AF12 -> 0.31442286 | AG12: =两日求解价格与决策!AG12 -> 0.011337143 | AH12: =两日求解价格与决策!AH12 -> 175 | ... BK12: =两日求解价格与决策!BK12 -> -990.780000 + 662.245345 + 42.764850 + 16.236922 + 491.470375 + -5.187500 = 216.749993 EUR
A13: =两日求解价格与决策!A13 -> 46235.042 | B13: =两日求解价格与决策!B13 -> 184.32 | C13: =两日求解价格与决策!C13 -> 66.224535 | D13: =两日求解价格与决策!D13 -> 7.1274751 | E13: =两日求解价格与决策!E13 -> 2.7061536 | F13: =两日求解价格与决策!F13 -> 171.08894 | G13: =两日求解价格与决策!G13 -> 74.70947 | H13: =两日求解价格与决策!H13 -> 未模拟 | ... Y13: =两日求解价格与决策!Y13 -> 0 | Z13: ="正式执行" -> 正式执行 | AA13: =两日求解价格与决策!AA13 -> 1 | AB13: =两日求解价格与决策!AB13 -> 1 | AC13: =两日求解价格与决策!AC13 -> 0.25 | AD13: =两日求解价格与决策!AD13 -> 0.3125 | AE13: =两日求解价格与决策!AE13 -> 0.13714286 | AF13: =两日求解价格与决策!AF13 -> 0.024434286 | AG13: =两日求解价格与决策!AG13 -> 0.040342857 | AH13: =两日求解价格与决策!AH13 -> 175 | ... BK13: =两日求解价格与决策!BK13 -> 937.194033 + 662.245345 + 42.764850 + 16.236922 + 25.082616 + -18.083961 = 1665.439807 EUR
A14: =两日求解价格与决策!A14 -> 46235.052 | B14: =两日求解价格与决策!B14 -> 174.23 | C14: =两日求解价格与决策!C14 -> 66.224535 | D14: =两日求解价格与决策!D14 -> 7.1274751 | E14: =两日求解价格与决策!E14 -> 2.7061536 | F14: =两日求解价格与决策!F14 -> 190.53685 | G14: =两日求解价格与决策!G14 -> 0 | H14: =两日求解价格与决策!H14 -> 未模拟 | ... Y14: =两日求解价格与决策!Y14 -> 0 | Z14: ="正式执行" -> 正式执行 | AA14: =两日求解价格与决策!AA14 -> 1 | AB14: =两日求解价格与决策!AB14 -> 1 | AC14: =两日求解价格与决策!AC14 -> 0.25 | AD14: =两日求解价格与决策!AD14 -> 0.3125 | AE14: =两日求解价格与决策!AE14 -> 0.13714286 | AF14: =两日求解价格与决策!AF14 -> 0.12907429 | AG14: =两日求解价格与决策!AG14 -> 0 | AH14: =两日求解价格与决策!AH14 -> 175 | ... BK14: =两日求解价格与决策!BK14 -> 0.000000 + 662.245345 + 42.764850 + 16.236922 + 147.560445 + 0.000000 = 868.807563 EUR
A15: =两日求解价格与决策!A15 -> 46235.062 | B15: =两日求解价格与决策!B15 -> 165.3 | C15: =两日求解价格与决策!C15 -> 66.224535 | D15: =两日求解价格与决策!D15 -> 7.1274751 | E15: =两日求解价格与决策!E15 -> 2.7061536 | F15: =两日求解价格与决策!F15 -> 181.55185 | G15: =两日求解价格与决策!G15 -> 0 | H15: =两日求解价格与决策!H15 -> 未模拟 | ... Y15: =两日求解价格与决策!Y15 -> 0 | Z15: ="正式执行" -> 正式执行 | AA15: =两日求解价格与决策!AA15 -> 1 | AB15: =两日求解价格与决策!AB15 -> 1 | AC15: =两日求解价格与决策!AC15 -> 0.25 | AD15: =两日求解价格与决策!AD15 -> 0.3125 | AE15: =两日求解价格与决策!AE15 -> 0.13714286 | AF15: =两日求解价格与决策!AF15 -> 0.14537143 | AG15: =两日求解价格与决策!AG15 -> 0 | AH15: =两日求解价格与决策!AH15 -> 175 | ... BK15: =两日求解价格与决策!BK15 -> 0.000000 + 662.245345 + 42.764850 + 16.236922 + 158.354707 + 0.000000 = 879.601825 EUR
A16: =两日求解价格与决策!A16 -> 46235.073 | B16: =两日求解价格与决策!B16 -> 157.23 | C16: =两日求解价格与决策!C16 -> 66.224535 | D16: =两日求解价格与决策!D16 -> 7.1274751 | E16: =两日求解价格与决策!E16 -> 2.7061536 | F16: =两日求解价格与决策!F16 -> 190.08785 | G16: =两日求解价格与决策!G16 -> 0 | H16: =两日求解价格与决策!H16 -> 未模拟 | ... Y16: =两日求解价格与决策!Y16 -> 0 | Z16: ="正式执行" -> 正式执行 | AA16: =两日求解价格与决策!AA16 -> 1 | AB16: =两日求解价格与决策!AB16 -> 1 | AC16: =两日求解价格与决策!AC16 -> 0.25 | AD16: =两日求解价格与决策!AD16 -> 0.3125 | AE16: =两日求解价格与决策!AE16 -> 0.13714286 | AF16: =两日求解价格与决策!AF16 -> 0.14626286 | AG16: =两日求解价格与决策!AG16 -> 0 | AH16: =两日求解价格与决策!AH16 -> 175 | ... BK16: =两日求解价格与决策!BK16 -> -943.380000 + 662.245345 + 42.764850 + 16.236922 + 166.816756 + 0.000000 = -55.316126 EUR
A17: =两日求解价格与决策!A17 -> 46235.083 | B17: =两日求解价格与决策!B17 -> 170.44 | C17: =两日求解价格与决策!C17 -> 66.224535 | D17: =两日求解价格与决策!D17 -> 7.1274751 | E17: =两日求解价格与决策!E17 -> 2.7061536 | F17: =两日求解价格与决策!F17 -> 227.42973 | G17: =两日求解价格与决策!G17 -> 0 | H17: =两日求解价格与决策!H17 -> 未模拟 | ... Y17: =两日求解价格与决策!Y17 -> 0 | Z17: ="正式执行" -> 正式执行 | AA17: =两日求解价格与决策!AA17 -> 1 | AB17: =两日求解价格与决策!AB17 -> 1 | AC17: =两日求解价格与决策!AC17 -> 0.25 | AD17: =两日求解价格与决策!AD17 -> 0.3125 | AE17: =两日求解价格与决策!AE17 -> 0.13714286 | AF17: =两日求解价格与决策!AF17 -> 0.33814857 | AG17: =两日求解价格与决策!AG17 -> 0 | AH17: =两日求解价格与决策!AH17 -> 175 | ... BK17: =两日求解价格与决策!BK17 -> 0.000000 + 662.245345 + 42.764850 + 16.236922 + 461.430221 + 0.000000 = 1182.677339 EUR
A18: =两日求解价格与决策!A18 -> 46235.094 | B18: =两日求解价格与决策!B18 -> 169.42 | C18: =两日求解价格与决策!C18 -> 66.224535 | D18: =两日求解价格与决策!D18 -> 7.1274751 | E18: =两日求解价格与决策!E18 -> 2.7061536 | F18: =两日求解价格与决策!F18 -> 236.08846 | G18: =两日求解价格与决策!G18 -> 0 | H18: =两日求解价格与决策!H18 -> 未模拟 | ... Y18: =两日求解价格与决策!Y18 -> 0 | Z18: ="正式执行" -> 正式执行 | AA18: =两日求解价格与决策!AA18 -> 1 | AB18: =两日求解价格与决策!AB18 -> 1 | AC18: =两日求解价格与决策!AC18 -> 0.25 | AD18: =两日求解价格与决策!AD18 -> 0.3125 | AE18: =两日求解价格与决策!AE18 -> 0.13714286 | AF18: =两日求解价格与决策!AF18 -> 0.3504 | AG18: =两日求解价格与决策!AG18 -> 0 | AH18: =两日求解价格与决策!AH18 -> 175 | ... BK18: =两日求解价格与决策!BK18 -> 0.000000 + 662.245345 + 42.764850 + 16.236922 + 496.352388 + 0.000000 = 1217.599505 EUR
A19: =两日求解价格与决策!A19 -> 46235.104 | B19: =两日求解价格与决策!B19 -> 158.09 | C19: =两日求解价格与决策!C19 -> 66.224535 | D19: =两日求解价格与决策!D19 -> 7.1274751 | E19: =两日求解价格与决策!E19 -> 2.7061536 | F19: =两日求解价格与决策!F19 -> 179.29545 | G19: =两日求解价格与决策!G19 -> 0 | H19: =两日求解价格与决策!H19 -> 未模拟 | ... Y19: =两日求解价格与决策!Y19 -> 0 | Z19: ="正式执行" -> 正式执行 | AA19: =两日求解价格与决策!AA19 -> 1 | AB19: =两日求解价格与决策!AB19 -> 1 | AC19: =两日求解价格与决策!AC19 -> 0.25 | AD19: =两日求解价格与决策!AD19 -> 0.3125 | AE19: =两日求解价格与决策!AE19 -> 0.13714286 | AF19: =两日求解价格与决策!AF19 -> 0.040845714 | AG19: =两日求解价格与决策!AG19 -> 0 | AH19: =两日求解价格与决策!AH19 -> 175 | ... BK19: =两日求解价格与决策!BK19 -> -43.031250 + 662.245345 + 42.764850 + 16.236922 + 43.940704 + 0.000000 = 722.156571 EUR
A20: =两日求解价格与决策!A20 -> 46235.115 | B20: =两日求解价格与决策!B20 -> 156.91 | C20: =两日求解价格与决策!C20 -> 66.224535 | D20: =两日求解价格与决策!D20 -> 7.1274751 | E20: =两日求解价格与决策!E20 -> 2.7061536 | F20: =两日求解价格与决策!F20 -> 170.86159 | G20: =两日求解价格与决策!G20 -> 0 | H20: =两日求解价格与决策!H20 -> 未模拟 | ... Y20: =两日求解价格与决策!Y20 -> 0 | Z20: ="正式执行" -> 正式执行 | AA20: =两日求解价格与决策!AA20 -> 1 | AB20: =两日求解价格与决策!AB20 -> 1 | AC20: =两日求解价格与决策!AC20 -> 0.25 | AD20: =两日求解价格与决策!AD20 -> 0.3125 | AE20: =两日求解价格与决策!AE20 -> 0.13714286 | AF20: =两日求解价格与决策!AF20 -> 0.0448 | AG20: =两日求解价格与决策!AG20 -> 0 | AH20: =两日求解价格与决策!AH20 -> 175 | ... BK20: =两日求解价格与决策!BK20 -> -167.503950 + 662.245345 + 42.764850 + 16.236922 + 45.927594 + 0.000000 = 599.670761 EUR
... A104: =两日求解价格与决策!A104 -> 46235.99 | B104: =两日求解价格与决策!B104 -> 169.1 | C104: =两日求解价格与决策!C104 -> 66.224535 | D104: =两日求解价格与决策!D104 -> 7.1274751 | E104: =两日求解价格与决策!E104 -> 2.5937149 | F104: =两日求解价格与决策!F104 -> 198.77747 | G104: =两日求解价格与决策!G104 -> 77.182551 | H104: =两日求解价格与决策!H104 -> 未模拟 | ... Y104: =两日求解价格与决策!Y104 -> 0 | Z104: ="正式执行" -> 正式执行 | AA104: =两日求解价格与决策!AA104 -> 1 | AB104: =两日求解价格与决策!AB104 -> 1 | AC104: =两日求解价格与决策!AC104 -> 0.25 | AD104: =两日求解价格与决策!AD104 -> 0.3125 | AE104: =两日求解价格与决策!AE104 -> 0.13714286 | AF104: =两日求解价格与决策!AF104 -> 0.048937143 | AG104: =两日求解价格与决策!AG104 -> 0.00288 | AH104: =两日求解价格与决策!AH104 -> 175 | ... BK104: =两日求解价格与决策!BK104 -> 0.000000 + 662.245345 + 42.764850 + 15.562289 + 58.365608 + -1.333714 = 777.604378 EUR
A106: 当日现金及电量合计 | O106: =SUM(O9:O104) -> 72.037554 | P106: =SUM(P9:P104) -> 40.595177 | Q106: =SUM(Q9:Q104) -> 18846.745 | R106: =SUM(R9:R104) -> 63575.553 | S106: =SUM(S9:S104) -> 2990.1873 | T106: =SUM(T9:T104) -> 1894.1284 | U106: =SUM(U9:U104) -> 17712.625 | V106: =SUM(V9:V104) -> 2519.1835 | ... X106: =SUM(X9:X104) -> 107538.42
A109: 承接前日末SOC MWh | B109: =订单与窗口!C6 -> 31.73913
A110: 当日期末SOC MWh | B110: =J104 -> 31.73913
A112: 两天正式现金合计 EUR | B112: ='8月1日审计'!W106+'8月2日审计'!W106 -> 208618.55
A115: 容量现金=中标预留MW×价格×时长；月份额只限制MW，不再次乘现金。
A116: FCR对称容量只计一次；激活电量已为MWh，不再乘0.25小时。
A117: 逐行现金公式在Q—W，含取值的过程在BE—BK；显示精度不改变底层数值。

Sheet 8月2日审计
A2: 2026-08-02 MILP审计
A3: 100MW/200MWh，月度份额版。订单由8月1日冻结，8月2日正式执行。
A4: A列为15分钟，B—H价格，I—P状态与选择，Q—W现金，BE—BK为带取值的计算过程。
A8: 时间 Bucharest | B8: DA价格 EUR/MWh | C8: FCR容量价 EUR/(MW·h) | D8: aFRR上容量价 EUR/(MW·h) | E8: aFRR下容量价 EUR/(MW·h) | F8: aFRR上激活价 EUR/MWh | G8: aFRR下激活价 EUR/MWh | H8: FCR激活 未纳入模型 | I8: 起SOC MWh | J8: 末SOC MWh | K8: DA净申报 MW | L8: FCR中标预留 MW | M8: aFRR上中标 MW | N8: aFRR下中标 MW | O8: 上调激活 MWh | P8: 下调激活 MWh | Q8: DA现金 EUR | R8: FCR容量现金 EUR | S8: aFRR上容量现金 EUR | T8: aFRR下容量现金 EUR | U8: aFRR上激活现金 EUR | V8: aFRR下激活现金 EUR | W8: 总现金 EUR | X8: 原账本总现金 EUR | Y8: 现金差异 EUR | Z8: 执行或计划 | AA8: aFRR小时有效 1/0 | AB8: FCR小时有效 1/0 | AC8: 时长h | AD8: FCR月份额 | AE8: aFRR月份额 | AF8: 有效α上 | AG8: 有效α下 | AH8: 系统上采购 MW | AI8: 系统下采购 MW | AJ8: 系统上激活 MWh | AK8: 系统下激活 MWh | AL8: 系统FCR采购 MW | AM8: EFC复算 | AN8: AC充电 MWh | AO8: AC放电 MWh | AP8: 相位复算末SOC MWh | AQ8: SOC差异 MWh | AR8: 汇率 RON/EUR | AS8: 汇率来源日 | AT8: UTC起点 | AU8: DA原生订单ID | AV8: DA原生分钟 | AW8: aFRR门禁原因 | AX8: FCR需求 MW | AY8: aFRR上需求 MW | AZ8: aFRR下需求 MW | BA8: FCR最终容量上限 MW | BB8: aFRR上最终上限 MW | BC8: aFRR下最终上限 MW | BD8: 求解窗口起日 | BE8: DA现金计算过程 | BF8: FCR容量现金计算过程 | BG8: aFRR上容量现金计算过程 | BH8: aFRR下容量现金计算过程 | BI8: aFRR上激活现金计算过程 | BJ8: aFRR下激活现金计算过程 | BK8: 总现金计算过程
A9: =两日求解价格与决策!A201 -> 46236 | B9: =两日求解价格与决策!B201 -> 172.11 | C9: =两日求解价格与决策!C201 -> 66.224535 | D9: =两日求解价格与决策!D201 -> 7.1274751 | E9: =两日求解价格与决策!E201 -> 2.7061536 | F9: =两日求解价格与决策!F201 -> 184.1103 | G9: =两日求解价格与决策!G201 -> 77.182551 | H9: =两日求解价格与决策!H201 -> 未模拟 | ... Y9: =两日求解价格与决策!Y201 -> 0 | Z9: ="正式执行" -> 正式执行 | AA9: =两日求解价格与决策!AA201 -> 1 | AB9: =两日求解价格与决策!AB201 -> 1 | AC9: =两日求解价格与决策!AC201 -> 0.25 | AD9: =两日求解价格与决策!AD201 -> 0.3125 | AE9: =两日求解价格与决策!AE201 -> 0.13714286 | AF9: =两日求解价格与决策!AF201 -> 0.05232 | AG9: =两日求解价格与决策!AG201 -> 0.0080685714 | AH9: =两日求解价格与决策!AH201 -> 175 | ... BK9: =两日求解价格与决策!BK201 -> -794.202771 + 662.245345 + 42.764850 + 16.236922 + 57.795907 + -3.736518 = -18.896264 EUR
A10: =两日求解价格与决策!A202 -> 46236.01 | B10: =两日求解价格与决策!B202 -> 171.94 | C10: =两日求解价格与决策!C202 -> 66.224535 | D10: =两日求解价格与决策!D202 -> 7.1274751 | E10: =两日求解价格与决策!E202 -> 2.7061536 | F10: =两日求解价格与决策!F202 -> 0 | G10: =两日求解价格与决策!G202 -> 70.316734 | H10: =两日求解价格与决策!H202 -> 未模拟 | ... Y10: =两日求解价格与决策!Y202 -> 0 | Z10: ="正式执行" -> 正式执行 | AA10: =两日求解价格与决策!AA202 -> 1 | AB10: =两日求解价格与决策!AB202 -> 1 | AC10: =两日求解价格与决策!AC202 -> 0.25 | AD10: =两日求解价格与决策!AD202 -> 0.3125 | AE10: =两日求解价格与决策!AE202 -> 0.13714286 | AF10: =两日求解价格与决策!AF202 -> 0 | AG10: =两日求解价格与决策!AG202 -> 0.12836571 | AH10: =两日求解价格与决策!AH202 -> 175 | ... BK10: =两日求解价格与决策!BK202 -> 0.000000 + 662.245345 + 42.764850 + 16.236922 + 0.000000 + -54.157547 = 667.089571 EUR
A11: =两日求解价格与决策!A203 -> 46236.021 | B11: =两日求解价格与决策!B203 -> 171.23 | C11: =两日求解价格与决策!C203 -> 66.224535 | D11: =两日求解价格与决策!D203 -> 7.1274751 | E11: =两日求解价格与决策!E203 -> 2.7061536 | F11: =两日求解价格与决策!F203 -> 176.42483 | G11: =两日求解价格与决策!G203 -> 70.125588 | H11: =两日求解价格与决策!H203 -> 未模拟 | ... Y11: =两日求解价格与决策!Y203 -> 0 | Z11: ="正式执行" -> 正式执行 | AA11: =两日求解价格与决策!AA203 -> 1 | AB11: =两日求解价格与决策!AB203 -> 1 | AC11: =两日求解价格与决策!AC203 -> 0.25 | AD11: =两日求解价格与决策!AD203 -> 0.3125 | AE11: =两日求解价格与决策!AE203 -> 0.13714286 | AF11: =两日求解价格与决策!AF203 -> 0.019908571 | AG11: =两日求解价格与决策!AG203 -> 0.02832 | AH11: =两日求解价格与决策!AH203 -> 175 | ... BK11: =两日求解价格与决策!BK203 -> 0.000000 + 662.245345 + 42.764850 + 16.236922 + 21.074198 + -11.915740 = 730.405575 EUR
A12: =两日求解价格与决策!A204 -> 46236.031 | B12: =两日求解价格与决策!B204 -> 164.72 | C12: =两日求解价格与决策!C204 -> 66.224535 | D12: =两日求解价格与决策!D204 -> 7.1274751 | E12: =两日求解价格与决策!E204 -> 2.7061536 | F12: =两日求解价格与决策!F204 -> 157.46479 | G12: =两日求解价格与决策!G204 -> 76.985497 | H12: =两日求解价格与决策!H204 -> 未模拟 | ... Y12: =两日求解价格与决策!Y204 -> 0 | Z12: ="正式执行" -> 正式执行 | AA12: =两日求解价格与决策!AA204 -> 1 | AB12: =两日求解价格与决策!AB204 -> 1 | AC12: =两日求解价格与决策!AC204 -> 0.25 | AD12: =两日求解价格与决策!AD204 -> 0.3125 | AE12: =两日求解价格与决策!AE204 -> 0.13714286 | AF12: =两日求解价格与决策!AF204 -> 0.00336 | AG12: =两日求解价格与决策!AG204 -> 0.023085714 | AH12: =两日求解价格与决策!AH204 -> 175 | ... BK12: =两日求解价格与决策!BK204 -> 0.000000 + 662.245345 + 42.764850 + 16.236922 + 3.174490 + -10.663591 = 713.758017 EUR
A13: =两日求解价格与决策!A205 -> 46236.042 | B13: =两日求解价格与决策!B205 -> 189.01 | C13: =两日求解价格与决策!C205 -> 66.224535 | D13: =两日求解价格与决策!D205 -> 7.1274751 | E13: =两日求解价格与决策!E205 -> 2.7061536 | F13: =两日求解价格与决策!F205 -> 0 | G13: =两日求解价格与决策!G205 -> 76.829989 | H13: =两日求解价格与决策!H205 -> 未模拟 | ... Y13: =两日求解价格与决策!Y205 -> 0 | Z13: ="正式执行" -> 正式执行 | AA13: =两日求解价格与决策!AA205 -> 1 | AB13: =两日求解价格与决策!AB205 -> 1 | AC13: =两日求解价格与决策!AC205 -> 0.25 | AD13: =两日求解价格与决策!AD205 -> 0.3125 | AE13: =两日求解价格与决策!AE205 -> 0.13714286 | AF13: =两日求解价格与决策!AF205 -> 0 | AG13: =两日求解价格与决策!AG205 -> 0.14333714 | AH13: =两日求解价格与决策!AH205 -> 175 | ... BK13: =两日求解价格与决策!BK205 -> 999.396879 + 662.245345 + 42.764850 + 16.236922 + 0.000000 + -66.075546 = 1654.568450 EUR
A14: =两日求解价格与决策!A206 -> 46236.052 | B14: =两日求解价格与决策!B206 -> 171.26 | C14: =两日求解价格与决策!C206 -> 66.224535 | D14: =两日求解价格与决策!D206 -> 7.1274751 | E14: =两日求解价格与决策!E206 -> 2.7061536 | F14: =两日求解价格与决策!F206 -> 152.45936 | G14: =两日求解价格与决策!G206 -> 77.033713 | H14: =两日求解价格与决策!H206 -> 未模拟 | ... Y14: =两日求解价格与决策!Y206 -> 0 | Z14: ="正式执行" -> 正式执行 | AA14: =两日求解价格与决策!AA206 -> 1 | AB14: =两日求解价格与决策!AB206 -> 1 | AC14: =两日求解价格与决策!AC206 -> 0.25 | AD14: =两日求解价格与决策!AD206 -> 0.3125 | AE14: =两日求解价格与决策!AE206 -> 0.13714286 | AF14: =两日求解价格与决策!AF206 -> 9.1428571e-05 | AG14: =两日求解价格与决策!AG206 -> 0.027748571 | AH14: =两日求解价格与决策!AH206 -> 175 | ... BK14: =两日求解价格与决策!BK206 -> 0.000000 + 662.245345 + 42.764850 + 16.236922 + 0.083635 + -12.825453 = 708.505300 EUR
A15: =两日求解价格与决策!A207 -> 46236.062 | B15: =两日求解价格与决策!B207 -> 161.1 | C15: =两日求解价格与决策!C207 -> 66.224535 | D15: =两日求解价格与决策!D207 -> 7.1274751 | E15: =两日求解价格与决策!E207 -> 2.7061536 | F15: =两日求解价格与决策!F207 -> 152.45936 | G15: =两日求解价格与决策!G207 -> 77.182551 | H15: =两日求解价格与决策!H207 -> 未模拟 | ... Y15: =两日求解价格与决策!Y207 -> 0 | Z15: ="正式执行" -> 正式执行 | AA15: =两日求解价格与决策!AA207 -> 1 | AB15: =两日求解价格与决策!AB207 -> 1 | AC15: =两日求解价格与决策!AC207 -> 0.25 | AD15: =两日求解价格与决策!AD207 -> 0.3125 | AE15: =两日求解价格与决策!AE207 -> 0.13714286 | AF15: =两日求解价格与决策!AF207 -> 0.00208 | AG15: =两日求解价格与决策!AG207 -> 0.032708571 | AH15: =两日求解价格与决策!AH207 -> 175 | ... BK15: =两日求解价格与决策!BK207 -> 0.000000 + 662.245345 + 42.764850 + 16.236922 + 1.902693 + -15.147186 = 708.002624 EUR
A16: =两日求解价格与决策!A208 -> 46236.073 | B16: =两日求解价格与决策!B208 -> 160.43 | C16: =两日求解价格与决策!C208 -> 66.224535 | D16: =两日求解价格与决策!D208 -> 7.1274751 | E16: =两日求解价格与决策!E208 -> 2.7061536 | F16: =两日求解价格与决策!F208 -> 165.00619 | G16: =两日求解价格与决策!G208 -> 77.182551 | H16: =两日求解价格与决策!H208 -> 未模拟 | ... Y16: =两日求解价格与决策!Y208 -> 0 | Z16: ="正式执行" -> 正式执行 | AA16: =两日求解价格与决策!AA208 -> 1 | AB16: =两日求解价格与决策!AB208 -> 1 | AC16: =两日求解价格与决策!AC208 -> 0.25 | AD16: =两日求解价格与决策!AD208 -> 0.3125 | AE16: =两日求解价格与决策!AE208 -> 0.13714286 | AF16: =两日求解价格与决策!AF208 -> 0.00464 | AG16: =两日求解价格与决策!AG208 -> 0.0104 | AH16: =两日求解价格与决策!AH208 -> 175 | ... BK16: =两日求解价格与决策!BK208 -> 0.000000 + 662.245345 + 42.764850 + 16.236922 + 4.593772 + -4.816191 = 721.024699 EUR
A17: =两日求解价格与决策!A209 -> 46236.083 | B17: =两日求解价格与决策!B209 -> 160.86 | C17: =两日求解价格与决策!C209 -> 66.224535 | D17: =两日求解价格与决策!D209 -> 7.1274751 | E17: =两日求解价格与决策!E209 -> 2.7061536 | F17: =两日求解价格与决策!F209 -> 178.91716 | G17: =两日求解价格与决策!G209 -> 0 | H17: =两日求解价格与决策!H209 -> 未模拟 | ... Y17: =两日求解价格与决策!Y209 -> 0 | Z17: ="正式执行" -> 正式执行 | AA17: =两日求解价格与决策!AA209 -> 1 | AB17: =两日求解价格与决策!AB209 -> 1 | AC17: =两日求解价格与决策!AC209 -> 0.25 | AD17: =两日求解价格与决策!AD209 -> 0.3125 | AE17: =两日求解价格与决策!AE209 -> 0.13714286 | AF17: =两日求解价格与决策!AF209 -> 0.050034286 | AG17: =两日求解价格与决策!AG209 -> 0 | AH17: =两日求解价格与决策!AH209 -> 175 | ... BK17: =两日求解价格与决策!BK209 -> -7.248674 + 662.245345 + 42.764850 + 16.236922 + 53.711953 + 0.000000 = 767.710397 EUR
A18: =两日求解价格与决策!A210 -> 46236.094 | B18: =两日求解价格与决策!B210 -> 156.81 | C18: =两日求解价格与决策!C210 -> 66.224535 | D18: =两日求解价格与决策!D210 -> 7.1274751 | E18: =两日求解价格与决策!E210 -> 2.7061536 | F18: =两日求解价格与决策!F210 -> 171.4133 | G18: =两日求解价格与决策!G210 -> 76.945667 | H18: =两日求解价格与决策!H210 -> 未模拟 | ... Y18: =两日求解价格与决策!Y210 -> 0 | Z18: ="正式执行" -> 正式执行 | AA18: =两日求解价格与决策!AA210 -> 1 | AB18: =两日求解价格与决策!AB210 -> 1 | AC18: =两日求解价格与决策!AC210 -> 0.25 | AD18: =两日求解价格与决策!AD210 -> 0.3125 | AE18: =两日求解价格与决策!AE210 -> 0.13714286 | AF18: =两日求解价格与决策!AF210 -> 0.062857143 | AG18: =两日求解价格与决策!AG210 -> 0.030742857 | AH18: =两日求解价格与决策!AH210 -> 175 | ... BK18: =两日求解价格与决策!BK210 -> -288.935452 + 662.245345 + 42.764850 + 16.236922 + 64.647301 + -14.193178 = 482.765788 EUR
A19: =两日求解价格与决策!A211 -> 46236.104 | B19: =两日求解价格与决策!B211 -> 162.01 | C19: =两日求解价格与决策!C211 -> 66.224535 | D19: =两日求解价格与决策!D211 -> 7.1274751 | E19: =两日求解价格与决策!E211 -> 2.7061536 | F19: =两日求解价格与决策!F211 -> 171.25703 | G19: =两日求解价格与决策!G211 -> 77.182551 | H19: =两日求解价格与决策!H211 -> 未模拟 | ... Y19: =两日求解价格与决策!Y211 -> 0 | Z19: ="正式执行" -> 正式执行 | AA19: =两日求解价格与决策!AA211 -> 1 | AB19: =两日求解价格与决策!AB211 -> 1 | AC19: =两日求解价格与决策!AC211 -> 0.25 | AD19: =两日求解价格与决策!AD211 -> 0.3125 | AE19: =两日求解价格与决策!AE211 -> 0.13714286 | AF19: =两日求解价格与决策!AF211 -> 0.095771429 | AG19: =两日求解价格与决策!AG211 -> 0.00038857143 | AH19: =两日求解价格与决策!AH211 -> 175 | ... BK19: =两日求解价格与决策!BK211 -> 0.000000 + 662.245345 + 42.764850 + 16.236922 + 98.409181 + -0.179946 = 819.476353 EUR
A20: =两日求解价格与决策!A212 -> 46236.115 | B20: =两日求解价格与决策!B212 -> 160.5 | C20: =两日求解价格与决策!C212 -> 66.224535 | D20: =两日求解价格与决策!D212 -> 7.1274751 | E20: =两日求解价格与决策!E212 -> 2.7061536 | F20: =两日求解价格与决策!F212 -> 161.2334 | G20: =两日求解价格与决策!G212 -> 0 | H20: =两日求解价格与决策!H212 -> 未模拟 | ... Y20: =两日求解价格与决策!Y212 -> 0 | Z20: ="正式执行" -> 正式执行 | AA20: =两日求解价格与决策!AA212 -> 1 | AB20: =两日求解价格与决策!AB212 -> 1 | AC20: =两日求解价格与决策!AC212 -> 0.25 | AD20: =两日求解价格与决策!AD212 -> 0.3125 | AE20: =两日求解价格与决策!AE212 -> 0.13714286 | AF20: =两日求解价格与决策!AF212 -> 0.00752 | AG20: =两日求解价格与决策!AG212 -> 0 | AH20: =两日求解价格与决策!AH212 -> 175 | ... BK20: =两日求解价格与决策!BK212 -> 0.000000 + 662.245345 + 42.764850 + 16.236922 + 7.274851 + 0.000000 = 728.521968 EUR
... A104: =两日求解价格与决策!A296 -> 46236.99 | B104: =两日求解价格与决策!B296 -> 183.75 | C104: =两日求解价格与决策!C296 -> 66.224535 | D104: =两日求解价格与决策!D296 -> 7.1274751 | E104: =两日求解价格与决策!E296 -> 2.5937149 | F104: =两日求解价格与决策!F296 -> 218.7485 | G104: =两日求解价格与决策!G296 -> 76.420254 | H104: =两日求解价格与决策!H296 -> 未模拟 | ... Y104: =两日求解价格与决策!Y296 -> 0 | Z104: ="正式执行" -> 正式执行 | AA104: =两日求解价格与决策!AA296 -> 1 | AB104: =两日求解价格与决策!AB296 -> 1 | AC104: =两日求解价格与决策!AC296 -> 0.25 | AD104: =两日求解价格与决策!AD296 -> 0.3125 | AE104: =两日求解价格与决策!AE296 -> 0.13714286 | AF104: =两日求解价格与决策!AF296 -> 0.14198857 | AG104: =两日求解价格与决策!AG296 -> 0.00096 | AH104: =两日求解价格与决策!AH296 -> 175 | ... BK104: =两日求解价格与决策!BK296 -> 0.000000 + 662.245345 + 42.764850 + 15.562289 + 186.358721 + -0.440181 = 906.491026 EUR
A106: 当日现金及电量合计 | O106: =SUM(O9:O104) -> 48.081737 | P106: =SUM(P9:P104) -> 53.256686 | Q106: =SUM(Q9:Q104) -> 22387.47 | R106: =SUM(R9:R104) -> 61841.328 | S106: =SUM(S9:S104) -> 3527.6199 | T106: =SUM(T9:T104) -> 2074.8957 | U106: =SUM(U9:U104) -> 9593.7193 | V106: =SUM(V9:V104) -> 1655.097 | ... X106: =SUM(X9:X104) -> 101080.13
A109: 承接前日末SOC MWh | B109: =订单与窗口!C7 -> 31.73913
A110: 当日期末SOC MWh | B110: =J104 -> 31.73913
A112: 两天正式现金合计 EUR | B112: ='8月1日审计'!W106+'8月2日审计'!W106 -> 208618.55
A115: 容量现金=中标预留MW×价格×时长；月份额只限制MW，不再次乘现金。
A116: FCR对称容量只计一次；激活电量已为MWh，不再乘0.25小时。
A117: 逐行现金公式在Q—W，含取值的过程在BE—BK；显示精度不改变底层数值。

Sheet 两日求解价格与决策
A2: 两次MILP求解的价格、决策与现金
A3: 首192行：8月1日求解，8月1日执行及8月2日冻结计划；后192行：8月2日求解及8月3日计划。
A4: 六类现金在本表通过Excel公式计算，日审计表链接执行部分。8月3日不计入两天现金。
J5: 1hr
J6: =40*66 -> 2640
A8: 时间 Bucharest | B8: DA价格 EUR/MWh | C8: FCR容量价 EUR/(MW·h) | D8: aFRR上容量价 EUR/(MW·h) | E8: aFRR下容量价 EUR/(MW·h) | F8: aFRR上激活价 EUR/MWh | G8: aFRR下激活价 EUR/MWh | H8: FCR激活 未纳入模型 | I8: 起SOC MWh | J8: 末SOC MWh | K8: DA净申报 MW | L8: FCR中标预留 MW | M8: aFRR上中标 MW | N8: aFRR下中标 MW | O8: 上调激活 MWh | P8: 下调激活 MWh | Q8: DA现金 EUR | R8: FCR容量现金 EUR | S8: aFRR上容量现金 EUR | T8: aFRR下容量现金 EUR | U8: aFRR上激活现金 EUR | V8: aFRR下激活现金 EUR | W8: 总现金 EUR | X8: 原账本总现金 EUR | Y8: 现金差异 EUR | Z8: 执行或计划 | AA8: aFRR小时有效 1/0 | AB8: FCR小时有效 1/0 | AC8: 时长h | AD8: FCR月份额 | AE8: aFRR月份额 | AF8: 有效α上 | AG8: 有效α下 | AH8: 系统上采购 MW | AI8: 系统下采购 MW | AJ8: 系统上激活 MWh | AK8: 系统下激活 MWh | AL8: 系统FCR采购 MW | AM8: EFC复算 | AN8: AC充电 MWh | AO8: AC放电 MWh | AP8: 相位复算末SOC MWh | AQ8: SOC差异 MWh | AR8: 汇率 RON/EUR | AS8: 汇率来源日 | AT8: UTC起点 | AU8: DA原生订单ID | AV8: DA原生分钟 | AW8: aFRR门禁原因 | AX8: FCR需求 MW | AY8: aFRR上需求 MW | AZ8: aFRR下需求 MW | BA8: FCR最终容量上限 MW | BB8: aFRR上最终上限 MW | BC8: aFRR下最终上限 MW | BD8: 求解窗口起日 | BE8: DA现金计算过程 | BF8: FCR容量现金计算过程 | BG8: aFRR上容量现金计算过程 | BH8: aFRR下容量现金计算过程 | BI8: aFRR上激活现金计算过程 | BJ8: aFRR下激活现金计算过程 | BK8: 总现金计算过程
A9: =原始输入与口径!C9 -> 46235 | B9: =IF(ISNUMBER(原始输入与口径!H9),原始输入与口径!H9,"缺失") -> 179.01 | C9: =IF(ISNUMBER(原始输入与口径!R9),原始输入与口径!R9,"缺失") -> 66.224535 | D9: =IF(ISNUMBER(原始输入与口径!W9),原始输入与口径!W9,"缺失") -> 7.1274751 | E9: =IF(ISNUMBER(原始输入与口径!AB9),原始输入与口径!AB9,"缺失") -> 2.7061536 | F9: =IF(ISNUMBER(原始输入与口径!AG9),原始输入与口径!AG9,"缺失") -> 391.8358 | G9: =IF(ISNUMBER(原始输入与口径!AJ9),原始输入与口径!AJ9,"缺失") -> 0 | H9: ="未模拟" -> 未模拟 | I9: =原始输入与口径!CD9 -> 31.73913 | J9: =原始输入与口径!CE9 -> 34.934674 | K9: =原始输入与口径!BZ9 -> -24 | L9: =原始输入与口径!CK9 -> 40 | M9: =原始输入与口径!BT9 -> 24 | N9: =原始输入与口径!BJ9 -> 24 | O9: =M9*AF9*AC9 -> 2.5265829 | P9: =N9*AG9*AC9 -> 0 | Q9: =IF(K9=0,0,IF(ISNUMBER(B9),K9*B9*AC9,NA())) -> -1074.06 | R9: =IF(L9=0,0,IF(ISNUMBER(C9),L9*C9*AC9,NA())) -> 662.24535 | S9: =IF(M9=0,0,IF(ISNUMBER(D9),M9*D9*AC9,NA())) -> 42.76485 | T9: =IF(N9=0,0,IF(ISNUMBER(E9),N9*E9*AC9,NA())) -> 16.236922 | U9: =IF(O9=0,0,O9*F9) -> 990.00562 | V9: =IF(P9=0,0,-P9*G9) -> 0 | W9: =SUM(Q9:V9) -> 637.19274 | X9: =原始输入与口径!CP9 -> 637.19274 | Y9: =W9-X9 -> 0 | Z9: ="当日执行" -> 当日执行 | AA9: =IF(原始输入与口径!AW9,1,0) -> 1 | AB9: =IF(原始输入与口径!AY9,1,0) -> 1 | AC9: =原始输入与口径!$F$5 -> 0.25 | AD9: =原始输入与口径!CG9 -> 0.3125 | AE9: =原始输入与口径!BQ9 -> 0.13714286 | AF9: =IF(AA9=0,0,AJ9/(AH9*AC9)) -> 0.42109714 | AG9: =IF(AA9=0,0,AK9/(AI9*AC9)) -> 0 | AH9: =IF(ISNUMBER(原始输入与口径!T9),原始输入与口径!T9,"缺失") -> 175 | AI9: =IF(ISNUMBER(原始输入与口径!Y9),原始输入与口径!Y9,"缺失") -> 175 | AJ9: =IF(ISNUMBER(原始输入与口径!AI9),原始输入与口径!AI9,"缺失") -> 18.423 | AK9: =IF(ISNUMBER(原始输入与口径!AL9),原始输入与口径!AL9,"缺失") -> 0 | AL9: =IF(ISNUMBER(原始输入与口径!O9),原始输入与口径!O9,"缺失") -> 131.968 | AM9: =SUMIFS(相位SOC复算!$N$9:$N$929,相位SOC复算!$S$9:$S$929,1) -> 0.0088765105 | AN9: =SUMIFS(相位SOC复算!$Q$9:$Q$929,相位SOC复算!$S$9:$S$929,1) -> 3.4734171 | AO9: =SUMIFS(相位SOC复算!$R$9:$R$929,相位SOC复算!$S$9:$S$929,1) -> 1.9822498e-14 | AP9: =相位SOC复算!J10 -> 34.934674 | AQ9: =AP9-J9 -> 0 | AR9: =IF(ISBLANK(原始输入与口径!M9),"",原始输入与口径!M9) -> 5.2473 | AS9: =IF(ISBLANK(原始输入与口径!L9),"",原始输入与口径!L9) -> 46234 | AT9: =IF(ISBLANK(原始输入与口径!A9),"",原始输入与口径!A9) -> 46234.875 | AU9: =IF(ISBLANK(原始输入与口径!I9),"",原始输入与口径!I9) -> 2026-07-31_93 | AV9: =IF(ISBLANK(原始输入与口径!J9),"",原始输入与口径!J9) -> 15 | AW9: =IF(ISBLANK(原始输入与口径!BB9),"",原始输入与口径!BB9) -> OK | AX9: =原始输入与口径!CI9 -> 128 | AY9: =原始输入与口径!BS9 -> 175 | AZ9: =原始输入与口径!BI9 -> 175 | BA9: =原始输入与口径!CM9 -> 40 | BB9: =原始输入与口径!BV9 -> 24 | BC9: =原始输入与口径!BL9 -> 24 | BD9: =46235 -> 46235 | BE9: =IF(K9=0,"零头寸，无结算现金",TEXT(K9,"0.000000")&" MW × "&TEXT(B9,"0.000000")&" × "&TEXT(AC9,"0.000000")&" h = "&TEXT(Q9,"0.000000")&" EUR") -> -24.000000 MW × 179.010000 × 0.250000 h = -1074.060000 EUR | BF9: =IF(L9=0,"零头寸，无结算现金",TEXT(L9,"0.000000")&" MW × "&TEXT(C9,"0.000000")&" × "&TEXT(AC9,"0.000000")&" h = "&TEXT(R9,"0.000000")&" EUR") -> 40.000000 MW × 66.224535 × 0.250000 h = 662.245345 EUR | BG9: =IF(M9=0,"零头寸，无结算现金",TEXT(M9,"0.000000")&" MW × "&TEXT(D9,"0.000000")&" × "&TEXT(AC9,"0.000000")&" h = "&TEXT(S9,"0.000000")&" EUR") -> 24.000000 MW × 7.127475 × 0.250000 h = 42.764850 EUR | BH9: =IF(N9=0,"零头寸，无结算现金",TEXT(N9,"0.000000")&" MW × "&TEXT(E9,"0.000000")&" × "&TEXT(AC9,"0.000000")&" h = "&TEXT(T9,"0.000000")&" EUR") -> 24.000000 MW × 2.706154 × 0.250000 h = 16.236922 EUR | BI9: =IF(O9=0,"零上调激活电量",TEXT(O9,"0.000000")&" MWh × "&TEXT(F9,"0.000000")&" = "&TEXT(U9,"0.000000")&" EUR") -> 2.526583 MWh × 391.835801 = 990.005618 EUR | BJ9: =IF(P9=0,"零下调激活电量","−("&TEXT(P9,"0.000000")&" MWh × "&TEXT(G9,"0.000000")&") = "&TEXT(V9,"0.000000")&" EUR") -> 零下调激活电量 | BK9: =TEXT(Q9,"0.000000")&" + "&TEXT(R9,"0.000000")&" + "&TEXT(S9,"0.000000")&" + "&TEXT(T9,"0.000000")&" + "&TEXT(U9,"0.000000")&" + "&TEXT(V9,"0.000000")&" = "&TEXT(W9,"0.000000")&" EUR" -> -1074.060000 + 662.245345 + 42.764850 + 16.236922 + 990.005618 + 0.000000 = 637.192736 EUR
A10: =原始输入与口径!C10 -> 46235.01 | B10: =IF(ISNUMBER(原始输入与口径!H10),原始输入与口径!H10,"缺失") -> 170.12 | C10: =IF(ISNUMBER(原始输入与口径!R10),原始输入与口径!R10,"缺失") -> 66.224535 | D10: =IF(ISNUMBER(原始输入与口径!W10),原始输入与口径!W10,"缺失") -> 7.1274751 | E10: =IF(ISNUMBER(原始输入与口径!AB10),原始输入与口径!AB10,"缺失") -> 2.7061536 | F10: =IF(ISNUMBER(原始输入与口径!AG10),原始输入与口径!AG10,"缺失") -> 264.63515 | G10: =IF(ISNUMBER(原始输入与口径!AJ10),原始输入与口径!AJ10,"缺失") -> 0 | H10: ="未模拟" -> 未模拟 | I10: =原始输入与口径!CD10 -> 34.934674 | J10: =原始输入与口径!CE10 -> 32.633208 | K10: =原始输入与口径!BZ10 -> 0 | L10: =原始输入与口径!CK10 -> 40 | M10: =原始输入与口径!BT10 -> 24 | N10: =原始输入与口径!BJ10 -> 24 | O10: =M10*AF10*AC10 -> 2.1173486 | P10: =N10*AG10*AC10 -> 0 | Q10: =IF(K10=0,0,IF(ISNUMBER(B10),K10*B10*AC10,NA())) -> 0 | R10: =IF(L10=0,0,IF(ISNUMBER(C10),L10*C10*AC10,NA())) -> 662.24535 | S10: =IF(M10=0,0,IF(ISNUMBER(D10),M10*D10*AC10,NA())) -> 42.76485 | T10: =IF(N10=0,0,IF(ISNUMBER(E10),N10*E10*AC10,NA())) -> 16.236922 | U10: =IF(O10=0,0,O10*F10) -> 560.32485 | V10: =IF(P10=0,0,-P10*G10) -> 0 | W10: =SUM(Q10:V10) -> 1281.572 | X10: =原始输入与口径!CP10 -> 1281.572 | Y10: =W10-X10 -> 0 | Z10: ="当日执行" -> 当日执行 | AA10: =IF(原始输入与口径!AW10,1,0) -> 1 | AB10: =IF(原始输入与口径!AY10,1,0) -> 1 | AC10: =原始输入与口径!$F$5 -> 0.25 | AD10: =原始输入与口径!CG10 -> 0.3125 | AE10: =原始输入与口径!BQ10 -> 0.13714286 | AF10: =IF(AA10=0,0,AJ10/(AH10*AC10)) -> 0.35289143 | AG10: =IF(AA10=0,0,AK10/(AI10*AC10)) -> 0 | AH10: =IF(ISNUMBER(原始输入与口径!T10),原始输入与口径!T10,"缺失") -> 175 | AI10: =IF(ISNUMBER(原始输入与口径!Y10),原始输入与口径!Y10,"缺失") -> 175 | AJ10: =IF(ISNUMBER(原始输入与口径!AI10),原始输入与口径!AI10,"缺失") -> 15.439 | AK10: =IF(ISNUMBER(原始输入与口径!AL10),原始输入与口径!AL10,"缺失") -> 0 | AL10: =IF(ISNUMBER(原始输入与口径!O10),原始输入与口径!O10,"缺失") -> 131.968 | AM10: =SUMIFS(相位SOC复算!$N$9:$N$929,相位SOC复算!$S$9:$S$929,2) -> 0.0063929607 | AN10: =SUMIFS(相位SOC复算!$Q$9:$Q$929,相位SOC复算!$S$9:$S$929,2) -> 0 | AO10: =SUMIFS(相位SOC复算!$R$9:$R$929,相位SOC复算!$S$9:$S$929,2) -> 2.1173486 | AP10: =相位SOC复算!J12 -> 32.633208 | AQ10: =AP10-J10 -> 0 | AR10: =IF(ISBLANK(原始输入与口径!M10),"",原始输入与口径!M10) -> 5.2473 | AS10: =IF(ISBLANK(原始输入与口径!L10),"",原始输入与口径!L10) -> 46234 | AT10: =IF(ISBLANK(原始输入与口径!A10),"",原始输入与口径!A10) -> 46234.885 | AU10: =IF(ISBLANK(原始输入与口径!I10),"",原始输入与口径!I10) -> 2026-07-31_94 | AV10: =IF(ISBLANK(原始输入与口径!J10),"",原始输入与口径!J10) -> 15 | AW10: =IF(ISBLANK(原始输入与口径!BB10),"",原始输入与口径!BB10) -> OK | AX10: =原始输入与口径!CI10 -> 128 | AY10: =原始输入与口径!BS10 -> 175 | AZ10: =原始输入与口径!BI10 -> 175 | BA10: =原始输入与口径!CM10 -> 40 | BB10: =原始输入与口径!BV10 -> 24 | BC10: =原始输入与口径!BL10 -> 24 | BD10: =46235 -> 46235 | BE10: =IF(K10=0,"零头寸，无结算现金",TEXT(K10,"0.000000")&" MW × "&TEXT(B10,"0.000000")&" × "&TEXT(AC10,"0.000000")&" h = "&TEXT(Q10,"0.000000")&" EUR") -> 零头寸，无结算现金 | BF10: =IF(L10=0,"零头寸，无结算现金",TEXT(L10,"0.000000")&" MW × "&TEXT(C10,"0.000000")&" × "&TEXT(AC10,"0.000000")&" h = "&TEXT(R10,"0.000000")&" EUR") -> 40.000000 MW × 66.224535 × 0.250000 h = 662.245345 EUR | BG10: =IF(M10=0,"零头寸，无结算现金",TEXT(M10,"0.000000")&" MW × "&TEXT(D10,"0.000000")&" × "&TEXT(AC10,"0.000000")&" h = "&TEXT(S10,"0.000000")&" EUR") -> 24.000000 MW × 7.127475 × 0.250000 h = 42.764850 EUR | BH10: =IF(N10=0,"零头寸，无结算现金",TEXT(N10,"0.000000")&" MW × "&TEXT(E10,"0.000000")&" × "&TEXT(AC10,"0.000000")&" h = "&TEXT(T10,"0.000000")&" EUR") -> 24.000000 MW × 2.706154 × 0.250000 h = 16.236922 EUR | BI10: =IF(O10=0,"零上调激活电量",TEXT(O10,"0.000000")&" MWh × "&TEXT(F10,"0.000000")&" = "&TEXT(U10,"0.000000")&" EUR") -> 2.117349 MWh × 264.635146 = 560.324848 EUR | BJ10: =IF(P10=0,"零下调激活电量","−("&TEXT(P10,"0.000000")&" MWh × "&TEXT(G10,"0.000000")&") = "&TEXT(V10,"0.000000")&" EUR") -> 零下调激活电量 | BK10: =TEXT(Q10,"0.000000")&" + "&TEXT(R10,"0.000000")&" + "&TEXT(S10,"0.000000")&" + "&TEXT(T10,"0.000000")&" + "&TEXT(U10,"0.000000")&" + "&TEXT(V10,"0.000000")&" = "&TEXT(W10,"0.000000")&" EUR" -> 0.000000 + 662.245345 + 42.764850 + 16.236922 + 560.324848 + 0.000000 = 1281.571965 EUR
A11: =原始输入与口径!C11 -> 46235.021 | B11: =IF(ISNUMBER(原始输入与口径!H11),原始输入与口径!H11,"缺失") -> 167.36 | C11: =IF(ISNUMBER(原始输入与口径!R11),原始输入与口径!R11,"缺失") -> 66.224535 | D11: =IF(ISNUMBER(原始输入与口径!W11),原始输入与口径!W11,"缺失") -> 7.1274751 | E11: =IF(ISNUMBER(原始输入与口径!AB11),原始输入与口径!AB11,"缺失") -> 2.7061536 | F11: =IF(ISNUMBER(原始输入与口径!AG11),原始输入与口径!AG11,"缺失") -> 422.70215 | G11: =IF(ISNUMBER(原始输入与口径!AJ11),原始输入与口径!AJ11,"缺失") -> 0 | H11: ="未模拟" -> 未模拟 | I11: =原始输入与口径!CD11 -> 32.633208 | J11: =原始输入与口径!CE11 -> 35.143389 | K11: =原始输入与口径!BZ11 -> -24 | L11: =原始输入与口径!CK11 -> 40 | M11: =原始输入与口径!BT11 -> 24 | N11: =原始输入与口径!BJ11 -> 24 | O11: =M11*AF11*AC11 -> 3.2715429 | P11: =N11*AG11*AC11 -> 0 | Q11: =IF(K11=0,0,IF(ISNUMBER(B11),K11*B11*AC11,NA())) -> -1004.16 | R11: =IF(L11=0,0,IF(ISNUMBER(C11),L11*C11*AC11,NA())) -> 662.24535 | S11: =IF(M11=0,0,IF(ISNUMBER(D11),M11*D11*AC11,NA())) -> 42.76485 | T11: =IF(N11=0,0,IF(ISNUMBER(E11),N11*E11*AC11,NA())) -> 16.236922 | U11: =IF(O11=0,0,O11*F11) -> 1382.8882 | V11: =IF(P11=0,0,-P11*G11) -> 0 | W11: =SUM(Q11:V11) -> 1099.9753 | X11: =原始输入与口径!CP11 -> 1099.9753 | Y11: =W11-X11 -> 0 | Z11: ="当日执行" -> 当日执行 | AA11: =IF(原始输入与口径!AW11,1,0) -> 1 | AB11: =IF(原始输入与口径!AY11,1,0) -> 1 | AC11: =原始输入与口径!$F$5 -> 0.25 | AD11: =原始输入与口径!CG11 -> 0.3125 | AE11: =原始输入与口径!BQ11 -> 0.13714286 | AF11: =IF(AA11=0,0,AJ11/(AH11*AC11)) -> 0.54525714 | AG11: =IF(AA11=0,0,AK11/(AI11*AC11)) -> 0 | AH11: =IF(ISNUMBER(原始输入与口径!T11),原始输入与口径!T11,"缺失") -> 175 | AI11: =IF(ISNUMBER(原始输入与口径!Y11),原始输入与口径!Y11,"缺失") -> 175 | AJ11: =IF(ISNUMBER(原始输入与口径!AI11),原始输入与口径!AI11,"缺失") -> 23.855 | AK11: =IF(ISNUMBER(原始输入与口径!AL11),原始输入与口径!AL11,"缺失") -> 0 | AL11: =IF(ISNUMBER(原始输入与口径!O11),原始输入与口径!O11,"缺失") -> 131.968 | AM11: =SUMIFS(相位SOC复算!$N$9:$N$929,相位SOC复算!$S$9:$S$929,3) -> 0.0069727238 | AN11: =SUMIFS(相位SOC复算!$Q$9:$Q$929,相位SOC复算!$S$9:$S$929,3) -> 2.7284571 | AO11: =SUMIFS(相位SOC复算!$R$9:$R$929,相位SOC复算!$S$9:$S$929,3) -> 0 | AP11: =相位SOC复算!J14 -> 35.143389 | AQ11: =AP11-J11 -> 0 | AR11: =IF(ISBLANK(原始输入与口径!M11),"",原始输入与口径!M11) -> 5.2473 | AS11: =IF(ISBLANK(原始输入与口径!L11),"",原始输入与口径!L11) -> 46234 | AT11: =IF(ISBLANK(原始输入与口径!A11),"",原始输入与口径!A11) -> 46234.896 | AU11: =IF(ISBLANK(原始输入与口径!I11),"",原始输入与口径!I11) -> 2026-07-31_95 | AV11: =IF(ISBLANK(原始输入与口径!J11),"",原始输入与口径!J11) -> 15 | AW11: =IF(ISBLANK(原始输入与口径!BB11),"",原始输入与口径!BB11) -> OK | AX11: =原始输入与口径!CI11 -> 128 | AY11: =原始输入与口径!BS11 -> 175 | AZ11: =原始输入与口径!BI11 -> 175 | BA11: =原始输入与口径!CM11 -> 40 | BB11: =原始输入与口径!BV11 -> 24 | BC11: =原始输入与口径!BL11 -> 24 | BD11: =46235 -> 46235 | BE11: =IF(K11=0,"零头寸，无结算现金",TEXT(K11,"0.000000")&" MW × "&TEXT(B11,"0.000000")&" × "&TEXT(AC11,"0.000000")&" h = "&TEXT(Q11,"0.000000")&" EUR") -> -24.000000 MW × 167.360000 × 0.250000 h = -1004.160000 EUR | BF11: =IF(L11=0,"零头寸，无结算现金",TEXT(L11,"0.000000")&" MW × "&TEXT(C11,"0.000000")&" × "&TEXT(AC11,"0.000000")&" h = "&TEXT(R11,"0.000000")&" EUR") -> 40.000000 MW × 66.224535 × 0.250000 h = 662.245345 EUR | BG11: =IF(M11=0,"零头寸，无结算现金",TEXT(M11,"0.000000")&" MW × "&TEXT(D11,"0.000000")&" × "&TEXT(AC11,"0.000000")&" h = "&TEXT(S11,"0.000000")&" EUR") -> 24.000000 MW × 7.127475 × 0.250000 h = 42.764850 EUR | BH11: =IF(N11=0,"零头寸，无结算现金",TEXT(N11,"0.000000")&" MW × "&TEXT(E11,"0.000000")&" × "&TEXT(AC11,"0.000000")&" h = "&TEXT(T11,"0.000000")&" EUR") -> 24.000000 MW × 2.706154 × 0.250000 h = 16.236922 EUR | BI11: =IF(O11=0,"零上调激活电量",TEXT(O11,"0.000000")&" MWh × "&TEXT(F11,"0.000000")&" = "&TEXT(U11,"0.000000")&" EUR") -> 3.271543 MWh × 422.702152 = 1382.888205 EUR | BJ11: =IF(P11=0,"零下调激活电量","−("&TEXT(P11,"0.000000")&" MWh × "&TEXT(G11,"0.000000")&") = "&TEXT(V11,"0.000000")&" EUR") -> 零下调激活电量 | BK11: =TEXT(Q11,"0.000000")&" + "&TEXT(R11,"0.000000")&" + "&TEXT(S11,"0.000000")&" + "&TEXT(T11,"0.000000")&" + "&TEXT(U11,"0.000000")&" + "&TEXT(V11,"0.000000")&" = "&TEXT(W11,"0.000000")&" EUR" -> -1004.160000 + 662.245345 + 42.764850 + 16.236922 + 1382.888205 + 0.000000 = 1099.975322 EUR
A12: =原始输入与口径!C12 -> 46235.031 | B12: =IF(ISNUMBER(原始输入与口径!H12),原始输入与口径!H12,"缺失") -> 165.13 | C12: =IF(ISNUMBER(原始输入与口径!R12),原始输入与口径!R12,"缺失") -> 66.224535 | D12: =IF(ISNUMBER(原始输入与口径!W12),原始输入与口径!W12,"缺失") -> 7.1274751 | E12: =IF(ISNUMBER(原始输入与口径!AB12),原始输入与口径!AB12,"缺失") -> 2.7061536 | F12: =IF(ISNUMBER(原始输入与口径!AG12),原始输入与口径!AG12,"缺失") -> 260.51455 | G12: =IF(ISNUMBER(原始输入与口径!AJ12),原始输入与口径!AJ12,"缺失") -> 76.261125 | H12: ="未模拟" -> 未模拟 | I12: =原始输入与口径!CD12 -> 35.143389 | J12: =原始输入与口径!CE12 -> 38.990356 | K12: =原始输入与口径!BZ12 -> -24 | L12: =原始输入与口径!CK12 -> 40 | M12: =原始输入与口径!BT12 -> 24 | N12: =原始输入与口径!BJ12 -> 24 | O12: =M12*AF12*AC12 -> 1.8865371 | P12: =N12*AG12*AC12 -> 0.068022857 | Q12: =IF(K12=0,0,IF(ISNUMBER(B12),K12*B12*AC12,NA())) -> -990.78 | R12: =IF(L12=0,0,IF(ISNUMBER(C12),L12*C12*AC12,NA())) -> 662.24535 | S12: =IF(M12=0,0,IF(ISNUMBER(D12),M12*D12*AC12,NA())) -> 42.76485 | T12: =IF(N12=0,0,IF(ISNUMBER(E12),N12*E12*AC12,NA())) -> 16.236922 | U12: =IF(O12=0,0,O12*F12) -> 491.47038 | V12: =IF(P12=0,0,-P12*G12) -> -5.1874996 | W12: =SUM(Q12:V12) -> 216.74999 | X12: =原始输入与口径!CP12 -> 216.74999 | Y12: =W12-X12 -> 0 | Z12: ="当日执行" -> 当日执行 | AA12: =IF(原始输入与口径!AW12,1,0) -> 1 | AB12: =IF(原始输入与口径!AY12,1,0) -> 1 | AC12: =原始输入与口径!$F$5 -> 0.25 | AD12: =原始输入与口径!CG12 -> 0.3125 | AE12: =原始输入与口径!BQ12 -> 0.13714286 | AF12: =IF(AA12=0,0,AJ12/(AH12*AC12)) -> 0.31442286 | AG12: =IF(AA12=0,0,AK12/(AI12*AC12)) -> 0.011337143 | AH12: =IF(ISNUMBER(原始输入与口径!T12),原始输入与口径!T12,"缺失") -> 175 | AI12: =IF(ISNUMBER(原始输入与口径!Y12),原始输入与口径!Y12,"缺失") -> 175 | AJ12: =IF(ISNUMBER(原始输入与口径!AI12),原始输入与口径!AI12,"缺失") -> 13.756 | AK12: =IF(ISNUMBER(原始输入与口径!AL12),原始输入与口径!AL12,"缺失") -> 0.496 | AL12: =IF(ISNUMBER(原始输入与口径!O12),原始输入与口径!O12,"缺失") -> 131.968 | AM12: =SUMIFS(相位SOC复算!$N$9:$N$929,相位SOC复算!$S$9:$S$929,4) -> 0.010686019 | AN12: =SUMIFS(相位SOC复算!$Q$9:$Q$929,相位SOC复算!$S$9:$S$929,4) -> 4.1814857 | AO12: =SUMIFS(相位SOC复算!$R$9:$R$929,相位SOC复算!$S$9:$S$929,4) -> 0 | AP12: =相位SOC复算!J17 -> 38.990356 | AQ12: =AP12-J12 -> 0 | AR12: =IF(ISBLANK(原始输入与口径!M12),"",原始输入与口径!M12) -> 5.2473 | AS12: =IF(ISBLANK(原始输入与口径!L12),"",原始输入与口径!L12) -> 46234 | AT12: =IF(ISBLANK(原始输入与口径!A12),"",原始输入与口径!A12) -> 46234.906 | AU12: =IF(ISBLANK(原始输入与口径!I12),"",原始输入与口径!I12) -> 2026-07-31_96 | AV12: =IF(ISBLANK(原始输入与口径!J12),"",原始输入与口径!J12) -> 15 | AW12: =IF(ISBLANK(原始输入与口径!BB12),"",原始输入与口径!BB12) -> OK | AX12: =原始输入与口径!CI12 -> 128 | AY12: =原始输入与口径!BS12 -> 175 | AZ12: =原始输入与口径!BI12 -> 175 | BA12: =原始输入与口径!CM12 -> 40 | BB12: =原始输入与口径!BV12 -> 24 | BC12: =原始输入与口径!BL12 -> 24 | BD12: =46235 -> 46235 | BE12: =IF(K12=0,"零头寸，无结算现金",TEXT(K12,"0.000000")&" MW × "&TEXT(B12,"0.000000")&" × "&TEXT(AC12,"0.000000")&" h = "&TEXT(Q12,"0.000000")&" EUR") -> -24.000000 MW × 165.130000 × 0.250000 h = -990.780000 EUR | BF12: =IF(L12=0,"零头寸，无结算现金",TEXT(L12,"0.000000")&" MW × "&TEXT(C12,"0.000000")&" × "&TEXT(AC12,"0.000000")&" h = "&TEXT(R12,"0.000000")&" EUR") -> 40.000000 MW × 66.224535 × 0.250000 h = 662.245345 EUR | BG12: =IF(M12=0,"零头寸，无结算现金",TEXT(M12,"0.000000")&" MW × "&TEXT(D12,"0.000000")&" × "&TEXT(AC12,"0.000000")&" h = "&TEXT(S12,"0.000000")&" EUR") -> 24.000000 MW × 7.127475 × 0.250000 h = 42.764850 EUR | BH12: =IF(N12=0,"零头寸，无结算现金",TEXT(N12,"0.000000")&" MW × "&TEXT(E12,"0.000000")&" × "&TEXT(AC12,"0.000000")&" h = "&TEXT(T12,"0.000000")&" EUR") -> 24.000000 MW × 2.706154 × 0.250000 h = 16.236922 EUR | BI12: =IF(O12=0,"零上调激活电量",TEXT(O12,"0.000000")&" MWh × "&TEXT(F12,"0.000000")&" = "&TEXT(U12,"0.000000")&" EUR") -> 1.886537 MWh × 260.514550 = 491.470375 EUR | BJ12: =IF(P12=0,"零下调激活电量","−("&TEXT(P12,"0.000000")&" MWh × "&TEXT(G12,"0.000000")&") = "&TEXT(V12,"0.000000")&" EUR") -> −(0.068023 MWh × 76.261125) = -5.187500 EUR | BK12: =TEXT(Q12,"0.000000")&" + "&TEXT(R12,"0.000000")&" + "&TEXT(S12,"0.000000")&" + "&TEXT(T12,"0.000000")&" + "&TEXT(U12,"0.000000")&" + "&TEXT(V12,"0.000000")&" = "&TEXT(W12,"0.000000")&" EUR" -> -990.780000 + 662.245345 + 42.764850 + 16.236922 + 491.470375 + -5.187500 = 216.749993 EUR
A13: =原始输入与口径!C13 -> 46235.042 | B13: =IF(ISNUMBER(原始输入与口径!H13),原始输入与口径!H13,"缺失") -> 184.32 | C13: =IF(ISNUMBER(原始输入与口径!R13),原始输入与口径!R13,"缺失") -> 66.224535 | D13: =IF(ISNUMBER(原始输入与口径!W13),原始输入与口径!W13,"缺失") -> 7.1274751 | E13: =IF(ISNUMBER(原始输入与口径!AB13),原始输入与口径!AB13,"缺失") -> 2.7061536 | F13: =IF(ISNUMBER(原始输入与口径!AG13),原始输入与口径!AG13,"缺失") -> 171.08894 | G13: =IF(ISNUMBER(原始输入与口径!AJ13),原始输入与口径!AJ13,"缺失") -> 74.70947 | H13: ="未模拟" -> 未模拟 | I13: =原始输入与口径!CD13 -> 38.990356 | J13: =原始输入与口径!CE13 -> 33.561199 | K13: =原始输入与口径!BZ13 -> 20.338412 | L13: =原始输入与口径!CK13 -> 40 | M13: =原始输入与口径!BT13 -> 24 | N13: =原始输入与口径!BJ13 -> 24 | O13: =M13*AF13*AC13 -> 0.14660571 | P13: =N13*AG13*AC13 -> 0.24205714 | Q13: =IF(K13=0,0,IF(ISNUMBER(B13),K13*B13*AC13,NA())) -> 937.19403 | R13: =IF(L13=0,0,IF(ISNUMBER(C13),L13*C13*AC13,NA())) -> 662.24535 | S13: =IF(M13=0,0,IF(ISNUMBER(D13),M13*D13*AC13,NA())) -> 42.76485 | T13: =IF(N13=0,0,IF(ISNUMBER(E13),N13*E13*AC13,NA())) -> 16.236922 | U13: =IF(O13=0,0,O13*F13) -> 25.082616 | V13: =IF(P13=0,0,-P13*G13) -> -18.083961 | W13: =SUM(Q13:V13) -> 1665.4398 | X13: =原始输入与口径!CP13 -> 1665.4398 | Y13: =W13-X13 -> 0 | Z13: ="当日执行" -> 当日执行 | AA13: =IF(原始输入与口径!AW13,1,0) -> 1 | AB13: =IF(原始输入与口径!AY13,1,0) -> 1 | AC13: =原始输入与口径!$F$5 -> 0.25 | AD13: =原始输入与口径!CG13 -> 0.3125 | AE13: =原始输入与口径!BQ13 -> 0.13714286 | AF13: =IF(AA13=0,0,AJ13/(AH13*AC13)) -> 0.024434286 | AG13: =IF(AA13=0,0,AK13/(AI13*AC13)) -> 0.040342857 | AH13: =IF(ISNUMBER(原始输入与口径!T13),原始输入与口径!T13,"缺失") -> 175 | AI13: =IF(ISNUMBER(原始输入与口径!Y13),原始输入与口径!Y13,"缺失") -> 175 | AJ13: =IF(ISNUMBER(原始输入与口径!AI13),原始输入与口径!AI13,"缺失") -> 1.069 | AK13: =IF(ISNUMBER(原始输入与口径!AL13),原始输入与口径!AL13,"缺失") -> 1.765 | AL13: =IF(ISNUMBER(原始输入与口径!O13),原始输入与口径!O13,"缺失") -> 128 | AM13: =SUMIFS(相位SOC复算!$N$9:$N$929,相位SOC复算!$S$9:$S$929,5) -> 0.015269742 | AN13: =SUMIFS(相位SOC复算!$Q$9:$Q$929,相位SOC复算!$S$9:$S$929,5) -> 0.036929729 | AO13: =SUMIFS(相位SOC复算!$R$9:$R$929,相位SOC复算!$S$9:$S$929,5) -> 5.0260813 | AP13: =相位SOC复算!J20 -> 33.561199 | AQ13: =AP13-J13 -> 0 | AR13: =IF(ISBLANK(原始输入与口径!M13),"",原始输入与口径!M13) -> 5.2473 | AS13: =IF(ISBLANK(原始输入与口径!L13),"",原始输入与口径!L13) -> 46234 | AT13: =IF(ISBLANK(原始输入与口径!A13),"",原始输入与口径!A13) -> 46234.917 | AU13: =IF(ISBLANK(原始输入与口径!I13),"",原始输入与口径!I13) -> 2026-08-01_1 | AV13: =IF(ISBLANK(原始输入与口径!J13),"",原始输入与口径!J13) -> 15 | AW13: =IF(ISBLANK(原始输入与口径!BB13),"",原始输入与口径!BB13) -> OK | AX13: =原始输入与口径!CI13 -> 128 | AY13: =原始输入与口径!BS13 -> 175 | AZ13: =原始输入与口径!BI13 -> 175 | BA13: =原始输入与口径!CM13 -> 40 | BB13: =原始输入与口径!BV13 -> 24 | BC13: =原始输入与口径!BL13 -> 24 | BD13: =46235 -> 46235 | BE13: =IF(K13=0,"零头寸，无结算现金",TEXT(K13,"0.000000")&" MW × "&TEXT(B13,"0.000000")&" × "&TEXT(AC13,"0.000000")&" h = "&TEXT(Q13,"0.000000")&" EUR") -> 20.338412 MW × 184.320000 × 0.250000 h = 937.194033 EUR | BF13: =IF(L13=0,"零头寸，无结算现金",TEXT(L13,"0.000000")&" MW × "&TEXT(C13,"0.000000")&" × "&TEXT(AC13,"0.000000")&" h = "&TEXT(R13,"0.000000")&" EUR") -> 40.000000 MW × 66.224535 × 0.250000 h = 662.245345 EUR | BG13: =IF(M13=0,"零头寸，无结算现金",TEXT(M13,"0.000000")&" MW × "&TEXT(D13,"0.000000")&" × "&TEXT(AC13,"0.000000")&" h = "&TEXT(S13,"0.000000")&" EUR") -> 24.000000 MW × 7.127475 × 0.250000 h = 42.764850 EUR | BH13: =IF(N13=0,"零头寸，无结算现金",TEXT(N13,"0.000000")&" MW × "&TEXT(E13,"0.000000")&" × "&TEXT(AC13,"0.000000")&" h = "&TEXT(T13,"0.000000")&" EUR") -> 24.000000 MW × 2.706154 × 0.250000 h = 16.236922 EUR | BI13: =IF(O13=0,"零上调激活电量",TEXT(O13,"0.000000")&" MWh × "&TEXT(F13,"0.000000")&" = "&TEXT(U13,"0.000000")&" EUR") -> 0.146606 MWh × 171.088941 = 25.082616 EUR | BJ13: =IF(P13=0,"零下调激活电量","−("&TEXT(P13,"0.000000")&" MWh × "&TEXT(G13,"0.000000")&") = "&TEXT(V13,"0.000000")&" EUR") -> −(0.242057 MWh × 74.709470) = -18.083961 EUR | BK13: =TEXT(Q13,"0.000000")&" + "&TEXT(R13,"0.000000")&" + "&TEXT(S13,"0.000000")&" + "&TEXT(T13,"0.000000")&" + "&TEXT(U13,"0.000000")&" + "&TEXT(V13,"0.000000")&" = "&TEXT(W13,"0.000000")&" EUR" -> 937.194033 + 662.245345 + 42.764850 + 16.236922 + 25.082616 + -18.083961 = 1665.439807 EUR
A14: =原始输入与口径!C14 -> 46235.052 | B14: =IF(ISNUMBER(原始输入与口径!H14),原始输入与口径!H14,"缺失") -> 174.23 | C14: =IF(ISNUMBER(原始输入与口径!R14),原始输入与口径!R14,"缺失") -> 66.224535 | D14: =IF(ISNUMBER(原始输入与口径!W14),原始输入与口径!W14,"缺失") -> 7.1274751 | E14: =IF(ISNUMBER(原始输入与口径!AB14),原始输入与口径!AB14,"缺失") -> 2.7061536 | F14: =IF(ISNUMBER(原始输入与口径!AG14),原始输入与口径!AG14,"缺失") -> 190.53685 | G14: =IF(ISNUMBER(原始输入与口径!AJ14),原始输入与口径!AJ14,"缺失") -> 0 | H14: ="未模拟" -> 未模拟 | I14: =原始输入与口径!CD14 -> 33.561199 | J14: =原始输入与口径!CE14 -> 32.71941 | K14: =原始输入与口径!BZ14 -> 0 | L14: =原始输入与口径!CK14 -> 40 | M14: =原始输入与口径!BT14 -> 24 | N14: =原始输入与口径!BJ14 -> 24 | O14: =M14*AF14*AC14 -> 0.77444571 | P14: =N14*AG14*AC14 -> 0 | Q14: =IF(K14=0,0,IF(ISNUMBER(B14),K14*B14*AC14,NA())) -> 0 | R14: =IF(L14=0,0,IF(ISNUMBER(C14),L14*C14*AC14,NA())) -> 662.24535 | S14: =IF(M14=0,0,IF(ISNUMBER(D14),M14*D14*AC14,NA())) -> 42.76485 | T14: =IF(N14=0,0,IF(ISNUMBER(E14),N14*E14*AC14,NA())) -> 16.236922 | U14: =IF(O14=0,0,O14*F14) -> 147.56044 | V14: =IF(P14=0,0,-P14*G14) -> 0 | W14: =SUM(Q14:V14) -> 868.80756 | X14: =原始输入与口径!CP14 -> 868.80756 | Y14: =W14-X14 -> 0 | Z14: ="当日执行" -> 当日执行 | AA14: =IF(原始输入与口径!AW14,1,0) -> 1 | AB14: =IF(原始输入与口径!AY14,1,0) -> 1 | AC14: =原始输入与口径!$F$5 -> 0.25 | AD14: =原始输入与口径!CG14 -> 0.3125 | AE14: =原始输入与口径!BQ14 -> 0.13714286 | AF14: =IF(AA14=0,0,AJ14/(AH14*AC14)) -> 0.12907429 | AG14: =IF(AA14=0,0,AK14/(AI14*AC14)) -> 0 | AH14: =IF(ISNUMBER(原始输入与口径!T14),原始输入与口径!T14,"缺失") -> 175 | AI14: =IF(ISNUMBER(原始输入与口径!Y14),原始输入与口径!Y14,"缺失") -> 175 | AJ14: =IF(ISNUMBER(原始输入与口径!AI14),原始输入与口径!AI14,"缺失") -> 5.647 | AK14: =IF(ISNUMBER(原始输入与口径!AL14),原始输入与口径!AL14,"缺失") -> 0 | AL14: =IF(ISNUMBER(原始输入与口径!O14),原始输入与口径!O14,"缺失") -> 128 | AM14: =SUMIFS(相位SOC复算!$N$9:$N$929,相位SOC复算!$S$9:$S$929,6) -> 0.0023383023 | AN14: =SUMIFS(相位SOC复算!$Q$9:$Q$929,相位SOC复算!$S$9:$S$929,6) -> 0 | AO14: =SUMIFS(相位SOC复算!$R$9:$R$929,相位SOC复算!$S$9:$S$929,6) -> 0.77444571 | AP14: =相位SOC复算!J22 -> 32.71941 | AQ14: =AP14-J14 -> 0 | AR14: =IF(ISBLANK(原始输入与口径!M14),"",原始输入与口径!M14) -> 5.2473 | AS14: =IF(ISBLANK(原始输入与口径!L14),"",原始输入与口径!L14) -> 46234 | AT14: =IF(ISBLANK(原始输入与口径!A14),"",原始输入与口径!A14) -> 46234.927 | AU14: =IF(ISBLANK(原始输入与口径!I14),"",原始输入与口径!I14) -> 2026-08-01_2 | AV14: =IF(ISBLANK(原始输入与口径!J14),"",原始输入与口径!J14) -> 15 | AW14: =IF(ISBLANK(原始输入与口径!BB14),"",原始输入与口径!BB14) -> OK | AX14: =原始输入与口径!CI14 -> 128 | AY14: =原始输入与口径!BS14 -> 175 | AZ14: =原始输入与口径!BI14 -> 175 | BA14: =原始输入与口径!CM14 -> 40 | BB14: =原始输入与口径!BV14 -> 24 | BC14: =原始输入与口径!BL14 -> 24 | BD14: =46235 -> 46235 | BE14: =IF(K14=0,"零头寸，无结算现金",TEXT(K14,"0.000000")&" MW × "&TEXT(B14,"0.000000")&" × "&TEXT(AC14,"0.000000")&" h = "&TEXT(Q14,"0.000000")&" EUR") -> 零头寸，无结算现金 | BF14: =IF(L14=0,"零头寸，无结算现金",TEXT(L14,"0.000000")&" MW × "&TEXT(C14,"0.000000")&" × "&TEXT(AC14,"0.000000")&" h = "&TEXT(R14,"0.000000")&" EUR") -> 40.000000 MW × 66.224535 × 0.250000 h = 662.245345 EUR | BG14: =IF(M14=0,"零头寸，无结算现金",TEXT(M14,"0.000000")&" MW × "&TEXT(D14,"0.000000")&" × "&TEXT(AC14,"0.000000")&" h = "&TEXT(S14,"0.000000")&" EUR") -> 24.000000 MW × 7.127475 × 0.250000 h = 42.764850 EUR | BH14: =IF(N14=0,"零头寸，无结算现金",TEXT(N14,"0.000000")&" MW × "&TEXT(E14,"0.000000")&" × "&TEXT(AC14,"0.000000")&" h = "&TEXT(T14,"0.000000")&" EUR") -> 24.000000 MW × 2.706154 × 0.250000 h = 16.236922 EUR | BI14: =IF(O14=0,"零上调激活电量",TEXT(O14,"0.000000")&" MWh × "&TEXT(F14,"0.000000")&" = "&TEXT(U14,"0.000000")&" EUR") -> 0.774446 MWh × 190.536848 = 147.560445 EUR | BJ14: =IF(P14=0,"零下调激活电量","−("&TEXT(P14,"0.000000")&" MWh × "&TEXT(G14,"0.000000")&") = "&TEXT(V14,"0.000000")&" EUR") -> 零下调激活电量 | BK14: =TEXT(Q14,"0.000000")&" + "&TEXT(R14,"0.000000")&" + "&TEXT(S14,"0.000000")&" + "&TEXT(T14,"0.000000")&" + "&TEXT(U14,"0.000000")&" + "&TEXT(V14,"0.000000")&" = "&TEXT(W14,"0.000000")&" EUR" -> 0.000000 + 662.245345 + 42.764850 + 16.236922 + 147.560445 + 0.000000 = 868.807563 EUR
A15: =原始输入与口径!C15 -> 46235.062 | B15: =IF(ISNUMBER(原始输入与口径!H15),原始输入与口径!H15,"缺失") -> 165.3 | C15: =IF(ISNUMBER(原始输入与口径!R15),原始输入与口径!R15,"缺失") -> 66.224535 | D15: =IF(ISNUMBER(原始输入与口径!W15),原始输入与口径!W15,"缺失") -> 7.1274751 | E15: =IF(ISNUMBER(原始输入与口径!AB15),原始输入与口径!AB15,"缺失") -> 2.7061536 | F15: =IF(ISNUMBER(原始输入与口径!AG15),原始输入与口径!AG15,"缺失") -> 181.55185 | G15: =IF(ISNUMBER(原始输入与口径!AJ15),原始输入与口径!AJ15,"缺失") -> 0 | H15: ="未模拟" -> 未模拟 | I15: =原始输入与口径!CD15 -> 32.71941 | J15: =原始输入与口径!CE15 -> 31.771336 | K15: =原始输入与口径!BZ15 -> 0 | L15: =原始输入与口径!CK15 -> 40 | M15: =原始输入与口径!BT15 -> 24 | N15: =原始输入与口径!BJ15 -> 24 | O15: =M15*AF15*AC15 -> 0.87222857 | P15: =N15*AG15*AC15 -> 0 | Q15: =IF(K15=0,0,IF(ISNUMBER(B15),K15*B15*AC15,NA())) -> 0 | R15: =IF(L15=0,0,IF(ISNUMBER(C15),L15*C15*AC15,NA())) -> 662.24535 | S15: =IF(M15=0,0,IF(ISNUMBER(D15),M15*D15*AC15,NA())) -> 42.76485 | T15: =IF(N15=0,0,IF(ISNUMBER(E15),N15*E15*AC15,NA())) -> 16.236922 | U15: =IF(O15=0,0,O15*F15) -> 158.35471 | V15: =IF(P15=0,0,-P15*G15) -> 0 | W15: =SUM(Q15:V15) -> 879.60182 | X15: =原始输入与口径!CP15 -> 879.60182 | Y15: =W15-X15 -> 0 | Z15: ="当日执行" -> 当日执行 | AA15: =IF(原始输入与口径!AW15,1,0) -> 1 | AB15: =IF(原始输入与口径!AY15,1,0) -> 1 | AC15: =原始输入与口径!$F$5 -> 0.25 | AD15: =原始输入与口径!CG15 -> 0.3125 | AE15: =原始输入与口径!BQ15 -> 0.13714286 | AF15: =IF(AA15=0,0,AJ15/(AH15*AC15)) -> 0.14537143 | AG15: =IF(AA15=0,0,AK15/(AI15*AC15)) -> 0 | AH15: =IF(ISNUMBER(原始输入与口径!T15),原始输入与口径!T15,"缺失") -> 175 | AI15: =IF(ISNUMBER(原始输入与口径!Y15),原始输入与口径!Y15,"缺失") -> 175 | AJ15: =IF(ISNUMBER(原始输入与口径!AI15),原始输入与口径!AI15,"缺失") -> 6.36 | AK15: =IF(ISNUMBER(原始输入与口径!AL15),原始输入与口径!AL15,"缺失") -> 0 | AL15: =IF(ISNUMBER(原始输入与口径!O15),原始输入与口径!O15,"缺失") -> 128 | AM15: =SUMIFS(相位SOC复算!$N$9:$N$929,相位SOC复算!$S$9:$S$929,7) -> 0.0026335404 | AN15: =SUMIFS(相位SOC复算!$Q$9:$Q$929,相位SOC复算!$S$9:$S$929,7) -> 0 | AO15: =SUMIFS(相位SOC复算!$R$9:$R$929,相位SOC复算!$S$9:$S$929,7) -> 0.87222857 | AP15: =相位SOC复算!J24 -> 31.771336 | AQ15: =AP15-J15 -> 0 | AR15: =IF(ISBLANK(原始输入与口径!M15),"",原始输入与口径!M15) -> 5.2473 | AS15: =IF(ISBLANK(原始输入与口径!L15),"",原始输入与口径!L15) -> 46234 | AT15: =IF(ISBLANK(原始输入与口径!A15),"",原始输入与口径!A15) -> 46234.938 | AU15: =IF(ISBLANK(原始输入与口径!I15),"",原始输入与口径!I15) -> 2026-08-01_3 | AV15: =IF(ISBLANK(原始输入与口径!J15),"",原始输入与口径!J15) -> 15 | AW15: =IF(ISBLANK(原始输入与口径!BB15),"",原始输入与口径!BB15) -> OK | AX15: =原始输入与口径!CI15 -> 128 | AY15: =原始输入与口径!BS15 -> 175 | AZ15: =原始输入与口径!BI15 -> 175 | BA15: =原始输入与口径!CM15 -> 40 | BB15: =原始输入与口径!BV15 -> 24 | BC15: =原始输入与口径!BL15 -> 24 | BD15: =46235 -> 46235 | BE15: =IF(K15=0,"零头寸，无结算现金",TEXT(K15,"0.000000")&" MW × "&TEXT(B15,"0.000000")&" × "&TEXT(AC15,"0.000000")&" h = "&TEXT(Q15,"0.000000")&" EUR") -> 零头寸，无结算现金 | BF15: =IF(L15=0,"零头寸，无结算现金",TEXT(L15,"0.000000")&" MW × "&TEXT(C15,"0.000000")&" × "&TEXT(AC15,"0.000000")&" h = "&TEXT(R15,"0.000000")&" EUR") -> 40.000000 MW × 66.224535 × 0.250000 h = 662.245345 EUR | BG15: =IF(M15=0,"零头寸，无结算现金",TEXT(M15,"0.000000")&" MW × "&TEXT(D15,"0.000000")&" × "&TEXT(AC15,"0.000000")&" h = "&TEXT(S15,"0.000000")&" EUR") -> 24.000000 MW × 7.127475 × 0.250000 h = 42.764850 EUR | BH15: =IF(N15=0,"零头寸，无结算现金",TEXT(N15,"0.000000")&" MW × "&TEXT(E15,"0.000000")&" × "&TEXT(AC15,"0.000000")&" h = "&TEXT(T15,"0.000000")&" EUR") -> 24.000000 MW × 2.706154 × 0.250000 h = 16.236922 EUR | BI15: =IF(O15=0,"零上调激活电量",TEXT(O15,"0.000000")&" MWh × "&TEXT(F15,"0.000000")&" = "&TEXT(U15,"0.000000")&" EUR") -> 0.872229 MWh × 181.551846 = 158.354707 EUR | BJ15: =IF(P15=0,"零下调激活电量","−("&TEXT(P15,"0.000000")&" MWh × "&TEXT(G15,"0.000000")&") = "&TEXT(V15,"0.000000")&" EUR") -> 零下调激活电量 | BK15: =TEXT(Q15,"0.000000")&" + "&TEXT(R15,"0.000000")&" + "&TEXT(S15,"0.000000")&" + "&TEXT(T15,"0.000000")&" + "&TEXT(U15,"0.000000")&" + "&TEXT(V15,"0.000000")&" = "&TEXT(W15,"0.000000")&" EUR" -> 0.000000 + 662.245345 + 42.764850 + 16.236922 + 158.354707 + 0.000000 = 879.601825 EUR
A16: =原始输入与口径!C16 -> 46235.073 | B16: =IF(ISNUMBER(原始输入与口径!H16),原始输入与口径!H16,"缺失") -> 157.23 | C16: =IF(ISNUMBER(原始输入与口径!R16),原始输入与口径!R16,"缺失") -> 66.224535 | D16: =IF(ISNUMBER(原始输入与口径!W16),原始输入与口径!W16,"缺失") -> 7.1274751 | E16: =IF(ISNUMBER(原始输入与口径!AB16),原始输入与口径!AB16,"缺失") -> 2.7061536 | F16: =IF(ISNUMBER(原始输入与口径!AG16),原始输入与口径!AG16,"缺失") -> 190.08785 | G16: =IF(ISNUMBER(原始输入与口径!AJ16),原始输入与口径!AJ16,"缺失") -> 0 | H16: ="未模拟" -> 未模拟 | I16: =原始输入与口径!CD16 -> 31.771336 | J16: =原始输入与口径!CE16 -> 36.483965 | K16: =原始输入与口径!BZ16 -> -24 | L16: =原始输入与口径!CK16 -> 40 | M16: =原始输入与口径!BT16 -> 24 | N16: =原始输入与口径!BJ16 -> 24 | O16: =M16*AF16*AC16 -> 0.87757714 | P16: =N16*AG16*AC16 -> 0 | Q16: =IF(K16=0,0,IF(ISNUMBER(B16),K16*B16*AC16,NA())) -> -943.38 | R16: =IF(L16=0,0,IF(ISNUMBER(C16),L16*C16*AC16,NA())) -> 662.24535 | S16: =IF(M16=0,0,IF(ISNUMBER(D16),M16*D16*AC16,NA())) -> 42.76485 | T16: =IF(N16=0,0,IF(ISNUMBER(E16),N16*E16*AC16,NA())) -> 16.236922 | U16: =IF(O16=0,0,O16*F16) -> 166.81676 | V16: =IF(P16=0,0,-P16*G16) -> 0 | W16: =SUM(Q16:V16) -> -55.316126 | X16: =原始输入与口径!CP16 -> -55.316126 | Y16: =W16-X16 -> 0 | Z16: ="当日执行" -> 当日执行 | AA16: =IF(原始输入与口径!AW16,1,0) -> 1 | AB16: =IF(原始输入与口径!AY16,1,0) -> 1 | AC16: =原始输入与口径!$F$5 -> 0.25 | AD16: =原始输入与口径!CG16 -> 0.3125 | AE16: =原始输入与口径!BQ16 -> 0.13714286 | AF16: =IF(AA16=0,0,AJ16/(AH16*AC16)) -> 0.14626286 | AG16: =IF(AA16=0,0,AK16/(AI16*AC16)) -> 0 | AH16: =IF(ISNUMBER(原始输入与口径!T16),原始输入与口径!T16,"缺失") -> 175 | AI16: =IF(ISNUMBER(原始输入与口径!Y16),原始输入与口径!Y16,"缺失") -> 175 | AJ16: =IF(ISNUMBER(原始输入与口径!AI16),原始输入与口径!AI16,"缺失") -> 6.399 | AK16: =IF(ISNUMBER(原始输入与口径!AL16),原始输入与口径!AL16,"缺失") -> 0 | AL16: =IF(ISNUMBER(原始输入与口径!O16),原始输入与口径!O16,"缺失") -> 128 | AM16: =SUMIFS(相位SOC复算!$N$9:$N$929,相位SOC复算!$S$9:$S$929,8) -> 0.013090636 | AN16: =SUMIFS(相位SOC复算!$Q$9:$Q$929,相位SOC复算!$S$9:$S$929,8) -> 5.1224229 | AO16: =SUMIFS(相位SOC复算!$R$9:$R$929,相位SOC复算!$S$9:$S$929,8) -> 0 | AP16: =相位SOC复算!J26 -> 36.483965 | AQ16: =AP16-J16 -> 0 | AR16: =IF(ISBLANK(原始输入与口径!M16),"",原始输入与口径!M16) -> 5.2473 | AS16: =IF(ISBLANK(原始输入与口径!L16),"",原始输入与口径!L16) -> 46234 | AT16: =IF(ISBLANK(原始输入与口径!A16),"",原始输入与口径!A16) -> 46234.948 | AU16: =IF(ISBLANK(原始输入与口径!I16),"",原始输入与口径!I16) -> 2026-08-01_4 | AV16: =IF(ISBLANK(原始输入与口径!J16),"",原始输入与口径!J16) -> 15 | AW16: =IF(ISBLANK(原始输入与口径!BB16),"",原始输入与口径!BB16) -> OK | AX16: =原始输入与口径!CI16 -> 128 | AY16: =原始输入与口径!BS16 -> 175 | AZ16: =原始输入与口径!BI16 -> 175 | BA16: =原始输入与口径!CM16 -> 40 | BB16: =原始输入与口径!BV16 -> 24 | BC16: =原始输入与口径!BL16 -> 24 | BD16: =46235 -> 46235 | BE16: =IF(K16=0,"零头寸，无结算现金",TEXT(K16,"0.000000")&" MW × "&TEXT(B16,"0.000000")&" × "&TEXT(AC16,"0.000000")&" h = "&TEXT(Q16,"0.000000")&" EUR") -> -24.000000 MW × 157.230000 × 0.250000 h = -943.380000 EUR | BF16: =IF(L16=0,"零头寸，无结算现金",TEXT(L16,"0.000000")&" MW × "&TEXT(C16,"0.000000")&" × "&TEXT(AC16,"0.000000")&" h = "&TEXT(R16,"0.000000")&" EUR") -> 40.000000 MW × 66.224535 × 0.250000 h = 662.245345 EUR | BG16: =IF(M16=0,"零头寸，无结算现金",TEXT(M16,"0.000000")&" MW × "&TEXT(D16,"0.000000")&" × "&TEXT(AC16,"0.000000")&" h = "&TEXT(S16,"0.000000")&" EUR") -> 24.000000 MW × 7.127475 × 0.250000 h = 42.764850 EUR | BH16: =IF(N16=0,"零头寸，无结算现金",TEXT(N16,"0.000000")&" MW × "&TEXT(E16,"0.000000")&" × "&TEXT(AC16,"0.000000")&" h = "&TEXT(T16,"0.000000")&" EUR") -> 24.000000 MW × 2.706154 × 0.250000 h = 16.236922 EUR | BI16: =IF(O16=0,"零上调激活电量",TEXT(O16,"0.000000")&" MWh × "&TEXT(F16,"0.000000")&" = "&TEXT(U16,"0.000000")&" EUR") -> 0.877577 MWh × 190.087855 = 166.816756 EUR | BJ16: =IF(P16=0,"零下调激活电量","−("&TEXT(P16,"0.000000")&" MWh × "&TEXT(G16,"0.000000")&") = "&TEXT(V16,"0.000000")&" EUR") -> 零下调激活电量 | BK16: =TEXT(Q16,"0.000000")&" + "&TEXT(R16,"0.000000")&" + "&TEXT(S16,"0.000000")&" + "&TEXT(T16,"0.000000")&" + "&TEXT(U16,"0.000000")&" + "&TEXT(V16,"0.000000")&" = "&TEXT(W16,"0.000000")&" EUR" -> -943.380000 + 662.245345 + 42.764850 + 16.236922 + 166.816756 + 0.000000 = -55.316126 EUR
A17: =原始输入与口径!C17 -> 46235.083 | B17: =IF(ISNUMBER(原始输入与口径!H17),原始输入与口径!H17,"缺失") -> 170.44 | C17: =IF(ISNUMBER(原始输入与口径!R17),原始输入与口径!R17,"缺失") -> 66.224535 | D17: =IF(ISNUMBER(原始输入与口径!W17),原始输入与口径!W17,"缺失") -> 7.1274751 | E17: =IF(ISNUMBER(原始输入与口径!AB17),原始输入与口径!AB17,"缺失") -> 2.7061536 | F17: =IF(ISNUMBER(原始输入与口径!AG17),原始输入与口径!AG17,"缺失") -> 227.42973 | G17: =IF(ISNUMBER(原始输入与口径!AJ17),原始输入与口径!AJ17,"缺失") -> 0 | H17: ="未模拟" -> 未模拟 | I17: =原始输入与口径!CD17 -> 36.483965 | J17: =原始输入与口径!CE17 -> 34.278648 | K17: =原始输入与口径!BZ17 -> 0 | L17: =原始输入与口径!CK17 -> 40 | M17: =原始输入与口径!BT17 -> 24 | N17: =原始输入与口径!BJ17 -> 24 | O17: =M17*AF17*AC17 -> 2.0288914 | P17: =N17*AG17*AC17 -> 0 | Q17: =IF(K17=0,0,IF(ISNUMBER(B17),K17*B17*AC17,NA())) -> 0 | R17: =IF(L17=0,0,IF(ISNUMBER(C17),L17*C17*AC17,NA())) -> 662.24535 | S17: =IF(M17=0,0,IF(ISNUMBER(D17),M17*D17*AC17,NA())) -> 42.76485 | T17: =IF(N17=0,0,IF(ISNUMBER(E17),N17*E17*AC17,NA())) -> 16.236922 | U17: =IF(O17=0,0,O17*F17) -> 461.43022 | V17: =IF(P17=0,0,-P17*G17) -> 0 | W17: =SUM(Q17:V17) -> 1182.6773 | X17: =原始输入与口径!CP17 -> 1182.6773 | Y17: =W17-X17 -> 0 | Z17: ="当日执行" -> 当日执行 | AA17: =IF(原始输入与口径!AW17,1,0) -> 1 | AB17: =IF(原始输入与口径!AY17,1,0) -> 1 | AC17: =原始输入与口径!$F$5 -> 0.25 | AD17: =原始输入与口径!CG17 -> 0.3125 | AE17: =原始输入与口径!BQ17 -> 0.13714286 | AF17: =IF(AA17=0,0,AJ17/(AH17*AC17)) -> 0.33814857 | AG17: =IF(AA17=0,0,AK17/(AI17*AC17)) -> 0 | AH17: =IF(ISNUMBER(原始输入与口径!T17),原始输入与口径!T17,"缺失") -> 175 | AI17: =IF(ISNUMBER(原始输入与口径!Y17),原始输入与口径!Y17,"缺失") -> 175 | AJ17: =IF(ISNUMBER(原始输入与口径!AI17),原始输入与口径!AI17,"缺失") -> 14.794 | AK17: =IF(ISNUMBER(原始输入与口径!AL17),原始输入与口径!AL17,"缺失") -> 0 | AL17: =IF(ISNUMBER(原始输入与口径!O17),原始输入与口径!O17,"缺失") -> 128 | AM17: =SUMIFS(相位SOC复算!$N$9:$N$929,相位SOC复算!$S$9:$S$929,9) -> 0.0061258799 | AN17: =SUMIFS(相位SOC复算!$Q$9:$Q$929,相位SOC复算!$S$9:$S$929,9) -> 0 | AO17: =SUMIFS(相位SOC复算!$R$9:$R$929,相位SOC复算!$S$9:$S$929,9) -> 2.0288914 | AP17: =相位SOC复算!J28 -> 34.278648 | AQ17: =AP17-J17 -> 0 | AR17: =IF(ISBLANK(原始输入与口径!M17),"",原始输入与口径!M17) -> 5.2473 | AS17: =IF(ISBLANK(原始输入与口径!L17),"",原始输入与口径!L17) -> 46234 | AT17: =IF(ISBLANK(原始输入与口径!A17),"",原始输入与口径!A17) -> 46234.958 | AU17: =IF(ISBLANK(原始输入与口径!I17),"",原始输入与口径!I17) -> 2026-08-01_5 | AV17: =IF(ISBLANK(原始输入与口径!J17),"",原始输入与口径!J17) -> 15 | AW17: =IF(ISBLANK(原始输入与口径!BB17),"",原始输入与口径!BB17) -> OK | AX17: =原始输入与口径!CI17 -> 128 | AY17: =原始输入与口径!BS17 -> 175 | AZ17: =原始输入与口径!BI17 -> 175 | BA17: =原始输入与口径!CM17 -> 40 | BB17: =原始输入与口径!BV17 -> 24 | BC17: =原始输入与口径!BL17 -> 24 | BD17: =46235 -> 46235 | BE17: =IF(K17=0,"零头寸，无结算现金",TEXT(K17,"0.000000")&" MW × "&TEXT(B17,"0.000000")&" × "&TEXT(AC17,"0.000000")&" h = "&TEXT(Q17,"0.000000")&" EUR") -> 零头寸，无结算现金 | BF17: =IF(L17=0,"零头寸，无结算现金",TEXT(L17,"0.000000")&" MW × "&TEXT(C17,"0.000000")&" × "&TEXT(AC17,"0.000000")&" h = "&TEXT(R17,"0.000000")&" EUR") -> 40.000000 MW × 66.224535 × 0.250000 h = 662.245345 EUR | BG17: =IF(M17=0,"零头寸，无结算现金",TEXT(M17,"0.000000")&" MW × "&TEXT(D17,"0.000000")&" × "&TEXT(AC17,"0.000000")&" h = "&TEXT(S17,"0.000000")&" EUR") -> 24.000000 MW × 7.127475 × 0.250000 h = 42.764850 EUR | BH17: =IF(N17=0,"零头寸，无结算现金",TEXT(N17,"0.000000")&" MW × "&TEXT(E17,"0.000000")&" × "&TEXT(AC17,"0.000000")&" h = "&TEXT(T17,"0.000000")&" EUR") -> 24.000000 MW × 2.706154 × 0.250000 h = 16.236922 EUR | BI17: =IF(O17=0,"零上调激活电量",TEXT(O17,"0.000000")&" MWh × "&TEXT(F17,"0.000000")&" = "&TEXT(U17,"0.000000")&" EUR") -> 2.028891 MWh × 227.429726 = 461.430221 EUR | BJ17: =IF(P17=0,"零下调激活电量","−("&TEXT(P17,"0.000000")&" MWh × "&TEXT(G17,"0.000000")&") = "&TEXT(V17,"0.000000")&" EUR") -> 零下调激活电量 | BK17: =TEXT(Q17,"0.000000")&" + "&TEXT(R17,"0.000000")&" + "&TEXT(S17,"0.000000")&" + "&TEXT(T17,"0.000000")&" + "&TEXT(U17,"0.000000")&" + "&TEXT(V17,"0.000000")&" = "&TEXT(W17,"0.000000")&" EUR" -> 0.000000 + 662.245345 + 42.764850 + 16.236922 + 461.430221 + 0.000000 = 1182.677339 EUR
A18: =原始输入与口径!C18 -> 46235.094 | B18: =IF(ISNUMBER(原始输入与口径!H18),原始输入与口径!H18,"缺失") -> 169.42 | C18: =IF(ISNUMBER(原始输入与口径!R18),原始输入与口径!R18,"缺失") -> 66.224535 | D18: =IF(ISNUMBER(原始输入与口径!W18),原始输入与口径!W18,"缺失") -> 7.1274751 | E18: =IF(ISNUMBER(原始输入与口径!AB18),原始输入与口径!AB18,"缺失") -> 2.7061536 | F18: =IF(ISNUMBER(原始输入与口径!AG18),原始输入与口径!AG18,"缺失") -> 236.08846 | G18: =IF(ISNUMBER(原始输入与口径!AJ18),原始输入与口径!AJ18,"缺失") -> 0 | H18: ="未模拟" -> 未模拟 | I18: =原始输入与口径!CD18 -> 34.278648 | J18: =原始输入与口径!CE18 -> 31.993431 | K18: =原始输入与口径!BZ18 -> 0 | L18: =原始输入与口径!CK18 -> 40 | M18: =原始输入与口径!BT18 -> 24 | N18: =原始输入与口径!BJ18 -> 24 | O18: =M18*AF18*AC18 -> 2.1024 | P18: =N18*AG18*AC18 -> 0 | Q18: =IF(K18=0,0,IF(ISNUMBER(B18),K18*B18*AC18,NA())) -> 0 | R18: =IF(L18=0,0,IF(ISNUMBER(C18),L18*C18*AC18,NA())) -> 662.24535 | S18: =IF(M18=0,0,IF(ISNUMBER(D18),M18*D18*AC18,NA())) -> 42.76485 | T18: =IF(N18=0,0,IF(ISNUMBER(E18),N18*E18*AC18,NA())) -> 16.236922 | U18: =IF(O18=0,0,O18*F18) -> 496.35239 | V18: =IF(P18=0,0,-P18*G18) -> 0 | W18: =SUM(Q18:V18) -> 1217.5995 | X18: =原始输入与口径!CP18 -> 1217.5995 | Y18: =W18-X18 -> 0 | Z18: ="当日执行" -> 当日执行 | AA18: =IF(原始输入与口径!AW18,1,0) -> 1 | AB18: =IF(原始输入与口径!AY18,1,0) -> 1 | AC18: =原始输入与口径!$F$5 -> 0.25 | AD18: =原始输入与口径!CG18 -> 0.3125 | AE18: =原始输入与口径!BQ18 -> 0.13714286 | AF18: =IF(AA18=0,0,AJ18/(AH18*AC18)) -> 0.3504 | AG18: =IF(AA18=0,0,AK18/(AI18*AC18)) -> 0 | AH18: =IF(ISNUMBER(原始输入与口径!T18),原始输入与口径!T18,"缺失") -> 175 | AI18: =IF(ISNUMBER(原始输入与口径!Y18),原始输入与口径!Y18,"缺失") -> 175 | AJ18: =IF(ISNUMBER(原始输入与口径!AI18),原始输入与口径!AI18,"缺失") -> 15.33 | AK18: =IF(ISNUMBER(原始输入与口径!AL18),原始输入与口径!AL18,"缺失") -> 0 | AL18: =IF(ISNUMBER(原始输入与口径!O18),原始输入与口径!O18,"缺失") -> 128 | AM18: =SUMIFS(相位SOC复算!$N$9:$N$929,相位SOC复算!$S$9:$S$929,10) -> 0.0063478261 | AN18: =SUMIFS(相位SOC复算!$Q$9:$Q$929,相位SOC复算!$S$9:$S$929,10) -> 0 | AO18: =SUMIFS(相位SOC复算!$R$9:$R$929,相位SOC复算!$S$9:$S$929,10) -> 2.1024 | AP18: =相位SOC复算!J30 -> 31.993431 | AQ18: =AP18-J18 -> 0 | AR18: =IF(ISBLANK(原始输入与口径!M18),"",原始输入与口径!M18) -> 5.2473 | AS18: =IF(ISBLANK(原始输入与口径!L18),"",原始输入与口径!L18) -> 46234 | AT18: =IF(ISBLANK(原始输入与口径!A18),"",原始输入与口径!A18) -> 46234.969 | AU18: =IF(ISBLANK(原始输入与口径!I18),"",原始输入与口径!I18) -> 2026-08-01_6 | AV18: =IF(ISBLANK(原始输入与口径!J18),"",原始输入与口径!J18) -> 15 | AW18: =IF(ISBLANK(原始输入与口径!BB18),"",原始输入与口径!BB18) -> OK | AX18: =原始输入与口径!CI18 -> 128 | AY18: =原始输入与口径!BS18 -> 175 | AZ18: =原始输入与口径!BI18 -> 175 | BA18: =原始输入与口径!CM18 -> 40 | BB18: =原始输入与口径!BV18 -> 24 | BC18: =原始输入与口径!BL18 -> 24 | BD18: =46235 -> 46235 | BE18: =IF(K18=0,"零头寸，无结算现金",TEXT(K18,"0.000000")&" MW × "&TEXT(B18,"0.000000")&" × "&TEXT(AC18,"0.000000")&" h = "&TEXT(Q18,"0.000000")&" EUR") -> 零头寸，无结算现金 | BF18: =IF(L18=0,"零头寸，无结算现金",TEXT(L18,"0.000000")&" MW × "&TEXT(C18,"0.000000")&" × "&TEXT(AC18,"0.000000")&" h = "&TEXT(R18,"0.000000")&" EUR") -> 40.000000 MW × 66.224535 × 0.250000 h = 662.245345 EUR | BG18: =IF(M18=0,"零头寸，无结算现金",TEXT(M18,"0.000000")&" MW × "&TEXT(D18,"0.000000")&" × "&TEXT(AC18,"0.000000")&" h = "&TEXT(S18,"0.000000")&" EUR") -> 24.000000 MW × 7.127475 × 0.250000 h = 42.764850 EUR | BH18: =IF(N18=0,"零头寸，无结算现金",TEXT(N18,"0.000000")&" MW × "&TEXT(E18,"0.000000")&" × "&TEXT(AC18,"0.000000")&" h = "&TEXT(T18,"0.000000")&" EUR") -> 24.000000 MW × 2.706154 × 0.250000 h = 16.236922 EUR | BI18: =IF(O18=0,"零上调激活电量",TEXT(O18,"0.000000")&" MWh × "&TEXT(F18,"0.000000")&" = "&TEXT(U18,"0.000000")&" EUR") -> 2.102400 MWh × 236.088465 = 496.352388 EUR | BJ18: =IF(P18=0,"零下调激活电量","−("&TEXT(P18,"0.000000")&" MWh × "&TEXT(G18,"0.000000")&") = "&TEXT(V18,"0.000000")&" EUR") -> 零下调激活电量 | BK18: =TEXT(Q18,"0.000000")&" + "&TEXT(R18,"0.000000")&" + "&TEXT(S18,"0.000000")&" + "&TEXT(T18,"0.000000")&" + "&TEXT(U18,"0.000000")&" + "&TEXT(V18,"0.000000")&" = "&TEXT(W18,"0.000000")&" EUR" -> 0.000000 + 662.245345 + 42.764850 + 16.236922 + 496.352388 + 0.000000 = 1217.599505 EUR
A19: =原始输入与口径!C19 -> 46235.104 | B19: =IF(ISNUMBER(原始输入与口径!H19),原始输入与口径!H19,"缺失") -> 158.09 | C19: =IF(ISNUMBER(原始输入与口径!R19),原始输入与口径!R19,"缺失") -> 66.224535 | D19: =IF(ISNUMBER(原始输入与口径!W19),原始输入与口径!W19,"缺失") -> 7.1274751 | E19: =IF(ISNUMBER(原始输入与口径!AB19),原始输入与口径!AB19,"缺失") -> 2.7061536 | F19: =IF(ISNUMBER(原始输入与口径!AG19),原始输入与口径!AG19,"缺失") -> 179.29545 | G19: =IF(ISNUMBER(原始输入与口径!AJ19),原始输入与口径!AJ19,"缺失") -> 0 | H19: ="未模拟" -> 未模拟 | I19: =原始输入与口径!CD19 -> 31.993431 | J19: =原始输入与口径!CE19 -> 31.979321 | K19: =原始输入与口径!BZ19 -> -1.0887785 | L19: =原始输入与口径!CK19 -> 40 | M19: =原始输入与口径!BT19 -> 24 | N19: =原始输入与口径!BJ19 -> 24 | O19: =M19*AF19*AC19 -> 0.24507429 | P19: =N19*AG19*AC19 -> 0 | Q19: =IF(K19=0,0,IF(ISNUMBER(B19),K19*B19*AC19,NA())) -> -43.03125 | R19: =IF(L19=0,0,IF(ISNUMBER(C19),L19*C19*AC19,NA())) -> 662.24535 | S19: =IF(M19=0,0,IF(ISNUMBER(D19),M19*D19*AC19,NA())) -> 42.76485 | T19: =IF(N19=0,0,IF(ISNUMBER(E19),N19*E19*AC19,NA())) -> 16.236922 | U19: =IF(O19=0,0,O19*F19) -> 43.940704 | V19: =IF(P19=0,0,-P19*G19) -> 0 | W19: =SUM(Q19:V19) -> 722.15657 | X19: =原始输入与口径!CP19 -> 722.15657 | Y19: =W19-X19 -> 0 | Z19: ="当日执行" -> 当日执行 | AA19: =IF(原始输入与口径!AW19,1,0) -> 1 | AB19: =IF(原始输入与口径!AY19,1,0) -> 1 | AC19: =原始输入与口径!$F$5 -> 0.25 | AD19: =原始输入与口径!CG19 -> 0.3125 | AE19: =原始输入与口径!BQ19 -> 0.13714286 | AF19: =IF(AA19=0,0,AJ19/(AH19*AC19)) -> 0.040845714 | AG19: =IF(AA19=0,0,AK19/(AI19*AC19)) -> 0 | AH19: =IF(ISNUMBER(原始输入与口径!T19),原始输入与口径!T19,"缺失") -> 175 | AI19: =IF(ISNUMBER(原始输入与口径!Y19),原始输入与口径!Y19,"缺失") -> 175 | AJ19: =IF(ISNUMBER(原始输入与口径!AI19),原始输入与口径!AI19,"缺失") -> 1.787 | AK19: =IF(ISNUMBER(原始输入与口径!AL19),原始输入与口径!AL19,"缺失") -> 0 | AL19: =IF(ISNUMBER(原始输入与口径!O19),原始输入与口径!O19,"缺失") -> 128 | AM19: =SUMIFS(相位SOC复算!$N$9:$N$929,相位SOC复算!$S$9:$S$929,11) -> 0.0013735857 | AN19: =SUMIFS(相位SOC复算!$Q$9:$Q$929,相位SOC复算!$S$9:$S$929,11) -> 0.26107665 | AO19: =SUMIFS(相位SOC复算!$R$9:$R$929,相位SOC复算!$S$9:$S$929,11) -> 0.2339563 | AP19: =相位SOC复算!J32 -> 31.979321 | AQ19: =AP19-J19 -> 0 | AR19: =IF(ISBLANK(原始输入与口径!M19),"",原始输入与口径!M19) -> 5.2473 | AS19: =IF(ISBLANK(原始输入与口径!L19),"",原始输入与口径!L19) -> 46234 | AT19: =IF(ISBLANK(原始输入与口径!A19),"",原始输入与口径!A19) -> 46234.979 | AU19: =IF(ISBLANK(原始输入与口径!I19),"",原始输入与口径!I19) -> 2026-08-01_7 | AV19: =IF(ISBLANK(原始输入与口径!J19),"",原始输入与口径!J19) -> 15 | AW19: =IF(ISBLANK(原始输入与口径!BB19),"",原始输入与口径!BB19) -> OK | AX19: =原始输入与口径!CI19 -> 128 | AY19: =原始输入与口径!BS19 -> 175 | AZ19: =原始输入与口径!BI19 -> 175 | BA19: =原始输入与口径!CM19 -> 40 | BB19: =原始输入与口径!BV19 -> 24 | BC19: =原始输入与口径!BL19 -> 24 | BD19: =46235 -> 46235 | BE19: =IF(K19=0,"零头寸，无结算现金",TEXT(K19,"0.000000")&" MW × "&TEXT(B19,"0.000000")&" × "&TEXT(AC19,"0.000000")&" h = "&TEXT(Q19,"0.000000")&" EUR") -> -1.088779 MW × 158.090000 × 0.250000 h = -43.031250 EUR | BF19: =IF(L19=0,"零头寸，无结算现金",TEXT(L19,"0.000000")&" MW × "&TEXT(C19,"0.000000")&" × "&TEXT(AC19,"0.000000")&" h = "&TEXT(R19,"0.000000")&" EUR") -> 40.000000 MW × 66.224535 × 0.250000 h = 662.245345 EUR | BG19: =IF(M19=0,"零头寸，无结算现金",TEXT(M19,"0.000000")&" MW × "&TEXT(D19,"0.000000")&" × "&TEXT(AC19,"0.000000")&" h = "&TEXT(S19,"0.000000")&" EUR") -> 24.000000 MW × 7.127475 × 0.250000 h = 42.764850 EUR | BH19: =IF(N19=0,"零头寸，无结算现金",TEXT(N19,"0.000000")&" MW × "&TEXT(E19,"0.000000")&" × "&TEXT(AC19,"0.000000")&" h = "&TEXT(T19,"0.000000")&" EUR") -> 24.000000 MW × 2.706154 × 0.250000 h = 16.236922 EUR | BI19: =IF(O19=0,"零上调激活电量",TEXT(O19,"0.000000")&" MWh × "&TEXT(F19,"0.000000")&" = "&TEXT(U19,"0.000000")&" EUR") -> 0.245074 MWh × 179.295447 = 43.940704 EUR | BJ19: =IF(P19=0,"零下调激活电量","−("&TEXT(P19,"0.000000")&" MWh × "&TEXT(G19,"0.000000")&") = "&TEXT(V19,"0.000000")&" EUR") -> 零下调激活电量 | BK19: =TEXT(Q19,"0.000000")&" + "&TEXT(R19,"0.000000")&" + "&TEXT(S19,"0.000000")&" + "&TEXT(T19,"0.000000")&" + "&TEXT(U19,"0.000000")&" + "&TEXT(V19,"0.000000")&" = "&TEXT(W19,"0.000000")&" EUR" -> -43.031250 + 662.245345 + 42.764850 + 16.236922 + 43.940704 + 0.000000 = 722.156571 EUR
A20: =原始输入与口径!C20 -> 46235.115 | B20: =IF(ISNUMBER(原始输入与口径!H20),原始输入与口径!H20,"缺失") -> 156.91 | C20: =IF(ISNUMBER(原始输入与口径!R20),原始输入与口径!R20,"缺失") -> 66.224535 | D20: =IF(ISNUMBER(原始输入与口径!W20),原始输入与口径!W20,"缺失") -> 7.1274751 | E20: =IF(ISNUMBER(原始输入与口径!AB20),原始输入与口径!AB20,"缺失") -> 2.7061536 | F20: =IF(ISNUMBER(原始输入与口径!AG20),原始输入与口径!AG20,"缺失") -> 170.86159 | G20: =IF(ISNUMBER(原始输入与口径!AJ20),原始输入与口径!AJ20,"缺失") -> 0 | H20: ="未模拟" -> 未模拟 | I20: =原始输入与口径!CD20 -> 31.979321 | J20: =原始输入与口径!CE20 -> 32.677246 | K20: =原始输入与口径!BZ20 -> -4.2700644 | L20: =原始输入与口径!CK20 -> 40 | M20: =原始输入与口径!BT20 -> 24 | N20: =原始输入与口径!BJ20 -> 24 | O20: =M20*AF20*AC20 -> 0.2688 | P20: =N20*AG20*AC20 -> 0 | Q20: =IF(K20=0,0,IF(ISNUMBER(B20),K20*B20*AC20,NA())) -> -167.50395 | R20: =IF(L20=0,0,IF(ISNUMBER(C20),L20*C20*AC20,NA())) -> 662.24535 | S20: =IF(M20=0,0,IF(ISNUMBER(D20),M20*D20*AC20,NA())) -> 42.76485 | T20: =IF(N20=0,0,IF(ISNUMBER(E20),N20*E20*AC20,NA())) -> 16.236922 | U20: =IF(O20=0,0,O20*F20) -> 45.927594 | V20: =IF(P20=0,0,-P20*G20) -> 0 | W20: =SUM(Q20:V20) -> 599.67076 | X20: =原始输入与口径!CP20 -> 599.67076 | Y20: =W20-X20 -> 0 | Z20: ="当日执行" -> 当日执行 | AA20: =IF(原始输入与口径!AW20,1,0) -> 1 | AB20: =IF(原始输入与口径!AY20,1,0) -> 1 | AC20: =原始输入与口径!$F$5 -> 0.25 | AD20: =原始输入与口径!CG20 -> 0.3125 | AE20: =原始输入与口径!BQ20 -> 0.13714286 | AF20: =IF(AA20=0,0,AJ20/(AH20*AC20)) -> 0.0448 | AG20: =IF(AA20=0,0,AK20/(AI20*AC20)) -> 0 | AH20: =IF(ISNUMBER(原始输入与口径!T20),原始输入与口径!T20,"缺失") -> 175 | AI20: =IF(ISNUMBER(原始输入与口径!Y20),原始输入与口径!Y20,"缺失") -> 175 | AJ20: =IF(ISNUMBER(原始输入与口径!AI20),原始输入与口径!AI20,"缺失") -> 1.96 | AK20: =IF(ISNUMBER(原始输入与口径!AL20),原始输入与口径!AL20,"缺失") -> 0 | AL20: =IF(ISNUMBER(原始输入与口径!O20),原始输入与口径!O20,"缺失") -> 128 | AM20: =SUMIFS(相位SOC复算!$N$9:$N$929,相位SOC复算!$S$9:$S$929,12) -> 0.0032730738 | AN20: =SUMIFS(相位SOC复算!$Q$9:$Q$929,相位SOC复算!$S$9:$S$929,12) -> 1.0196914 | AO20: =SUMIFS(相位SOC复算!$R$9:$R$929,相位SOC复算!$S$9:$S$929,12) -> 0.22097528 | AP20: =相位SOC复算!J34 -> 32.677246 | AQ20: =AP20-J20 -> 0 | AR20: =IF(ISBLANK(原始输入与口径!M20),"",原始输入与口径!M20) -> 5.2473 | AS20: =IF(ISBLANK(原始输入与口径!L20),"",原始输入与口径!L20) -> 46234 | AT20: =IF(ISBLANK(原始输入与口径!A20),"",原始输入与口径!A20) -> 46234.99 | AU20: =IF(ISBLANK(原始输入与口径!I20),"",原始输入与口径!I20) -> 2026-08-01_8 | AV20: =IF(ISBLANK(原始输入与口径!J20),"",原始输入与口径!J20) -> 15 | AW20: =IF(ISBLANK(原始输入与口径!BB20),"",原始输入与口径!BB20) -> OK | AX20: =原始输入与口径!CI20 -> 128 | AY20: =原始输入与口径!BS20 -> 175 | AZ20: =原始输入与口径!BI20 -> 175 | BA20: =原始输入与口径!CM20 -> 40 | BB20: =原始输入与口径!BV20 -> 24 | BC20: =原始输入与口径!BL20 -> 24 | BD20: =46235 -> 46235 | BE20: =IF(K20=0,"零头寸，无结算现金",TEXT(K20,"0.000000")&" MW × "&TEXT(B20,"0.000000")&" × "&TEXT(AC20,"0.000000")&" h = "&TEXT(Q20,"0.000000")&" EUR") -> -4.270064 MW × 156.910000 × 0.250000 h = -167.503950 EUR | BF20: =IF(L20=0,"零头寸，无结算现金",TEXT(L20,"0.000000")&" MW × "&TEXT(C20,"0.000000")&" × "&TEXT(AC20,"0.000000")&" h = "&TEXT(R20,"0.000000")&" EUR") -> 40.000000 MW × 66.224535 × 0.250000 h = 662.245345 EUR | BG20: =IF(M20=0,"零头寸，无结算现金",TEXT(M20,"0.000000")&" MW × "&TEXT(D20,"0.000000")&" × "&TEXT(AC20,"0.000000")&" h = "&TEXT(S20,"0.000000")&" EUR") -> 24.000000 MW × 7.127475 × 0.250000 h = 42.764850 EUR | BH20: =IF(N20=0,"零头寸，无结算现金",TEXT(N20,"0.000000")&" MW × "&TEXT(E20,"0.000000")&" × "&TEXT(AC20,"0.000000")&" h = "&TEXT(T20,"0.000000")&" EUR") -> 24.000000 MW × 2.706154 × 0.250000 h = 16.236922 EUR | BI20: =IF(O20=0,"零上调激活电量",TEXT(O20,"0.000000")&" MWh × "&TEXT(F20,"0.000000")&" = "&TEXT(U20,"0.000000")&" EUR") -> 0.268800 MWh × 170.861586 = 45.927594 EUR | BJ20: =IF(P20=0,"零下调激活电量","−("&TEXT(P20,"0.000000")&" MWh × "&TEXT(G20,"0.000000")&") = "&TEXT(V20,"0.000000")&" EUR") -> 零下调激活电量 | BK20: =TEXT(Q20,"0.000000")&" + "&TEXT(R20,"0.000000")&" + "&TEXT(S20,"0.000000")&" + "&TEXT(T20,"0.000000")&" + "&TEXT(U20,"0.000000")&" + "&TEXT(V20,"0.000000")&" = "&TEXT(W20,"0.000000")&" EUR" -> -167.503950 + 662.245345 + 42.764850 + 16.236922 + 45.927594 + 0.000000 = 599.670761 EUR
A21: =原始输入与口径!C21 -> 46235.125 | B21: =IF(ISNUMBER(原始输入与口径!H21),原始输入与口径!H21,"缺失") -> 161.92 | C21: =IF(ISNUMBER(原始输入与口径!R21),原始输入与口径!R21,"缺失") -> 66.224535 | D21: =IF(ISNUMBER(原始输入与口径!W21),原始输入与口径!W21,"缺失") -> 7.1274751 | E21: =IF(ISNUMBER(原始输入与口径!AB21),原始输入与口径!AB21,"缺失") -> 4.2097841 | F21: =IF(ISNUMBER(原始输入与口径!AG21),原始输入与口径!AG21,"缺失") -> 256.41282 | G21: =IF(ISNUMBER(原始输入与口径!AJ21),原始输入与口径!AJ21,"缺失") -> 0 | H21: ="未模拟" -> 未模拟 | I21: =原始输入与口径!CD21 -> 32.677246 | J21: =原始输入与口径!CE21 -> 33.80577 | K21: =原始输入与口径!BZ21 -> -16.316392 | L21: =原始输入与口径!CK21 -> 40 | M21: =原始输入与口径!BT21 -> 24 | N21: =原始输入与口径!BJ21 -> 24 | O21: =M21*AF21*AC21 -> 2.6958171 | P21: =N21*AG21*AC21 -> 0 | Q21: =IF(K21=0,0,IF(ISNUMBER(B21),K21*B21*AC21,NA())) -> -660.48754 | R21: =IF(L21=0,0,IF(ISNUMBER(C21),L21*C21*AC21,NA())) -> 662.24535 | S21: =IF(M21=0,0,IF(ISNUMBER(D21),M21*D21*AC21,NA())) -> 42.76485 | T21: =IF(N21=0,0,IF(ISNUMBER(E21),N21*E21*AC21,NA())) -> 25.258704 | U21: =IF(O21=0,0,O21*F21) -> 691.24208 | V21: =IF(P21=0,0,-P21*G21) -> 0 | W21: =SUM(Q21:V21) -> 761.02344 | X21: =原始输入与口径!CP21 -> 761.02344 | Y21: =W21-X21 -> 0 | Z21: ="当日执行" -> 当日执行 | AA21: =IF(原始输入与口径!AW21,1,0) -> 1 | AB21: =IF(原始输入与口径!AY21,1,0) -> 1 | AC21: =原始输入与口径!$F$5 -> 0.25 | AD21: =原始输入与口径!CG21 -> 0.3125 | AE21: =原始输入与口径!BQ21 -> 0.13714286 | AF21: =IF(AA21=0,0,AJ21/(AH21*AC21)) -> 0.44930286 | AG21: =IF(AA21=0,0,AK21/(AI21*AC21)) -> 0 | AH21: =IF(ISNUMBER(原始输入与口径!T21),原始输入与口径!T21,"缺失") -> 175 | AI21: =IF(ISNUMBER(原始输入与口径!Y21),原始输入与口径!Y21,"缺失") -> 175 | AJ21: =IF(ISNUMBER(原始输入与口径!AI21),原始输入与口径!AI21,"缺失") -> 19.657 | AK21: =IF(ISNUMBER(原始输入与口径!AL21),原始输入与口径!AL21,"缺失") -> 0 | AL21: =IF(ISNUMBER(原始输入与口径!O21),原始输入与口径!O21,"缺失") -> 128 | AM21: =SUMIFS(相位SOC复算!$N$9:$N$929,相位SOC复算!$S$9:$S$929,13) -> 0.008346544 | AN21: =SUMIFS(相位SOC复算!$Q$9:$Q$929,相位SOC复算!$S$9:$S$929,13) -> 2.2463476 | AO21: =SUMIFS(相位SOC复算!$R$9:$R$929,相位SOC复算!$S$9:$S$929,13) -> 0.86306678 | AP21: =相位SOC复算!J36 -> 33.80577 | AQ21: =AP21-J21 -> 0 | AR21: =IF(ISBLANK(原始输入与口径!M21),"",原始输入与口径!M21) -> 5.2473 | AS21: =IF(ISBLANK(原始输入与口径!L21),"",原始输入与口径!L21) -> 46234 | AT21: =IF(ISBLANK(原始输入与口径!A21),"",原始输入与口径!A21) -> 46235 | AU21: =IF(ISBLANK(原始输入与口径!I21),"",原始输入与口径!I21) -> 2026-08-01_9 | AV21: =IF(ISBLANK(原始输入与口径!J21),"",原始输入与口径!J21) -> 15 | AW21: =IF(ISBLANK(原始输入与口径!BB21),"",原始输入与口径!BB21) -> OK | AX21: =原始输入与口径!CI21 -> 128 | AY21: =原始输入与口径!BS21 -> 175 | AZ21: =原始输入与口径!BI21 -> 175 | BA21: =原始输入与口径!CM21 -> 40 | BB21: =原始输入与口径!BV21 -> 24 | BC21: =原始输入与口径!BL21 -> 24 | BD21: =46235 -> 46235 | BE21: =IF(K21=0,"零头寸，无结算现金",TEXT(K21,"0.000000")&" MW × "&TEXT(B21,"0.000000")&" × "&TEXT(AC21,"0.000000")&" h = "&TEXT(Q21,"0.000000")&" EUR") -> -16.316392 MW × 161.920000 × 0.250000 h = -660.487540 EUR | BF21: =IF(L21=0,"零头寸，无结算现金",TEXT(L21,"0.000000")&" MW × "&TEXT(C21,"0.000000")&" × "&TEXT(AC21,"0.000000")&" h = "&TEXT(R21,"0.000000")&" EUR") -> 40.000000 MW × 66.224535 × 0.250000 h = 662.245345 EUR | BG21: =IF(M21=0,"零头寸，无结算现金",TEXT(M21,"0.000000")&" MW × "&TEXT(D21,"0.000000")&" × "&TEXT(AC21,"0.000000")&" h = "&TEXT(S21,"0.000000")&" EUR") -> 24.000000 MW × 7.127475 × 0.250000 h = 42.764850 EUR | BH21: =IF(N21=0,"零头寸，无结算现金",TEXT(N21,"0.000000")&" MW × "&TEXT(E21,"0.000000")&" × "&TEXT(AC21,"0.000000")&" h = "&TEXT(T21,"0.000000")&" EUR") -> 24.000000 MW × 4.209784 × 0.250000 h = 25.258704 EUR | BI21: =IF(O21=0,"零上调激活电量",TEXT(O21,"0.000000")&" MWh × "&TEXT(F21,"0.000000")&" = "&TEXT(U21,"0.000000")&" EUR") -> 2.695817 MWh × 256.412822 = 691.242081 EUR | BJ21: =IF(P21=0,"零下调激活电量","−("&TEXT(P21,"0.000000")&" MWh × "&TEXT(G21,"0.000000")&") = "&TEXT(V21,"0.000000")&" EUR") -> 零下调激活电量 | BK21: =TEXT(Q21,"0.000000")&" + "&TEXT(R21,"0.000000")&" + "&TEXT(S21,"0.000000")&" + "&TEXT(T21,"0.000000")&" + "&TEXT(U21,"0.000000")&" + "&TEXT(V21,"0.000000")&" = "&TEXT(W21,"0.000000")&" EUR" -> -660.487540 + 662.245345 + 42.764850 + 25.258704 + 691.242081 + 0.000000 = 761.023441 EUR
A22: =原始输入与口径!C22 -> 46235.135 | B22: =IF(ISNUMBER(原始输入与口径!H22),原始输入与口径!H22,"缺失") -> 160.57 | C22: =IF(ISNUMBER(原始输入与口径!R22),原始输入与口径!R22,"缺失") -> 66.224535 | D22: =IF(ISNUMBER(原始输入与口径!W22),原始输入与口径!W22,"缺失") -> 7.1274751 | E22: =IF(ISNUMBER(原始输入与口径!AB22),原始输入与口径!AB22,"缺失") -> 4.2097841 | F22: =IF(ISNUMBER(原始输入与口径!AG22),原始输入与口径!AG22,"缺失") -> 350.54123 | G22: =IF(ISNUMBER(原始输入与口径!AJ22),原始输入与口径!AJ22,"缺失") -> 0 | H22: ="未模拟" -> 未模拟 | I22: =原始输入与口径!CD22 -> 33.80577 | J22: =原始输入与口径!CE22 -> 35.274153 | K22: =原始输入与口径!BZ22 -> -24 | L22: =原始输入与口径!CK22 -> 40 | M22: =原始输入与口径!BT22 -> 24 | N22: =原始输入与口径!BJ22 -> 24 | O22: =M22*AF22*AC22 -> 4.4039314 | P22: =N22*AG22*AC22 -> 0 | Q22: =IF(K22=0,0,IF(ISNUMBER(B22),K22*B22*AC22,NA())) -> -963.42 | R22: =IF(L22=0,0,IF(ISNUMBER(C22),L22*C22*AC22,NA())) -> 662.24535 | S22: =IF(M22=0,0,IF(ISNUMBER(D22),M22*D22*AC22,NA())) -> 42.76485 | T22: =IF(N22=0,0,IF(ISNUMBER(E22),N22*E22*AC22,NA())) -> 25.258704 | U22: =IF(O22=0,0,O22*F22) -> 1543.7595 | V22: =IF(P22=0,0,-P22*G22) -> 0 | W22: =SUM(Q22:V22) -> 1310.6084 | X22: =原始输入与口径!CP22 -> 1310.6084 | Y22: =W22-X22 -> 0 | Z22: ="当日执行" -> 当日执行 | AA22: =IF(原始输入与口径!AW22,1,0) -> 1 | AB22: =IF(原始输入与口径!AY22,1,0) -> 1 | AC22: =原始输入与口径!$F$5 -> 0.25 | AD22: =原始输入与口径!CG22 -> 0.3125 | AE22: =原始输入与口径!BQ22 -> 0.13714286 | AF22: =IF(AA22=0,0,AJ22/(AH22*AC22)) -> 0.73398857 | AG22: =IF(AA22=0,0,AK22/(AI22*AC22)) -> 0 | AH22: =IF(ISNUMBER(原始输入与口径!T22),原始输入与口径!T22,"缺失") -> 175 | AI22: =IF(ISNUMBER(原始输入与口径!Y22),原始输入与口径!Y22,"缺失") -> 175 | AJ22: =IF(ISNUMBER(原始输入与口径!AI22),原始输入与口径!AI22,"缺失") -> 32.112 | AK22: =IF(ISNUMBER(原始输入与口径!AL22),原始输入与口径!AL22,"缺失") -> 0 | AL22: =IF(ISNUMBER(原始输入与口径!O22),原始输入与口径!O22,"缺失") -> 128 | AM22: =SUMIFS(相位SOC复算!$N$9:$N$929,相位SOC复算!$S$9:$S$929,14) -> 0.0040788419 | AN22: =SUMIFS(相位SOC复算!$Q$9:$Q$929,相位SOC复算!$S$9:$S$929,14) -> 1.5960686 | AO22: =SUMIFS(相位SOC复算!$R$9:$R$929,相位SOC复算!$S$9:$S$929,14) -> 0 | AP22: =相位SOC复算!J38 -> 35.274153 | AQ22: =AP22-J22 -> 0 | AR22: =IF(ISBLANK(原始输入与口径!M22),"",原始输入与口径!M22) -> 5.2473 | AS22: =IF(ISBLANK(原始输入与口径!L22),"",原始输入与口径!L22) -> 46234 | AT22: =IF(ISBLANK(原始输入与口径!A22),"",原始输入与口径!A22) -> 46235.01 | AU22: =IF(ISBLANK(原始输入与口径!I22),"",原始输入与口径!I22) -> 2026-08-01_10 | AV22: =IF(ISBLANK(原始输入与口径!J22),"",原始输入与口径!J22) -> 15 | AW22: =IF(ISBLANK(原始输入与口径!BB22),"",原始输入与口径!BB22) -> OK | AX22: =原始输入与口径!CI22 -> 128 | AY22: =原始输入与口径!BS22 -> 175 | AZ22: =原始输入与口径!BI22 -> 175 | BA22: =原始输入与口径!CM22 -> 40 | BB22: =原始输入与口径!BV22 -> 24 | BC22: =原始输入与口径!BL22 -> 24 | BD22: =46235 -> 46235 | BE22: =IF(K22=0,"零头寸，无结算现金",TEXT(K22,"0.000000")&" MW × "&TEXT(B22,"0.000000")&" × "&TEXT(AC22,"0.000000")&" h = "&TEXT(Q22,"0.000000")&" EUR") -> -24.000000 MW × 160.570000 × 0.250000 h = -963.420000 EUR | BF22: =IF(L22=0,"零头寸，无结算现金",TEXT(L22,"0.000000")&" MW × "&TEXT(C22,"0.000000")&" × "&TEXT(AC22,"0.000000")&" h = "&TEXT(R22,"0.000000")&" EUR") -> 40.000000 MW × 66.224535 × 0.250000 h = 662.245345 EUR | BG22: =IF(M22=0,"零头寸，无结算现金",TEXT(M22,"0.000000")&" MW × "&TEXT(D22,"0.000000")&" × "&TEXT(AC22,"0.000000")&" h = "&TEXT(S22,"0.000000")&" EUR") -> 24.000000 MW × 7.127475 × 0.250000 h = 42.764850 EUR | BH22: =IF(N22=0,"零头寸，无结算现金",TEXT(N22,"0.000000")&" MW × "&TEXT(E22,"0.000000")&" × "&TEXT(AC22,"0.000000")&" h = "&TEXT(T22,"0.000000")&" EUR") -> 24.000000 MW × 4.209784 × 0.250000 h = 25.258704 EUR | BI22: =IF(O22=0,"零上调激活电量",TEXT(O22,"0.000000")&" MWh × "&TEXT(F22,"0.000000")&" = "&TEXT(U22,"0.000000")&" EUR") -> 4.403931 MWh × 350.541231 = 1543.759543 EUR | BJ22: =IF(P22=0,"零下调激活电量","−("&TEXT(P22,"0.000000")&" MWh × "&TEXT(G22,"0.000000")&") = "&TEXT(V22,"0.000000")&" EUR") -> 零下调激活电量 | BK22: =TEXT(Q22,"0.000000")&" + "&TEXT(R22,"0.000000")&" + "&TEXT(S22,"0.000000")&" + "&TEXT(T22,"0.000000")&" + "&TEXT(U22,"0.000000")&" + "&TEXT(V22,"0.000000")&" = "&TEXT(W22,"0.000000")&" EUR" -> -963.420000 + 662.245345 + 42.764850 + 25.258704 + 1543.759543 + 0.000000 = 1310.608443 EUR
A23: =原始输入与口径!C23 -> 46235.146 | B23: =IF(ISNUMBER(原始输入与口径!H23),原始输入与口径!H23,"缺失") -> 156.74 | C23: =IF(ISNUMBER(原始输入与口径!R23),原始输入与口径!R23,"缺失") -> 66.224535 | D23: =IF(ISNUMBER(原始输入与口径!W23),原始输入与口径!W23,"缺失") -> 7.1274751 | E23: =IF(ISNUMBER(原始输入与口径!AB23),原始输入与口径!AB23,"缺失") -> 4.2097841 | F23: =IF(ISNUMBER(原始输入与口径!AG23),原始输入与口径!AG23,"缺失") -> 271.16212 | G23: =IF(ISNUMBER(原始输入与口径!AJ23),原始输入与口径!AJ23,"缺失") -> 0 | H23: ="未模拟" -> 未模拟 | I23: =原始输入与口径!CD23 -> 35.274153 | J23: =原始输入与口径!CE23 -> 37.237128 | K23: =原始输入与口径!BZ23 -> -24 | L23: =原始输入与口径!CK23 -> 40 | M23: =原始输入与口径!BT23 -> 24 | N23: =原始输入与口径!BJ23 -> 24 | O23: =M23*AF23*AC23 -> 3.8663314 | P23: =N23*AG23*AC23 -> 0 | Q23: =IF(K23=0,0,IF(ISNUMBER(B23),K23*B23*AC23,NA())) -> -940.44 | R23: =IF(L23=0,0,IF(ISNUMBER(C23),L23*C23*AC23,NA())) -> 662.24535 | S23: =IF(M23=0,0,IF(ISNUMBER(D23),M23*D23*AC23,NA())) -> 42.76485 | T23: =IF(N23=0,0,IF(ISNUMBER(E23),N23*E23*AC23,NA())) -> 25.258704 | U23: =IF(O23=0,0,O23*F23) -> 1048.4026 | V23: =IF(P23=0,0,-P23*G23) -> 0 | W23: =SUM(Q23:V23) -> 838.23153 | X23: =原始输入与口径!CP23 -> 838.23153 | Y23: =W23-X23 -> 0 | Z23: ="当日执行" -> 当日执行 | AA23: =IF(原始输入与口径!AW23,1,0) -> 1 | AB23: =IF(原始输入与口径!AY23,1,0) -> 1 | AC23: =原始输入与口径!$F$5 -> 0.25 | AD23: =原始输入与口径!CG23 -> 0.3125 | AE23: =原始输入与口径!BQ23 -> 0.13714286 | AF23: =IF(AA23=0,0,AJ23/(AH23*AC23)) -> 0.64438857 | AG23: =IF(AA23=0,0,AK23/(AI23*AC23)) -> 0 | AH23: =IF(ISNUMBER(原始输入与口径!T23),原始输入与口径!T23,"缺失") -> 175 | AI23: =IF(ISNUMBER(原始输入与口径!Y23),原始输入与口径!Y23,"缺失") -> 175 | AJ23: =IF(ISNUMBER(原始输入与口径!AI23),原始输入与口径!AI23,"缺失") -> 28.192 | AK23: =IF(ISNUMBER(原始输入与口径!AL23),原始输入与口径!AL23,"缺失") -> 0 | AL23: =IF(ISNUMBER(原始输入与口径!O23),原始输入与口径!O23,"缺失") -> 128 | AM23: =SUMIFS(相位SOC复算!$N$9:$N$929,相位SOC复算!$S$9:$S$929,15) -> 0.0054527086 | AN23: =SUMIFS(相位SOC复算!$Q$9:$Q$929,相位SOC复算!$S$9:$S$929,15) -> 2.1336686 | AO23: =SUMIFS(相位SOC复算!$R$9:$R$929,相位SOC复算!$S$9:$S$929,15) -> 0 | AP23: =相位SOC复算!J40 -> 37.237128 | AQ23: =AP23-J23 -> 0 | AR23: =IF(ISBLANK(原始输入与口径!M23),"",原始输入与口径!M23) -> 5.2473 | AS23: =IF(ISBLANK(原始输入与口径!L23),"",原始输入与口径!L23) -> 46234 | AT23: =IF(ISBLANK(原始输入与口径!A23),"",原始输入与口径!A23) -> 46235.021 | AU23: =IF(ISBLANK(原始输入与口径!I23),"",原始输入与口径!I23) -> 2026-08-01_11 | AV23: =IF(ISBLANK(原始输入与口径!J23),"",原始输入与口径!J23) -> 15 | AW23: =IF(ISBLANK(原始输入与口径!BB23),"",原始输入与口径!BB23) -> OK | AX23: =原始输入与口径!CI23 -> 128 | AY23: =原始输入与口径!BS23 -> 175 | AZ23: =原始输入与口径!BI23 -> 175 | BA23: =原始输入与口径!CM23 -> 40 | BB23: =原始输入与口径!BV23 -> 24 | BC23: =原始输入与口径!BL23 -> 24 | BD23: =46235 -> 46235 | BE23: =IF(K23=0,"零头寸，无结算现金",TEXT(K23,"0.000000")&" MW × "&TEXT(B23,"0.000000")&" × "&TEXT(AC23,"0.000000")&" h = "&TEXT(Q23,"0.000000")&" EUR") -> -24.000000 MW × 156.740000 × 0.250000 h = -940.440000 EUR | BF23: =IF(L23=0,"零头寸，无结算现金",TEXT(L23,"0.000000")&" MW × "&TEXT(C23,"0.000000")&" × "&TEXT(AC23,"0.000000")&" h = "&TEXT(R23,"0.000000")&" EUR") -> 40.000000 MW × 66.224535 × 0.250000 h = 662.245345 EUR | BG23: =IF(M23=0,"零头寸，无结算现金",TEXT(M23,"0.000000")&" MW × "&TEXT(D23,"0.000000")&" × "&TEXT(AC23,"0.000000")&" h = "&TEXT(S23,"0.000000")&" EUR") -> 24.000000 MW × 7.127475 × 0.250000 h = 42.764850 EUR | BH23: =IF(N23=0,"零头寸，无结算现金",TEXT(N23,"0.000000")&" MW × "&TEXT(E23,"0.000000")&" × "&TEXT(AC23,"0.000000")&" h = "&TEXT(T23,"0.000000")&" EUR") -> 24.000000 MW × 4.209784 × 0.250000 h = 25.258704 EUR | BI23: =IF(O23=0,"零上调激活电量",TEXT(O23,"0.000000")&" MWh × "&TEXT(F23,"0.000000")&" = "&TEXT(U23,"0.000000")&" EUR") -> 3.866331 MWh × 271.162121 = 1048.402632 EUR | BJ23: =IF(P23=0,"零下调激活电量","−("&TEXT(P23,"0.000000")&" MWh × "&TEXT(G23,"0.000000")&") = "&TEXT(V23,"0.000000")&" EUR") -> 零下调激活电量 | BK23: =TEXT(Q23,"0.000000")&" + "&TEXT(R23,"0.000000")&" + "&TEXT(S23,"0.000000")&" + "&TEXT(T23,"0.000000")&" + "&TEXT(U23,"0.000000")&" + "&TEXT(V23,"0.000000")&" = "&TEXT(W23,"0.000000")&" EUR" -> -940.440000 + 662.245345 + 42.764850 + 25.258704 + 1048.402632 + 0.000000 = 838.231533 EUR
A24: =原始输入与口径!C24 -> 46235.156 | B24: =IF(ISNUMBER(原始输入与口径!H24),原始输入与口径!H24,"缺失") -> 153.21 | C24: =IF(ISNUMBER(原始输入与口径!R24),原始输入与口径!R24,"缺失") -> 66.224535 | D24: =IF(ISNUMBER(原始输入与口径!W24),原始输入与口径!W24,"缺失") -> 7.1274751 | E24: =IF(ISNUMBER(原始输入与口径!AB24),原始输入与口径!AB24,"缺失") -> 4.2097841 | F24: =IF(ISNUMBER(原始输入与口径!AG24),原始输入与口径!AG24,"缺失") -> 263.23786 | G24: =IF(ISNUMBER(原始输入与口径!AJ24),原始输入与口径!AJ24,"缺失") -> 0 | H24: ="未模拟" -> 未模拟 | I24: =原始输入与口径!CD24 -> 37.237128 | J24: =原始输入与口径!CE24 -> 39.477807 | K24: =原始输入与口径!BZ24 -> -24 | L24: =原始输入与口径!CK24 -> 40 | M24: =原始输入与口径!BT24 -> 24 | N24: =原始输入与口径!BJ24 -> 24 | O24: =M24*AF24*AC24 -> 3.56448 | P24: =N24*AG24*AC24 -> 0 | Q24: =IF(K24=0,0,IF(ISNUMBER(B24),K24*B24*AC24,NA())) -> -919.26 | R24: =IF(L24=0,0,IF(ISNUMBER(C24),L24*C24*AC24,NA())) -> 662.24535 | S24: =IF(M24=0,0,IF(ISNUMBER(D24),M24*D24*AC24,NA())) -> 42.76485 | T24: =IF(N24=0,0,IF(ISNUMBER(E24),N24*E24*AC24,NA())) -> 25.258704 | U24: =IF(O24=0,0,O24*F24) -> 938.30607 | V24: =IF(P24=0,0,-P24*G24) -> 0 | W24: =SUM(Q24:V24) -> 749.31497 | X24: =原始输入与口径!CP24 -> 749.31497 | Y24: =W24-X24 -> 0 | Z24: ="当日执行" -> 当日执行 | AA24: =IF(原始输入与口径!AW24,1,0) -> 1 | AB24: =IF(原始输入与口径!AY24,1,0) -> 1 | AC24: =原始输入与口径!$F$5 -> 0.25 | AD24: =原始输入与口径!CG24 -> 0.3125 | AE24: =原始输入与口径!BQ24 -> 0.13714286 | AF24: =IF(AA24=0,0,AJ24/(AH24*AC24)) -> 0.59408 | AG24: =IF(AA24=0,0,AK24/(AI24*AC24)) -> 0 | AH24: =IF(ISNUMBER(原始输入与口径!T24),原始输入与口径!T24,"缺失") -> 175 | AI24: =IF(ISNUMBER(原始输入与口径!Y24),原始输入与口径!Y24,"缺失") -> 175 | AJ24: =IF(ISNUMBER(原始输入与口径!AI24),原始输入与口径!AI24,"缺失") -> 25.991 | AK24: =IF(ISNUMBER(原始输入与口径!AL24),原始输入与口径!AL24,"缺失") -> 0 | AL24: =IF(ISNUMBER(原始输入与口径!O24),原始输入与口径!O24,"缺失") -> 128 | AM24: =SUMIFS(相位SOC复算!$N$9:$N$929,相位SOC复算!$S$9:$S$929,16) -> 0.0062241067 | AN24: =SUMIFS(相位SOC复算!$Q$9:$Q$929,相位SOC复算!$S$9:$S$929,16) -> 2.43552 | AO24: =SUMIFS(相位SOC复算!$R$9:$R$929,相位SOC复算!$S$9:$S$929,16) -> 0 | AP24: =相位SOC复算!J42 -> 39.477807 | AQ24: =AP24-J24 -> 0 | AR24: =IF(ISBLANK(原始输入与口径!M24),"",原始输入与口径!M24) -> 5.2473 | AS24: =IF(ISBLANK(原始输入与口径!L24),"",原始输入与口径!L24) -> 46234 | AT24: =IF(ISBLANK(原始输入与口径!A24),"",原始输入与口径!A24) -> 46235.031 | AU24: =IF(ISBLANK(原始输入与口径!I24),"",原始输入与口径!I24) -> 2026-08-01_12 | AV24: =IF(ISBLANK(原始输入与口径!J24),"",原始输入与口径!J24) -> 15 | AW24: =IF(ISBLANK(原始输入与口径!BB24),"",原始输入与口径!BB24) -> OK | AX24: =原始输入与口径!CI24 -> 128 | AY24: =原始输入与口径!BS24 -> 175 | AZ24: =原始输入与口径!BI24 -> 175 | BA24: =原始输入与口径!CM24 -> 40 | BB24: =原始输入与口径!BV24 -> 24 | BC24: =原始输入与口径!BL24 -> 24 | BD24: =46235 -> 46235 | BE24: =IF(K24=0,"零头寸，无结算现金",TEXT(K24,"0.000000")&" MW × "&TEXT(B24,"0.000000")&" × "&TEXT(AC24,"0.000000")&" h = "&TEXT(Q24,"0.000000")&" EUR") -> -24.000000 MW × 153.210000 × 0.250000 h = -919.260000 EUR | BF24: =IF(L24=0,"零头寸，无结算现金",TEXT(L24,"0.000000")&" MW × "&TEXT(C24,"0.000000")&" × "&TEXT(AC24,"0.000000")&" h = "&TEXT(R24,"0.000000")&" EUR") -> 40.000000 MW × 66.224535 × 0.250000 h = 662.245345 EUR | BG24: =IF(M24=0,"零头寸，无结算现金",TEXT(M24,"0.000000")&" MW × "&TEXT(D24,"0.000000")&" × "&TEXT(AC24,"0.000000")&" h = "&TEXT(S24,"0.000000")&" EUR") -> 24.000000 MW × 7.127475 × 0.250000 h = 42.764850 EUR | BH24: =IF(N24=0,"零头寸，无结算现金",TEXT(N24,"0.000000")&" MW × "&TEXT(E24,"0.000000")&" × "&TEXT(AC24,"0.000000")&" h = "&TEXT(T24,"0.000000")&" EUR") -> 24.000000 MW × 4.209784 × 0.250000 h = 25.258704 EUR | BI24: =IF(O24=0,"零上调激活电量",TEXT(O24,"0.000000")&" MWh × "&TEXT(F24,"0.000000")&" = "&TEXT(U24,"0.000000")&" EUR") -> 3.564480 MWh × 263.237856 = 938.306072 EUR | BJ24: =IF(P24=0,"零下调激活电量","−("&TEXT(P24,"0.000000")&" MWh × "&TEXT(G24,"0.000000")&") = "&TEXT(V24,"0.000000")&" EUR") -> 零下调激活电量 | BK24: =TEXT(Q24,"0.000000")&" + "&TEXT(R24,"0.000000")&" + "&TEXT(S24,"0.000000")&" + "&TEXT(T24,"0.000000")&" + "&TEXT(U24,"0.000000")&" + "&TEXT(V24,"0.000000")&" = "&TEXT(W24,"0.000000")&" EUR" -> -919.260000 + 662.245345 + 42.764850 + 25.258704 + 938.306072 + 0.000000 = 749.314972 EUR
A25: =原始输入与口径!C25 -> 46235.167 | B25: =IF(ISNUMBER(原始输入与口径!H25),原始输入与口径!H25,"缺失") -> 158.42 | C25: =IF(ISNUMBER(原始输入与口径!R25),原始输入与口径!R25,"缺失") -> 66.224535 | D25: =IF(ISNUMBER(原始输入与口径!W25),原始输入与口径!W25,"缺失") -> 7.1274751 | E25: =IF(ISNUMBER(原始输入与口径!AB25),原始输入与口径!AB25,"缺失") -> 5.0768967 | F25: =IF(ISNUMBER(原始输入与口径!AG25),原始输入与口径!AG25,"缺失") -> 224.30412 | G25: =IF(ISNUMBER(原始输入与口径!AJ25),原始输入与口径!AJ25,"缺失") -> 0 | H25: ="未模拟" -> 未模拟 | I25: =原始输入与口径!CD25 -> 39.477807 | J25: =原始输入与口径!CE25 -> 36.896838 | K25: =原始输入与口径!BZ25 -> 0 | L25: =原始输入与口径!CK25 -> 40 | M25: =原始输入与口径!BT25 -> 24 | N25: =原始输入与口径!BJ25 -> 24 | O25: =M25*AF25*AC25 -> 2.3744914 | P25: =N25*AG25*AC25 -> 0 | Q25: =IF(K25=0,0,IF(ISNUMBER(B25),K25*B25*AC25,NA())) -> 0 | R25: =IF(L25=0,0,IF(ISNUMBER(C25),L25*C25*AC25,NA())) -> 662.24535 | S25: =IF(M25=0,0,IF(ISNUMBER(D25),M25*D25*AC25,NA())) -> 42.76485 | T25: =IF(N25=0,0,IF(ISNUMBER(E25),N25*E25*AC25,NA())) -> 30.46138 | U25: =IF(O25=0,0,O25*F25) -> 532.60821 | V25: =IF(P25=0,0,-P25*G25) -> 0 | W25: =SUM(Q25:V25) -> 1268.0798 | X25: =原始输入与口径!CP25 -> 1268.0798 | Y25: =W25-X25 -> 0 | Z25: ="当日执行" -> 当日执行 | AA25: =IF(原始输入与口径!AW25,1,0) -> 1 | AB25: =IF(原始输入与口径!AY25,1,0) -> 1 | AC25: =原始输入与口径!$F$5 -> 0.25 | AD25: =原始输入与口径!CG25 -> 0.3125 | AE25: =原始输入与口径!BQ25 -> 0.13714286 | AF25: =IF(AA25=0,0,AJ25/(AH25*AC25)) -> 0.39574857 | AG25: =IF(AA25=0,0,AK25/(AI25*AC25)) -> 0 | AH25: =IF(ISNUMBER(原始输入与口径!T25),原始输入与口径!T25,"缺失") -> 175 | AI25: =IF(ISNUMBER(原始输入与口径!Y25),原始输入与口径!Y25,"缺失") -> 175 | AJ25: =IF(ISNUMBER(原始输入与口径!AI25),原始输入与口径!AI25,"缺失") -> 17.314 | AK25: =IF(ISNUMBER(原始输入与口径!AL25),原始输入与口径!AL25,"缺失") -> 0 | AL25: =IF(ISNUMBER(原始输入与口径!O25),原始输入与口径!O25,"缺失") -> 128 | AM25: =SUMIFS(相位SOC复算!$N$9:$N$929,相位SOC复算!$S$9:$S$929,17) -> 0.0071693582 | AN25: =SUMIFS(相位SOC复算!$Q$9:$Q$929,相位SOC复算!$S$9:$S$929,17) -> 0 | AO25: =SUMIFS(相位SOC复算!$R$9:$R$929,相位SOC复算!$S$9:$S$929,17) -> 2.3744914 | AP25: =相位SOC复算!J44 -> 36.896838 | AQ25: =AP25-J25 -> 0 | AR25: =IF(ISBLANK(原始输入与口径!M25),"",原始输入与口径!M25) -> 5.2473 | AS25: =IF(ISBLANK(原始输入与口径!L25),"",原始输入与口径!L25) -> 46234 | AT25: =IF(ISBLANK(原始输入与口径!A25),"",原始输入与口径!A25) -> 46235.042 | AU25: =IF(ISBLANK(原始输入与口径!I25),"",原始输入与口径!I25) -> 2026-08-01_13 | AV25: =IF(ISBLANK(原始输入与口径!J25),"",原始输入与口径!J25) -> 15 | AW25: =IF(ISBLANK(原始输入与口径!BB25),"",原始输入与口径!BB25) -> OK | AX25: =原始输入与口径!CI25 -> 128 | AY25: =原始输入与口径!BS25 -> 175 | AZ25: =原始输入与口径!BI25 -> 175 | BA25: =原始输入与口径!CM25 -> 40 | BB25: =原始输入与口径!BV25 -> 24 | BC25: =原始输入与口径!BL25 -> 24 | BD25: =46235 -> 46235 | BE25: =IF(K25=0,"零头寸，无结算现金",TEXT(K25,"0.000000")&" MW × "&TEXT(B25,"0.000000")&" × "&TEXT(AC25,"0.000000")&" h = "&TEXT(Q25,"0.000000")&" EUR") -> 零头寸，无结算现金 | BF25: =IF(L25=0,"零头寸，无结算现金",TEXT(L25,"0.000000")&" MW × "&TEXT(C25,"0.000000")&" × "&TEXT(AC25,"0.000000")&" h = "&TEXT(R25,"0.000000")&" EUR") -> 40.000000 MW × 66.224535 × 0.250000 h = 662.245345 EUR | BG25: =IF(M25=0,"零头寸，无结算现金",TEXT(M25,"0.000000")&" MW × "&TEXT(D25,"0.000000")&" × "&TEXT(AC25,"0.000000")&" h = "&TEXT(S25,"0.000000")&" EUR") -> 24.000000 MW × 7.127475 × 0.250000 h = 42.764850 EUR | BH25: =IF(N25=0,"零头寸，无结算现金",TEXT(N25,"0.000000")&" MW × "&TEXT(E25,"0.000000")&" × "&TEXT(AC25,"0.000000")&" h = "&TEXT(T25,"0.000000")&" EUR") -> 24.000000 MW × 5.076897 × 0.250000 h = 30.461380 EUR | BI25: =IF(O25=0,"零上调激活电量",TEXT(O25,"0.000000")&" MWh × "&TEXT(F25,"0.000000")&" = "&TEXT(U25,"0.000000")&" EUR") -> 2.374491 MWh × 224.304118 = 532.608206 EUR | BJ25: =IF(P25=0,"零下调激活电量","−("&TEXT(P25,"0.000000")&" MWh × "&TEXT(G25,"0.000000")&") = "&TEXT(V25,"0.000000")&" EUR") -> 零下调激活电量 | BK25: =TEXT(Q25,"0.000000")&" + "&TEXT(R25,"0.000000")&" + "&TEXT(S25,"0.000000")&" + "&TEXT(T25,"0.000000")&" + "&TEXT(U25,"0.000000")&" + "&TEXT(V25,"0.000000")&" = "&TEXT(W25,"0.000000")&" EUR" -> 0.000000 + 662.245345 + 42.764850 + 30.461380 + 532.608206 + 0.000000 = 1268.079782 EUR
A26: =原始输入与口径!C26 -> 46235.177 | B26: =IF(ISNUMBER(原始输入与口径!H26),原始输入与口径!H26,"缺失") -> 154.34 | C26: =IF(ISNUMBER(原始输入与口径!R26),原始输入与口径!R26,"缺失") -> 66.224535 | D26: =IF(ISNUMBER(原始输入与口径!W26),原始输入与口径!W26,"缺失") -> 7.1274751 | E26: =IF(ISNUMBER(原始输入与口径!AB26),原始输入与口径!AB26,"缺失") -> 5.0768967 | F26: =IF(ISNUMBER(原始输入与口径!AG26),原始输入与口径!AG26,"缺失") -> 227.01427 | G26: =IF(ISNUMBER(原始输入与口径!AJ26),原始输入与口径!AJ26,"缺失") -> 0 | H26: ="未模拟" -> 未模拟 | I26: =原始输入与口径!CD26 -> 36.896838 | J26: =原始输入与口径!CE26 -> 40.124177 | K26: =原始输入与口径!BZ26 -> -24 | L26: =原始输入与口径!CK26 -> 40 | M26: =原始输入与口径!BT26 -> 24 | N26: =原始输入与口径!BJ26 -> 24 | O26: =M26*AF26*AC26 -> 2.4920229 | P26: =N26*AG26*AC26 -> 0 | Q26: =IF(K26=0,0,IF(ISNUMBER(B26),K26*B26*AC26,NA())) -> -926.04 | R26: =IF(L26=0,0,IF(ISNUMBER(C26),L26*C26*AC26,NA())) -> 662.24535 | S26: =IF(M26=0,0,IF(ISNUMBER(D26),M26*D26*AC26,NA())) -> 42.76485 | T26: =IF(N26=0,0,IF(ISNUMBER(E26),N26*E26*AC26,NA())) -> 30.46138 | U26: =IF(O26=0,0,O26*F26) -> 565.72476 | V26: =IF(P26=0,0,-P26*G26) -> 0 | W26: =SUM(Q26:V26) -> 375.15634 | X26: =原始输入与口径!CP26 -> 375.15634 | Y26: =W26-X26 -> 0 | Z26: ="当日执行" -> 当日执行 | AA26: =IF(原始输入与口径!AW26,1,0) -> 1 | AB26: =IF(原始输入与口径!AY26,1,0) -> 1 | AC26: =原始输入与口径!$F$5 -> 0.25 | AD26: =原始输入与口径!CG26 -> 0.3125 | AE26: =原始输入与口径!BQ26 -> 0.13714286 | AF26: =IF(AA26=0,0,AJ26/(AH26*AC26)) -> 0.41533714 | AG26: =IF(AA26=0,0,AK26/(AI26*AC26)) -> 0 | AH26: =IF(ISNUMBER(原始输入与口径!T26),原始输入与口径!T26,"缺失") -> 175 | AI26: =IF(ISNUMBER(原始输入与口径!Y26),原始输入与口径!Y26,"缺失") -> 175 | AJ26: =IF(ISNUMBER(原始输入与口径!AI26),原始输入与口径!AI26,"缺失") -> 18.171 | AK26: =IF(ISNUMBER(原始输入与口径!AL26),原始输入与口径!AL26,"缺失") -> 0 | AL26: =IF(ISNUMBER(原始输入与口径!O26),原始输入与口径!O26,"缺失") -> 128 | AM26: =SUMIFS(相位SOC复算!$N$9:$N$929,相位SOC复算!$S$9:$S$929,18) -> 0.0089648305 | AN26: =SUMIFS(相位SOC复算!$Q$9:$Q$929,相位SOC复算!$S$9:$S$929,18) -> 3.5079771 | AO26: =SUMIFS(相位SOC复算!$R$9:$R$929,相位SOC复算!$S$9:$S$929,18) -> 0 | AP26: =相位SOC复算!J46 -> 40.124177 | AQ26: =AP26-J26 -> 0 | AR26: =IF(ISBLANK(原始输入与口径!M26),"",原始输入与口径!M26) -> 5.2473 | AS26: =IF(ISBLANK(原始输入与口径!L26),"",原始输入与口径!L26) -> 46234 | AT26: =IF(ISBLANK(原始输入与口径!A26),"",原始输入与口径!A26) -> 46235.052 | AU26: =IF(ISBLANK(原始输入与口径!I26),"",原始输入与口径!I26) -> 2026-08-01_14 | AV26: =IF(ISBLANK(原始输入与口径!J26),"",原始输入与口径!J26) -> 15 | AW26: =IF(ISBLANK(原始输入与口径!BB26),"",原始输入与口径!BB26) -> OK | AX26: =原始输入与口径!CI26 -> 128 | AY26: =原始输入与口径!BS26 -> 175 | AZ26: =原始输入与口径!BI26 -> 175 | BA26: =原始输入与口径!CM26 -> 40 | BB26: =原始输入与口径!BV26 -> 24 | BC26: =原始输入与口径!BL26 -> 24 | BD26: =46235 -> 46235 | BE26: =IF(K26=0,"零头寸，无结算现金",TEXT(K26,"0.000000")&" MW × "&TEXT(B26,"0.000000")&" × "&TEXT(AC26,"0.000000")&" h = "&TEXT(Q26,"0.000000")&" EUR") -> -24.000000 MW × 154.340000 × 0.250000 h = -926.040000 EUR | BF26: =IF(L26=0,"零头寸，无结算现金",TEXT(L26,"0.000000")&" MW × "&TEXT(C26,"0.000000")&" × "&TEXT(AC26,"0.000000")&" h = "&TEXT(R26,"0.000000")&" EUR") -> 40.000000 MW × 66.224535 × 0.250000 h = 662.245345 EUR | BG26: =IF(M26=0,"零头寸，无结算现金",TEXT(M26,"0.000000")&" MW × "&TEXT(D26,"0.000000")&" × "&TEXT(AC26,"0.000000")&" h = "&TEXT(S26,"0.000000")&" EUR") -> 24.000000 MW × 7.127475 × 0.250000 h = 42.764850 EUR | BH26: =IF(N26=0,"零头寸，无结算现金",TEXT(N26,"0.000000")&" MW × "&TEXT(E26,"0.000000")&" × "&TEXT(AC26,"0.000000")&" h = "&TEXT(T26,"0.000000")&" EUR") -> 24.000000 MW × 5.076897 × 0.250000 h = 30.461380 EUR | BI26: =IF(O26=0,"零上调激活电量",TEXT(O26,"0.000000")&" MWh × "&TEXT(F26,"0.000000")&" = "&TEXT(U26,"0.000000")&" EUR") -> 2.492023 MWh × 227.014274 = 565.724760 EUR | BJ26: =IF(P26=0,"零下调激活电量","−("&TEXT(P26,"0.000000")&" MWh × "&TEXT(G26,"0.000000")&") = "&TEXT(V26,"0.000000")&" EUR") -> 零下调激活电量 | BK26: =TEXT(Q26,"0.000000")&" + "&TEXT(R26,"0.000000")&" + "&TEXT(S26,"0.000000")&" + "&TEXT(T26,"0.000000")&" + "&TEXT(U26,"0.000000")&" + "&TEXT(V26,"0.000000")&" = "&TEXT(W26,"0.000000")&" EUR" -> -926.040000 + 662.245345 + 42.764850 + 30.461380 + 565.724760 + 0.000000 = 375.156336 EUR
A27: =原始输入与口径!C27 -> 46235.188 | B27: =IF(ISNUMBER(原始输入与口径!H27),原始输入与口径!H27,"缺失") -> 156.18 | C27: =IF(ISNUMBER(原始输入与口径!R27),原始输入与口径!R27,"缺失") -> 66.224535 | D27: =IF(ISNUMBER(原始输入与口径!W27),原始输入与口径!W27,"缺失") -> 7.1274751 | E27: =IF(ISNUMBER(原始输入与口径!AB27),原始输入与口径!AB27,"缺失") -> 5.0768967 | F27: =IF(ISNUMBER(原始输入与口径!AG27),原始输入与口径!AG27,"缺失") -> 243.39432 | G27: =IF(ISNUMBER(原始输入与口径!AJ27),原始输入与口径!AJ27,"缺失") -> 0 | H27: ="未模拟" -> 未模拟 | I27: =原始输入与口径!CD27 -> 40.124177 | J27: =原始输入与口径!CE27 -> 37.122388 | K27: =原始输入与口径!BZ27 -> 0 | L27: =原始输入与口径!CK27 -> 40 | M27: =原始输入与口径!BT27 -> 24 | N27: =原始输入与口径!BJ27 -> 24 | O27: =M27*AF27*AC27 -> 2.7616457 | P27: =N27*AG27*AC27 -> 0 | Q27: =IF(K27=0,0,IF(ISNUMBER(B27),K27*B27*AC27,NA())) -> 0 | R27: =IF(L27=0,0,IF(ISNUMBER(C27),L27*C27*AC27,NA())) -> 662.24535 | S27: =IF(M27=0,0,IF(ISNUMBER(D27),M27*D27*AC27,NA())) -> 42.76485 | T27: =IF(N27=0,0,IF(ISNUMBER(E27),N27*E27*AC27,NA())) -> 30.46138 | U27: =IF(O27=0,0,O27*F27) -> 672.16887 | V27: =IF(P27=0,0,-P27*G27) -> 0 | W27: =SUM(Q27:V27) -> 1407.6404 | X27: =原始输入与口径!CP27 -> 1407.6404 | Y27: =W27-X27 -> 0 | Z27: ="当日执行" -> 当日执行 | AA27: =IF(原始输入与口径!AW27,1,0) -> 1 | AB27: =IF(原始输入与口径!AY27,1,0) -> 1 | AC27: =原始输入与口径!$F$5 -> 0.25 | AD27: =原始输入与口径!CG27 -> 0.3125 | AE27: =原始输入与口径!BQ27 -> 0.13714286 | AF27: =IF(AA27=0,0,AJ27/(AH27*AC27)) -> 0.46027429 | AG27: =IF(AA27=0,0,AK27/(AI27*AC27)) -> 0 | AH27: =IF(ISNUMBER(原始输入与口径!T27),原始输入与口径!T27,"缺失") -> 175 | AI27: =IF(ISNUMBER(原始输入与口径!Y27),原始输入与口径!Y27,"缺失") -> 175 | AJ27: =IF(ISNUMBER(原始输入与口径!AI27),原始输入与口径!AI27,"缺失") -> 20.137 | AK27: =IF(ISNUMBER(原始输入与口径!AL27),原始输入与口径!AL27,"缺失") -> 0 | AL27: =IF(ISNUMBER(原始输入与口径!O27),原始输入与口径!O27,"缺失") -> 128 | AM27: =SUMIFS(相位SOC复算!$N$9:$N$929,相位SOC复算!$S$9:$S$929,19) -> 0.0083383023 | AN27: =SUMIFS(相位SOC复算!$Q$9:$Q$929,相位SOC复算!$S$9:$S$929,19) -> 0 | AO27: =SUMIFS(相位SOC复算!$R$9:$R$929,相位SOC复算!$S$9:$S$929,19) -> 2.7616457 | AP27: =相位SOC复算!J48 -> 37.122388 | AQ27: =AP27-J27 -> 0 | AR27: =IF(ISBLANK(原始输入与口径!M27),"",原始输入与口径!M27) -> 5.2473 | AS27: =IF(ISBLANK(原始输入与口径!L27),"",原始输入与口径!L27) -> 46234 | AT27: =IF(ISBLANK(原始输入与口径!A27),"",原始输入与口径!A27) -> 46235.062 | AU27: =IF(ISBLANK(原始输入与口径!I27),"",原始输入与口径!I27) -> 2026-08-01_15 | AV27: =IF(ISBLANK(原始输入与口径!J27),"",原始输入与口径!J27) -> 15 | AW27: =IF(ISBLANK(原始输入与口径!BB27),"",原始输入与口径!BB27) -> OK | AX27: =原始输入与口径!CI27 -> 128 | AY27: =原始输入与口径!BS27 -> 175 | AZ27: =原始输入与口径!BI27 -> 175 | BA27: =原始输入与口径!CM27 -> 40 | BB27: =原始输入与口径!BV27 -> 24 | BC27: =原始输入与口径!BL27 -> 24 | BD27: =46235 -> 46235 | BE27: =IF(K27=0,"零头寸，无结算现金",TEXT(K27,"0.000000")&" MW × "&TEXT(B27,"0.000000")&" × "&TEXT(AC27,"0.000000")&" h = "&TEXT(Q27,"0.000000")&" EUR") -> 零头寸，无结算现金 | BF27: =IF(L27=0,"零头寸，无结算现金",TEXT(L27,"0.000000")&" MW × "&TEXT(C27,"0.000000")&" × "&TEXT(AC27,"0.000000")&" h = "&TEXT(R27,"0.000000")&" EUR") -> 40.000000 MW × 66.224535 × 0.250000 h = 662.245345 EUR | BG27: =IF(M27=0,"零头寸，无结算现金",TEXT(M27,"0.000000")&" MW × "&TEXT(D27,"0.000000")&" × "&TEXT(AC27,"0.000000")&" h = "&TEXT(S27,"0.000000")&" EUR") -> 24.000000 MW × 7.127475 × 0.250000 h = 42.764850 EUR | BH27: =IF(N27=0,"零头寸，无结算现金",TEXT(N27,"0.000000")&" MW × "&TEXT(E27,"0.000000")&" × "&TEXT(AC27,"0.000000")&" h = "&TEXT(T27,"0.000000")&" EUR") -> 24.000000 MW × 5.076897 × 0.250000 h = 30.461380 EUR | BI27: =IF(O27=0,"零上调激活电量",TEXT(O27,"0.000000")&" MWh × "&TEXT(F27,"0.000000")&" = "&TEXT(U27,"0.000000")&" EUR") -> 2.761646 MWh × 243.394317 = 672.168873 EUR | BJ27: =IF(P27=0,"零下调激活电量","−("&TEXT(P27,"0.000000")&" MWh × "&TEXT(G27,"0.000000")&") = "&TEXT(V27,"0.000000")&" EUR") -> 零下调激活电量 | BK27: =TEXT(Q27,"0.000000")&" + "&TEXT(R27,"0.000000")&" + "&TEXT(S27,"0.000000")&" + "&TEXT(T27,"0.000000")&" + "&TEXT(U27,"0.000000")&" + "&TEXT(V27,"0.000000")&" = "&TEXT(W27,"0.000000")&" EUR" -> 0.000000 + 662.245345 + 42.764850 + 30.461380 + 672.168873 + 0.000000 = 1407.640448 EUR
A28: =原始输入与口径!C28 -> 46235.198 | B28: =IF(ISNUMBER(原始输入与口径!H28),原始输入与口径!H28,"缺失") -> 154.47 | C28: =IF(ISNUMBER(原始输入与口径!R28),原始输入与口径!R28,"缺失") -> 66.224535 | D28: =IF(ISNUMBER(原始输入与口径!W28),原始输入与口径!W28,"缺失") -> 7.1274751 | E28: =IF(ISNUMBER(原始输入与口径!AB28),原始输入与口径!AB28,"缺失") -> 5.0768967 | F28: =IF(ISNUMBER(原始输入与口径!AG28),原始输入与口径!AG28,"缺失") -> 186.71069 | G28: =IF(ISNUMBER(原始输入与口径!AJ28),原始输入与口径!AJ28,"缺失") -> 0 | H28: ="未模拟" -> 未模拟 | I28: =原始输入与口径!CD28 -> 37.122388 | J28: =原始输入与口径!CE28 -> 35.86291 | K28: =原始输入与口径!BZ28 -> 0 | L28: =原始输入与口径!CK28 -> 40 | M28: =原始输入与口径!BT28 -> 24 | N28: =原始输入与口径!BJ28 -> 24 | O28: =M28*AF28*AC28 -> 1.15872 | P28: =N28*AG28*AC28 -> 0 | Q28: =IF(K28=0,0,IF(ISNUMBER(B28),K28*B28*AC28,NA())) -> 0 | R28: =IF(L28=0,0,IF(ISNUMBER(C28),L28*C28*AC28,NA())) -> 662.24535 | S28: =IF(M28=0,0,IF(ISNUMBER(D28),M28*D28*AC28,NA())) -> 42.76485 | T28: =IF(N28=0,0,IF(ISNUMBER(E28),N28*E28*AC28,NA())) -> 30.46138 | U28: =IF(O28=0,0,O28*F28) -> 216.34541 | V28: =IF(P28=0,0,-P28*G28) -> 0 | W28: =SUM(Q28:V28) -> 951.81699 | X28: =原始输入与口径!CP28 -> 951.81699 | Y28: =W28-X28 -> 0 | Z28: ="当日执行" -> 当日执行 | AA28: =IF(原始输入与口径!AW28,1,0) -> 1 | AB28: =IF(原始输入与口径!AY28,1,0) -> 1 | AC28: =原始输入与口径!$F$5 -> 0.25 | AD28: =原始输入与口径!CG28 -> 0.3125 | AE28: =原始输入与口径!BQ28 -> 0.13714286 | AF28: =IF(AA28=0,0,AJ28/(AH28*AC28)) -> 0.19312 | AG28: =IF(AA28=0,0,AK28/(AI28*AC28)) -> 0 | AH28: =IF(ISNUMBER(原始输入与口径!T28),原始输入与口径!T28,"缺失") -> 175 | AI28: =IF(ISNUMBER(原始输入与口径!Y28),原始输入与口径!Y28,"缺失") -> 175 | AJ28: =IF(ISNUMBER(原始输入与口径!AI28),原始输入与口径!AI28,"缺失") -> 8.449 | AK28: =IF(ISNUMBER(原始输入与口径!AL28),原始输入与口径!AL28,"缺失") -> 0 | AL28: =IF(ISNUMBER(原始输入与口径!O28),原始输入与口径!O28,"缺失") -> 128 | AM28: =SUMIFS(相位SOC复算!$N$9:$N$929,相位SOC复算!$S$9:$S$929,20) -> 0.0034985507 | AN28: =SUMIFS(相位SOC复算!$Q$9:$Q$929,相位SOC复算!$S$9:$S$929,20) -> 0 | AO28: =SUMIFS(相位SOC复算!$R$9:$R$929,相位SOC复算!$S$9:$S$929,20) -> 1.15872 | AP28: =相位SOC复算!J50 -> 35.86291 | AQ28: =AP28-J28 -> 0 | AR28: =IF(ISBLANK(原始输入与口径!M28),"",原始输入与口径!M28) -> 5.2473 | AS28: =IF(ISBLANK(原始输入与口径!L28),"",原始输入与口径!L28) -> 46234 | AT28: =IF(ISBLANK(原始输入与口径!A28),"",原始输入与口径!A28) -> 46235.073 | AU28: =IF(ISBLANK(原始输入与口径!I28),"",原始输入与口径!I28) -> 2026-08-01_16 | AV28: =IF(ISBLANK(原始输入与口径!J28),"",原始输入与口径!J28) -> 15 | AW28: =IF(ISBLANK(原始输入与口径!BB28),"",原始输入与口径!BB28) -> OK | AX28: =原始输入与口径!CI28 -> 128 | AY28: =原始输入与口径!BS28 -> 175 | AZ28: =原始输入与口径!BI28 -> 175 | BA28: =原始输入与口径!CM28 -> 40 | BB28: =原始输入与口径!BV28 -> 24 | BC28: =原始输入与口径!BL28 -> 24 | BD28: =46235 -> 46235 | BE28: =IF(K28=0,"零头寸，无结算现金",TEXT(K28,"0.000000")&" MW × "&TEXT(B28,"0.000000")&" × "&TEXT(AC28,"0.000000")&" h = "&TEXT(Q28,"0.000000")&" EUR") -> 零头寸，无结算现金 | BF28: =IF(L28=0,"零头寸，无结算现金",TEXT(L28,"0.000000")&" MW × "&TEXT(C28,"0.000000")&" × "&TEXT(AC28,"0.000000")&" h = "&TEXT(R28,"0.000000")&" EUR") -> 40.000000 MW × 66.224535 × 0.250000 h = 662.245345 EUR | BG28: =IF(M28=0,"零头寸，无结算现金",TEXT(M28,"0.000000")&" MW × "&TEXT(D28,"0.000000")&" × "&TEXT(AC28,"0.000000")&" h = "&TEXT(S28,"0.000000")&" EUR") -> 24.000000 MW × 7.127475 × 0.250000 h = 42.764850 EUR | BH28: =IF(N28=0,"零头寸，无结算现金",TEXT(N28,"0.000000")&" MW × "&TEXT(E28,"0.000000")&" × "&TEXT(AC28,"0.000000")&" h = "&TEXT(T28,"0.000000")&" EUR") -> 24.000000 MW × 5.076897 × 0.250000 h = 30.461380 EUR | BI28: =IF(O28=0,"零上调激活电量",TEXT(O28,"0.000000")&" MWh × "&TEXT(F28,"0.000000")&" = "&TEXT(U28,"0.000000")&" EUR") -> 1.158720 MWh × 186.710689 = 216.345410 EUR | BJ28: =IF(P28=0,"零下调激活电量","−("&TEXT(P28,"0.000000")&" MWh × "&TEXT(G28,"0.000000")&") = "&TEXT(V28,"0.000000")&" EUR") -> 零下调激活电量 | BK28: =TEXT(Q28,"0.000000")&" + "&TEXT(R28,"0.000000")&" + "&TEXT(S28,"0.000000")&" + "&TEXT(T28,"0.000000")&" + "&TEXT(U28,"0.000000")&" + "&TEXT(V28,"0.000000")&" = "&TEXT(W28,"0.000000")&" EUR" -> 0.000000 + 662.245345 + 42.764850 + 30.461380 + 216.345410 + 0.000000 = 951.816986 EUR
A29: =原始输入与口径!C29 -> 46235.208 | B29: =IF(ISNUMBER(原始输入与口径!H29),原始输入与口径!H29,"缺失") -> 157.06 | C29: =IF(ISNUMBER(原始输入与口径!R29),原始输入与口径!R29,"缺失") -> 66.224535 | D29: =IF(ISNUMBER(原始输入与口径!W29),原始输入与口径!W29,"缺失") -> 7.1274751 | E29: =IF(ISNUMBER(原始输入与口径!AB29),原始输入与口径!AB29,"缺失") -> 5.0730852 | F29: =IF(ISNUMBER(原始输入与口径!AG29),原始输入与口径!AG29,"缺失") -> 177.26145 | G29: =IF(ISNUMBER(原始输入与口径!AJ29),原始输入与口径!AJ29,"缺失") -> 0 | H29: ="未模拟" -> 未模拟 | I29: =原始输入与口径!CD29 -> 35.86291 | J29: =原始输入与口径!CE29 -> 35.076425 | K29: =原始输入与口径!BZ29 -> 0 | L29: =原始输入与口径!CK29 -> 40 | M29: =原始输入与口径!BT29 -> 24 | N29: =原始输入与口径!BJ29 -> 24 | O29: =M29*AF29*AC29 -> 0.72356571 | P29: =N29*AG29*AC29 -> 0 | Q29: =IF(K29=0,0,IF(ISNUMBER(B29),K29*B29*AC29,NA())) -> 0 | R29: =IF(L29=0,0,IF(ISNUMBER(C29),L29*C29*AC29,NA())) -> 662.24535 | S29: =IF(M29=0,0,IF(ISNUMBER(D29),M29*D29*AC29,NA())) -> 42.76485 | T29: =IF(N29=0,0,IF(ISNUMBER(E29),N29*E29*AC29,NA())) -> 30.438511 | U29: =IF(O29=0,0,O29*F29) -> 128.26031 | V29: =IF(P29=0,0,-P29*G29) -> 0 | W29: =SUM(Q29:V29) -> 863.70901 | X29: =原始输入与口径!CP29 -> 863.70901 | Y29: =W29-X29 -> 0 | Z29: ="当日执行" -> 当日执行 | AA29: =IF(原始输入与口径!AW29,1,0) -> 1 | AB29: =IF(原始输入与口径!AY29,1,0) -> 1 | AC29: =原始输入与口径!$F$5 -> 0.25 | AD29: =原始输入与口径!CG29 -> 0.3125 | AE29: =原始输入与口径!BQ29 -> 0.13714286 | AF29: =IF(AA29=0,0,AJ29/(AH29*AC29)) -> 0.12059429 | AG29: =IF(AA29=0,0,AK29/(AI29*AC29)) -> 0 | AH29: =IF(ISNUMBER(原始输入与口径!T29),原始输入与口径!T29,"缺失") -> 175 | AI29: =IF(ISNUMBER(原始输入与口径!Y29),原始输入与口径!Y29,"缺失") -> 175 | AJ29: =IF(ISNUMBER(原始输入与口径!AI29),原始输入与口径!AI29,"缺失") -> 5.276 | AK29: =IF(ISNUMBER(原始输入与口径!AL29),原始输入与口径!AL29,"缺失") -> 0 | AL29: =IF(ISNUMBER(原始输入与口径!O29),原始输入与口径!O29,"缺失") -> 128 | AM29: =SUMIFS(相位SOC复算!$N$9:$N$929,相位SOC复算!$S$9:$S$929,21) -> 0.0021846791 | AN29: =SUMIFS(相位SOC复算!$Q$9:$Q$929,相位SOC复算!$S$9:$S$929,21) -> 0 | AO29: =SUMIFS(相位SOC复算!$R$9:$R$929,相位SOC复算!$S$9:$S$929,21) -> 0.72356571 | AP29: =相位SOC复算!J52 -> 35.076425 | AQ29: =AP29-J29 -> 0 | AR29: =IF(ISBLANK(原始输入与口径!M29),"",原始输入与口径!M29) -> 5.2473 | AS29: =IF(ISBLANK(原始输入与口径!L29),"",原始输入与口径!L29) -> 46234 | AT29: =IF(ISBLANK(原始输入与口径!A29),"",原始输入与口径!A29) -> 46235.083 | AU29: =IF(ISBLANK(原始输入与口径!I29),"",原始输入与口径!I29) -> 2026-08-01_17 | AV29: =IF(ISBLANK(原始输入与口径!J29),"",原始输入与口径!J29) -> 15 | AW29: =IF(ISBLANK(原始输入与口径!BB29),"",原始输入与口径!BB29) -> OK | AX29: =原始输入与口径!CI29 -> 128 | AY29: =原始输入与口径!BS29 -> 175 | AZ29: =原始输入与口径!BI29 -> 175 | BA29: =原始输入与口径!CM29 -> 40 | BB29: =原始输入与口径!BV29 -> 24 | BC29: =原始输入与口径!BL29 -> 24 | BD29: =46235 -> 46235 | BE29: =IF(K29=0,"零头寸，无结算现金",TEXT(K29,"0.000000")&" MW × "&TEXT(B29,"0.000000")&" × "&TEXT(AC29,"0.000000")&" h = "&TEXT(Q29,"0.000000")&" EUR") -> 零头寸，无结算现金 | BF29: =IF(L29=0,"零头寸，无结算现金",TEXT(L29,"0.000000")&" MW × "&TEXT(C29,"0.000000")&" × "&TEXT(AC29,"0.000000")&" h = "&TEXT(R29,"0.000000")&" EUR") -> 40.000000 MW × 66.224535 × 0.250000 h = 662.245345 EUR | BG29: =IF(M29=0,"零头寸，无结算现金",TEXT(M29,"0.000000")&" MW × "&TEXT(D29,"0.000000")&" × "&TEXT(AC29,"0.000000")&" h = "&TEXT(S29,"0.000000")&" EUR") -> 24.000000 MW × 7.127475 × 0.250000 h = 42.764850 EUR | BH29: =IF(N29=0,"零头寸，无结算现金",TEXT(N29,"0.000000")&" MW × "&TEXT(E29,"0.000000")&" × "&TEXT(AC29,"0.000000")&" h = "&TEXT(T29,"0.000000")&" EUR") -> 24.000000 MW × 5.073085 × 0.250000 h = 30.438511 EUR | BI29: =IF(O29=0,"零上调激活电量",TEXT(O29,"0.000000")&" MWh × "&TEXT(F29,"0.000000")&" = "&TEXT(U29,"0.000000")&" EUR") -> 0.723566 MWh × 177.261449 = 128.260307 EUR | BJ29: =IF(P29=0,"零下调激活电量","−("&TEXT(P29,"0.000000")&" MWh × "&TEXT(G29,"0.000000")&") = "&TEXT(V29,"0.000000")&" EUR") -> 零下调激活电量 | BK29: =TEXT(Q29,"0.000000")&" + "&TEXT(R29,"0.000000")&" + "&TEXT(S29,"0.000000")&" + "&TEXT(T29,"0.000000")&" + "&TEXT(U29,"0.000000")&" + "&TEXT(V29,"0.000000")&" = "&TEXT(W29,"0.000000")&" EUR" -> 0.000000 + 662.245345 + 42.764850 + 30.438511 + 128.260307 + 0.000000 = 863.709014 EUR
A30: =原始输入与口径!C30 -> 46235.219 | B30: =IF(ISNUMBER(原始输入与口径!H30),原始输入与口径!H30,"缺失") -> 161.38 | C30: =IF(ISNUMBER(原始输入与口径!R30),原始输入与口径!R30,"缺失") -> 66.224535 | D30: =IF(ISNUMBER(原始输入与口径!W30),原始输入与口径!W30,"缺失") -> 7.1274751 | E30: =IF(ISNUMBER(原始输入与口径!AB30),原始输入与口径!AB30,"缺失") -> 5.0730852 | F30: =IF(ISNUMBER(原始输入与口径!AG30),原始输入与口径!AG30,"缺失") -> 211.85848 | G30: =IF(ISNUMBER(原始输入与口径!AJ30),原始输入与口径!AJ30,"缺失") -> 0 | H30: ="未模拟" -> 未模拟 | I30: =原始输入与口径!CD30 -> 35.076425 | J30: =原始输入与口径!CE30 -> 33.137941 | K30: =原始输入与口径!BZ30 -> 0 | L30: =原始输入与口径!CK30 -> 40 | M30: =原始输入与口径!BT30 -> 24 | N30: =原始输入与口径!BJ30 -> 24 | O30: =M30*AF30*AC30 -> 1.7834057 | P30: =N30*AG30*AC30 -> 0 | Q30: =IF(K30=0,0,IF(ISNUMBER(B30),K30*B30*AC30,NA())) -> 0 | R30: =IF(L30=0,0,IF(ISNUMBER(C30),L30*C30*AC30,NA())) -> 662.24535 | S30: =IF(M30=0,0,IF(ISNUMBER(D30),M30*D30*AC30,NA())) -> 42.76485 | T30: =IF(N30=0,0,IF(ISNUMBER(E30),N30*E30*AC30,NA())) -> 30.438511 | U30: =IF(O30=0,0,O30*F30) -> 377.82962 | V30: =IF(P30=0,0,-P30*G30) -> 0 | W30: =SUM(Q30:V30) -> 1113.2783 | X30: =原始输入与口径!CP30 -> 1113.2783 | Y30: =W30-X30 -> 0 | Z30: ="当日执行" -> 当日执行 | AA30: =IF(原始输入与口径!AW30,1,0) -> 1 | AB30: =IF(原始输入与口径!AY30,1,0) -> 1 | AC30: =原始输入与口径!$F$5 -> 0.25 | AD30: =原始输入与口径!CG30 -> 0.3125 | AE30: =原始输入与口径!BQ30 -> 0.13714286 | AF30: =IF(AA30=0,0,AJ30/(AH30*AC30)) -> 0.29723429 | AG30: =IF(AA30=0,0,AK30/(AI30*AC30)) -> 0 | AH30: =IF(ISNUMBER(原始输入与口径!T30),原始输入与口径!T30,"缺失") -> 175 | AI30: =IF(ISNUMBER(原始输入与口径!Y30),原始输入与口径!Y30,"缺失") -> 175 | AJ30: =IF(ISNUMBER(原始输入与口径!AI30),原始输入与口径!AI30,"缺失") -> 13.004 | AK30: =IF(ISNUMBER(原始输入与口径!AL30),原始输入与口径!AL30,"缺失") -> 0 | AL30: =IF(ISNUMBER(原始输入与口径!O30),原始输入与口径!O30,"缺失") -> 128 | AM30: =SUMIFS(相位SOC复算!$N$9:$N$929,相位SOC复算!$S$9:$S$929,22) -> 0.0053846791 | AN30: =SUMIFS(相位SOC复算!$Q$9:$Q$929,相位SOC复算!$S$9:$S$929,22) -> 0 | AO30: =SUMIFS(相位SOC复算!$R$9:$R$929,相位SOC复算!$S$9:$S$929,22) -> 1.7834057 | AP30: =相位SOC复算!J54 -> 33.137941 | AQ30: =AP30-J30 -> 0 | AR30: =IF(ISBLANK(原始输入与口径!M30),"",原始输入与口径!M30) -> 5.2473 | AS30: =IF(ISBLANK(原始输入与口径!L30),"",原始输入与口径!L30) -> 46234 | AT30: =IF(ISBLANK(原始输入与口径!A30),"",原始输入与口径!A30) -> 46235.094 | AU30: =IF(ISBLANK(原始输入与口径!I30),"",原始输入与口径!I30) -> 2026-08-01_18 | AV30: =IF(ISBLANK(原始输入与口径!J30),"",原始输入与口径!J30) -> 15 | AW30: =IF(ISBLANK(原始输入与口径!BB30),"",原始输入与口径!BB30) -> OK | AX30: =原始输入与口径!CI30 -> 128 | AY30: =原始输入与口径!BS30 -> 175 | AZ30: =原始输入与口径!BI30 -> 175 | BA30: =原始输入与口径!CM30 -> 40 | BB30: =原始输入与口径!BV30 -> 24 | BC30: =原始输入与口径!BL30 -> 24 | BD30: =46235 -> 46235 | BE30: =IF(K30=0,"零头寸，无结算现金",TEXT(K30,"0.000000")&" MW × "&TEXT(B30,"0.000000")&" × "&TEXT(AC30,"0.000000")&" h = "&TEXT(Q30,"0.000000")&" EUR") -> 零头寸，无结算现金 | BF30: =IF(L30=0,"零头寸，无结算现金",TEXT(L30,"0.000000")&" MW × "&TEXT(C30,"0.000000")&" × "&TEXT(AC30,"0.000000")&" h = "&TEXT(R30,"0.000000")&" EUR") -> 40.000000 MW × 66.224535 × 0.250000 h = 662.245345 EUR | BG30: =IF(M30=0,"零头寸，无结算现金",TEXT(M30,"0.000000")&" MW × "&TEXT(D30,"0.000000")&" × "&TEXT(AC30,"0.000000")&" h = "&TEXT(S30,"0.000000")&" EUR") -> 24.000000 MW × 7.127475 × 0.250000 h = 42.764850 EUR | BH30: =IF(N30=0,"零头寸，无结算现金",TEXT(N30,"0.000000")&" MW × "&TEXT(E30,"0.000000")&" × "&TEXT(AC30,"0.000000")&" h = "&TEXT(T30,"0.000000")&" EUR") -> 24.000000 MW × 5.073085 × 0.250000 h = 30.438511 EUR | BI30: =IF(O30=0,"零上调激活电量",TEXT(O30,"0.000000")&" MWh × "&TEXT(F30,"0.000000")&" = "&TEXT(U30,"0.000000")&" EUR") -> 1.783406 MWh × 211.858480 = 377.829623 EUR | BJ30: =IF(P30=0,"零下调激活电量","−("&TEXT(P30,"0.000000")&" MWh × "&TEXT(G30,"0.000000")&") = "&TEXT(V30,"0.000000")&" EUR") -> 零下调激活电量 | BK30: =TEXT(Q30,"0.000000")&" + "&TEXT(R30,"0.000000")&" + "&TEXT(S30,"0.000000")&" + "&TEXT(T30,"0.000000")&" + "&TEXT(U30,"0.000000")&" + "&TEXT(V30,"0.000000")&" = "&TEXT(W30,"0.000000")&" EUR" -> 0.000000 + 662.245345 + 42.764850 + 30.438511 + 377.829623 + 0.000000 = 1113.278330 EUR
A31: =原始输入与口径!C31 -> 46235.229 | B31: =IF(ISNUMBER(原始输入与口径!H31),原始输入与口径!H31,"缺失") -> 154.83 | C31: =IF(ISNUMBER(原始输入与口径!R31),原始输入与口径!R31,"缺失") -> 66.224535 | D31: =IF(ISNUMBER(原始输入与口径!W31),原始输入与口径!W31,"缺失") -> 7.1274751 | E31: =IF(ISNUMBER(原始输入与口径!AB31),原始输入与口径!AB31,"缺失") -> 5.0730852 | F31: =IF(ISNUMBER(原始输入与口径!AG31),原始输入与口径!AG31,"缺失") -> 248.52343 | G31: =IF(ISNUMBER(原始输入与口径!AJ31),原始输入与口径!AJ31,"缺失") -> 0 | H31: ="未模拟" -> 未模拟 | I31: =原始输入与口径!CD31 -> 33.137941 | J31: =原始输入与口径!CE31 -> 35.80041 | K31: =原始输入与口径!BZ31 -> -24 | L31: =原始输入与口径!CK31 -> 40 | M31: =原始输入与口径!BT31 -> 24 | N31: =原始输入与口径!BJ31 -> 24 | O31: =M31*AF31*AC31 -> 3.1060114 | P31: =N31*AG31*AC31 -> 0 | Q31: =IF(K31=0,0,IF(ISNUMBER(B31),K31*B31*AC31,NA())) -> -928.98 | R31: =IF(L31=0,0,IF(ISNUMBER(C31),L31*C31*AC31,NA())) -> 662.24535 | S31: =IF(M31=0,0,IF(ISNUMBER(D31),M31*D31*AC31,NA())) -> 42.76485 | T31: =IF(N31=0,0,IF(ISNUMBER(E31),N31*E31*AC31,NA())) -> 30.438511 | U31: =IF(O31=0,0,O31*F31) -> 771.91662 | V31: =IF(P31=0,0,-P31*G31) -> 0 | W31: =SUM(Q31:V31) -> 578.38532 | X31: =原始输入与口径!CP31 -> 578.38532 | Y31: =W31-X31 -> 0 | Z31: ="当日执行" -> 当日执行 | AA31: =IF(原始输入与口径!AW31,1,0) -> 1 | AB31: =IF(原始输入与口径!AY31,1,0) -> 1 | AC31: =原始输入与口径!$F$5 -> 0.25 | AD31: =原始输入与口径!CG31 -> 0.3125 | AE31: =原始输入与口径!BQ31 -> 0.13714286 | AF31: =IF(AA31=0,0,AJ31/(AH31*AC31)) -> 0.51766857 | AG31: =IF(AA31=0,0,AK31/(AI31*AC31)) -> 0 | AH31: =IF(ISNUMBER(原始输入与口径!T31),原始输入与口径!T31,"缺失") -> 175 | AI31: =IF(ISNUMBER(原始输入与口径!Y31),原始输入与口径!Y31,"缺失") -> 175 | AJ31: =IF(ISNUMBER(原始输入与口径!AI31),原始输入与口径!AI31,"缺失") -> 22.648 | AK31: =IF(ISNUMBER(原始输入与口径!AL31),原始输入与口径!AL31,"缺失") -> 0 | AL31: =IF(ISNUMBER(原始输入与口径!O31),原始输入与口径!O31,"缺失") -> 128 | AM31: =SUMIFS(相位SOC复算!$N$9:$N$929,相位SOC复算!$S$9:$S$929,23) -> 0.0073957486 | AN31: =SUMIFS(相位SOC复算!$Q$9:$Q$929,相位SOC复算!$S$9:$S$929,23) -> 2.8939886 | AO31: =SUMIFS(相位SOC复算!$R$9:$R$929,相位SOC复算!$S$9:$S$929,23) -> 0 | AP31: =相位SOC复算!J56 -> 35.80041 | AQ31: =AP31-J31 -> 0 | AR31: =IF(ISBLANK(原始输入与口径!M31),"",原始输入与口径!M31) -> 5.2473 | AS31: =IF(ISBLANK(原始输入与口径!L31),"",原始输入与口径!L31) -> 46234 | AT31: =IF(ISBLANK(原始输入与口径!A31),"",原始输入与口径!A31) -> 46235.104 | AU31: =IF(ISBLANK(原始输入与口径!I31),"",原始输入与口径!I31) -> 2026-08-01_19 | AV31: =IF(ISBLANK(原始输入与口径!J31),"",原始输入与口径!J31) -> 15 | AW31: =IF(ISBLANK(原始输入与口径!BB31),"",原始输入与口径!BB31) -> OK | AX31: =原始输入与口径!CI31 -> 128 | AY31: =原始输入与口径!BS31 -> 175 | AZ31: =原始输入与口径!BI31 -> 175 | BA31: =原始输入与口径!CM31 -> 40 | BB31: =原始输入与口径!BV31 -> 24 | BC31: =原始输入与口径!BL31 -> 24 | BD31: =46235 -> 46235 | BE31: =IF(K31=0,"零头寸，无结算现金",TEXT(K31,"0.000000")&" MW × "&TEXT(B31,"0.000000")&" × "&TEXT(AC31,"0.000000")&" h = "&TEXT(Q31,"0.000000")&" EUR") -> -24.000000 MW × 154.830000 × 0.250000 h = -928.980000 EUR | BF31: =IF(L31=0,"零头寸，无结算现金",TEXT(L31,"0.000000")&" MW × "&TEXT(C31,"0.000000")&" × "&TEXT(AC31,"0.000000")&" h = "&TEXT(R31,"0.000000")&" EUR") -> 40.000000 MW × 66.224535 × 0.250000 h = 662.245345 EUR | BG31: =IF(M31=0,"零头寸，无结算现金",TEXT(M31,"0.000000")&" MW × "&TEXT(D31,"0.000000")&" × "&TEXT(AC31,"0.000000")&" h = "&TEXT(S31,"0.000000")&" EUR") -> 24.000000 MW × 7.127475 × 0.250000 h = 42.764850 EUR | BH31: =IF(N31=0,"零头寸，无结算现金",TEXT(N31,"0.000000")&" MW × "&TEXT(E31,"0.000000")&" × "&TEXT(AC31,"0.000000")&" h = "&TEXT(T31,"0.000000")&" EUR") -> 24.000000 MW × 5.073085 × 0.250000 h = 30.438511 EUR | BI31: =IF(O31=0,"零上调激活电量",TEXT(O31,"0.000000")&" MWh × "&TEXT(F31,"0.000000")&" = "&TEXT(U31,"0.000000")&" EUR") -> 3.106011 MWh × 248.523431 = 771.916617 EUR | BJ31: =IF(P31=0,"零下调激活电量","−("&TEXT(P31,"0.000000")&" MWh × "&TEXT(G31,"0.000000")&") = "&TEXT(V31,"0.000000")&" EUR") -> 零下调激活电量 | BK31: =TEXT(Q31,"0.000000")&" + "&TEXT(R31,"0.000000")&" + "&TEXT(S31,"0.000000")&" + "&TEXT(T31,"0.000000")&" + "&TEXT(U31,"0.000000")&" + "&TEXT(V31,"0.000000")&" = "&TEXT(W31,"0.000000")&" EUR" -> -928.980000 + 662.245345 + 42.764850 + 30.438511 + 771.916617 + 0.000000 = 578.385324 EUR
A32: =原始输入与口径!C32 -> 46235.24 | B32: =IF(ISNUMBER(原始输入与口径!H32),原始输入与口径!H32,"缺失") -> 151.91 | C32: =IF(ISNUMBER(原始输入与口径!R32),原始输入与口径!R32,"缺失") -> 66.224535 | D32: =IF(ISNUMBER(原始输入与口径!W32),原始输入与口径!W32,"缺失") -> 7.1274751 | E32: =IF(ISNUMBER(原始输入与口径!AB32),原始输入与口径!AB32,"缺失") -> 5.0730852 | F32: =IF(ISNUMBER(原始输入与口径!AG32),原始输入与口径!AG32,"缺失") -> 254.40417 | G32: =IF(ISNUMBER(原始输入与口径!AJ32),原始输入与口径!AJ32,"缺失") -> 0 | H32: ="未模拟" -> 未模拟 | I32: =原始输入与口径!CD32 -> 35.80041 | J32: =原始输入与口径!CE32 -> 38.154264 | K32: =原始输入与口径!BZ32 -> -24 | L32: =原始输入与口径!CK32 -> 40 | M32: =原始输入与口径!BT32 -> 24 | N32: =原始输入与口径!BJ32 -> 24 | O32: =M32*AF32*AC32 -> 3.4414629 | P32: =N32*AG32*AC32 -> 0 | Q32: =IF(K32=0,0,IF(ISNUMBER(B32),K32*B32*AC32,NA())) -> -911.46 | R32: =IF(L32=0,0,IF(ISNUMBER(C32),L32*C32*AC32,NA())) -> 662.24535 | S32: =IF(M32=0,0,IF(ISNUMBER(D32),M32*D32*AC32,NA())) -> 42.76485 | T32: =IF(N32=0,0,IF(ISNUMBER(E32),N32*E32*AC32,NA())) -> 30.438511 | U32: =IF(O32=0,0,O32*F32) -> 875.5225 | V32: =IF(P32=0,0,-P32*G32) -> 0 | W32: =SUM(Q32:V32) -> 699.51121 | X32: =原始输入与口径!CP32 -> 699.51121 | Y32: =W32-X32 -> 0 | Z32: ="当日执行" -> 当日执行 | AA32: =IF(原始输入与口径!AW32,1,0) -> 1 | AB32: =IF(原始输入与口径!AY32,1,0) -> 1 | AC32: =原始输入与口径!$F$5 -> 0.25 | AD32: =原始输入与口径!CG32 -> 0.3125 | AE32: =原始输入与口径!BQ32 -> 0.13714286 | AF32: =IF(AA32=0,0,AJ32/(AH32*AC32)) -> 0.57357714 | AG32: =IF(AA32=0,0,AK32/(AI32*AC32)) -> 0 | AH32: =IF(ISNUMBER(原始输入与口径!T32),原始输入与口径!T32,"缺失") -> 175 | AI32: =IF(ISNUMBER(原始输入与口径!Y32),原始输入与口径!Y32,"缺失") -> 175 | AJ32: =IF(ISNUMBER(原始输入与口径!AI32),原始输入与口径!AI32,"缺失") -> 25.094 | AK32: =IF(ISNUMBER(原始输入与口径!AL32),原始输入与口径!AL32,"缺失") -> 0 | AL32: =IF(ISNUMBER(原始输入与口径!O32),原始输入与口径!O32,"缺失") -> 128 | AM32: =SUMIFS(相位SOC复算!$N$9:$N$929,相位SOC复算!$S$9:$S$929,24) -> 0.0065384838 | AN32: =SUMIFS(相位SOC复算!$Q$9:$Q$929,相位SOC复算!$S$9:$S$929,24) -> 2.5585371 | AO32: =SUMIFS(相位SOC复算!$R$9:$R$929,相位SOC复算!$S$9:$S$929,24) -> 0 | AP32: =相位SOC复算!J58 -> 38.154264 | AQ32: =AP32-J32 -> 0 | AR32: =IF(ISBLANK(原始输入与口径!M32),"",原始输入与口径!M32) -> 5.2473 | AS32: =IF(ISBLANK(原始输入与口径!L32),"",原始输入与口径!L32) -> 46234 | AT32: =IF(ISBLANK(原始输入与口径!A32),"",原始输入与口径!A32) -> 46235.115 | AU32: =IF(ISBLANK(原始输入与口径!I32),"",原始输入与口径!I32) -> 2026-08-01_20 | AV32: =IF(ISBLANK(原始输入与口径!J32),"",原始输入与口径!J32) -> 15 | AW32: =IF(ISBLANK(原始输入与口径!BB32),"",原始输入与口径!BB32) -> OK | AX32: =原始输入与口径!CI32 -> 128 | AY32: =原始输入与口径!BS32 -> 175 | AZ32: =原始输入与口径!BI32 -> 175 | BA32: =原始输入与口径!CM32 -> 40 | BB32: =原始输入与口径!BV32 -> 24 | BC32: =原始输入与口径!BL32 -> 24 | BD32: =46235 -> 46235 | BE32: =IF(K32=0,"零头寸，无结算现金",TEXT(K32,"0.000000")&" MW × "&TEXT(B32,"0.000000")&" × "&TEXT(AC32,"0.000000")&" h = "&TEXT(Q32,"0.000000")&" EUR") -> -24.000000 MW × 151.910000 × 0.250000 h = -911.460000 EUR | BF32: =IF(L32=0,"零头寸，无结算现金",TEXT(L32,"0.000000")&" MW × "&TEXT(C32,"0.000000")&" × "&TEXT(AC32,"0.000000")&" h = "&TEXT(R32,"0.000000")&" EUR") -> 40.000000 MW × 66.224535 × 0.250000 h = 662.245345 EUR | BG32: =IF(M32=0,"零头寸，无结算现金",TEXT(M32,"0.000000")&" MW × "&TEXT(D32,"0.000000")&" × "&TEXT(AC32,"0.000000")&" h = "&TEXT(S32,"0.000000")&" EUR") -> 24.000000 MW × 7.127475 × 0.250000 h = 42.764850 EUR | BH32: =IF(N32=0,"零头寸，无结算现金",TEXT(N32,"0.000000")&" MW × "&TEXT(E32,"0.000000")&" × "&TEXT(AC32,"0.000000")&" h = "&TEXT(T32,"0.000000")&" EUR") -> 24.000000 MW × 5.073085 × 0.250000 h = 30.438511 EUR | BI32: =IF(O32=0,"零上调激活电量",TEXT(O32,"0.000000")&" MWh × "&TEXT(F32,"0.000000")&" = "&TEXT(U32,"0.000000")&" EUR") -> 3.441463 MWh × 254.404170 = 875.522501 EUR | BJ32: =IF(P32=0,"零下调激活电量","−("&TEXT(P32,"0.000000")&" MWh × "&TEXT(G32,"0.000000")&") = "&TEXT(V32,"0.000000")&" EUR") -> 零下调激活电量 | BK32: =TEXT(Q32,"0.000000")&" + "&TEXT(R32,"0.000000")&" + "&TEXT(S32,"0.000000")&" + "&TEXT(T32,"0.000000")&" + "&TEXT(U32,"0.000000")&" + "&TEXT(V32,"0.000000")&" = "&TEXT(W32,"0.000000")&" EUR" -> -911.460000 + 662.245345 + 42.764850 + 30.438511 + 875.522501 + 0.000000 = 699.511208 EUR
A33: =原始输入与口径!C33 -> 46235.25 | B33: =IF(ISNUMBER(原始输入与口径!H33),原始输入与口径!H33,"缺失") -> 154.07 | C33: =IF(ISNUMBER(原始输入与口径!R33),原始输入与口径!R33,"缺失") -> 66.224535 | D33: =IF(ISNUMBER(原始输入与口径!W33),原始输入与口径!W33,"缺失") -> 7.0626799 | E33: =IF(ISNUMBER(原始输入与口径!AB33),原始输入与口径!AB33,"缺失") -> 2.8376498 | F33: =IF(ISNUMBER(原始输入与口径!AG33),原始输入与口径!AG33,"缺失") -> 242.46355 | G33: =IF(ISNUMBER(原始输入与口径!AJ33),原始输入与口径!AJ33,"缺失") -> 0 | H33: ="未模拟" -> 未模拟 | I33: =原始输入与口径!CD33 -> 38.154264 | J33: =原始输入与口径!CE33 -> 40.826828 | K33: =原始输入与口径!BZ33 -> -24 | L33: =原始输入与口径!CK33 -> 40 | M33: =原始输入与口径!BT33 -> 24 | N33: =原始输入与口径!BJ33 -> 24 | O33: =M33*AF33*AC33 -> 3.09504 | P33: =N33*AG33*AC33 -> 0 | Q33: =IF(K33=0,0,IF(ISNUMBER(B33),K33*B33*AC33,NA())) -> -924.42 | R33: =IF(L33=0,0,IF(ISNUMBER(C33),L33*C33*AC33,NA())) -> 662.24535 | S33: =IF(M33=0,0,IF(ISNUMBER(D33),M33*D33*AC33,NA())) -> 42.376079 | T33: =IF(N33=0,0,IF(ISNUMBER(E33),N33*E33*AC33,NA())) -> 17.025899 | U33: =IF(O33=0,0,O33*F33) -> 750.43439 | V33: =IF(P33=0,0,-P33*G33) -> 0 | W33: =SUM(Q33:V33) -> 547.66172 | X33: =原始输入与口径!CP33 -> 547.66172 | Y33: =W33-X33 -> 0 | Z33: ="当日执行" -> 当日执行 | AA33: =IF(原始输入与口径!AW33,1,0) -> 1 | AB33: =IF(原始输入与口径!AY33,1,0) -> 1 | AC33: =原始输入与口径!$F$5 -> 0.25 | AD33: =原始输入与口径!CG33 -> 0.3125 | AE33: =原始输入与口径!BQ33 -> 0.13714286 | AF33: =IF(AA33=0,0,AJ33/(AH33*AC33)) -> 0.51584 | AG33: =IF(AA33=0,0,AK33/(AI33*AC33)) -> 0 | AH33: =IF(ISNUMBER(原始输入与口径!T33),原始输入与口径!T33,"缺失") -> 175 | AI33: =IF(ISNUMBER(原始输入与口径!Y33),原始输入与口径!Y33,"缺失") -> 175 | AJ33: =IF(ISNUMBER(原始输入与口径!AI33),原始输入与口径!AI33,"缺失") -> 22.568 | AK33: =IF(ISNUMBER(原始输入与口径!AL33),原始输入与口径!AL33,"缺失") -> 0 | AL33: =IF(ISNUMBER(原始输入与口径!O33),原始输入与口径!O33,"缺失") -> 128 | AM33: =SUMIFS(相位SOC复算!$N$9:$N$929,相位SOC复算!$S$9:$S$929,25) -> 0.0074237867 | AN33: =SUMIFS(相位SOC复算!$Q$9:$Q$929,相位SOC复算!$S$9:$S$929,25) -> 2.90496 | AO33: =SUMIFS(相位SOC复算!$R$9:$R$929,相位SOC复算!$S$9:$S$929,25) -> 0 | AP33: =相位SOC复算!J60 -> 40.826828 | AQ33: =AP33-J33 -> 0 | AR33: =IF(ISBLANK(原始输入与口径!M33),"",原始输入与口径!M33) -> 5.2473 | AS33: =IF(ISBLANK(原始输入与口径!L33),"",原始输入与口径!L33) -> 46234 | AT33: =IF(ISBLANK(原始输入与口径!A33),"",原始输入与口径!A33) -> 46235.125 | AU33: =IF(ISBLANK(原始输入与口径!I33),"",原始输入与口径!I33) -> 2026-08-01_21 | AV33: =IF(ISBLANK(原始输入与口径!J33),"",原始输入与口径!J33) -> 15 | AW33: =IF(ISBLANK(原始输入与口径!BB33),"",原始输入与口径!BB33) -> OK | AX33: =原始输入与口径!CI33 -> 128 | AY33: =原始输入与口径!BS33 -> 175 | AZ33: =原始输入与口径!BI33 -> 175 | BA33: =原始输入与口径!CM33 -> 40 | BB33: =原始输入与口径!BV33 -> 24 | BC33: =原始输入与口径!BL33 -> 24 | BD33: =46235 -> 46235 | BE33: =IF(K33=0,"零头寸，无结算现金",TEXT(K33,"0.000000")&" MW × "&TEXT(B33,"0.000000")&" × "&TEXT(AC33,"0.000000")&" h = "&TEXT(Q33,"0.000000")&" EUR") -> -24.000000 MW × 154.070000 × 0.250000 h = -924.420000 EUR | BF33: =IF(L33=0,"零头寸，无结算现金",TEXT(L33,"0.000000")&" MW × "&TEXT(C33,"0.000000")&" × "&TEXT(AC33,"0.000000")&" h = "&TEXT(R33,"0.000000")&" EUR") -> 40.000000 MW × 66.224535 × 0.250000 h = 662.245345 EUR | BG33: =IF(M33=0,"零头寸，无结算现金",TEXT(M33,"0.000000")&" MW × "&TEXT(D33,"0.000000")&" × "&TEXT(AC33,"0.000000")&" h = "&TEXT(S33,"0.000000")&" EUR") -> 24.000000 MW × 7.062680 × 0.250000 h = 42.376079 EUR | BH33: =IF(N33=0,"零头寸，无结算现金",TEXT(N33,"0.000000")&" MW × "&TEXT(E33,"0.000000")&" × "&TEXT(AC33,"0.000000")&" h = "&TEXT(T33,"0.000000")&" EUR") -> 24.000000 MW × 2.837650 × 0.250000 h = 17.025899 EUR | BI33: =IF(O33=0,"零上调激活电量",TEXT(O33,"0.000000")&" MWh × "&TEXT(F33,"0.000000")&" = "&TEXT(U33,"0.000000")&" EUR") -> 3.095040 MWh × 242.463553 = 750.434394 EUR | BJ33: =IF(P33=0,"零下调激活电量","−("&TEXT(P33,"0.000000")&" MWh × "&TEXT(G33,"0.000000")&") = "&TEXT(V33,"0.000000")&" EUR") -> 零下调激活电量 | BK33: =TEXT(Q33,"0.000000")&" + "&TEXT(R33,"0.000000")&" + "&TEXT(S33,"0.000000")&" + "&TEXT(T33,"0.000000")&" + "&TEXT(U33,"0.000000")&" + "&TEXT(V33,"0.000000")&" = "&TEXT(W33,"0.000000")&" EUR" -> -924.420000 + 662.245345 + 42.376079 + 17.025899 + 750.434394 + 0.000000 = 547.661717 EUR
A34: =原始输入与口径!C34 -> 46235.26 | B34: =IF(ISNUMBER(原始输入与口径!H34),原始输入与口径!H34,"缺失") -> 163.2 | C34: =IF(ISNUMBER(原始输入与口径!R34),原始输入与口径!R34,"缺失") -> 66.224535 | D34: =IF(ISNUMBER(原始输入与口径!W34),原始输入与口径!W34,"缺失") -> 7.0626799 | E34: =IF(ISNUMBER(原始输入与口径!AB34),原始输入与口径!AB34,"缺失") -> 2.8376498 | F34: =IF(ISNUMBER(原始输入与口径!AG34),原始输入与口径!AG34,"缺失") -> 173.58241 | G34: =IF(ISNUMBER(原始输入与口径!AJ34),原始输入与口径!AJ34,"缺失") -> 0 | H34: ="未模拟" -> 未模拟 | I34: =原始输入与口径!CD34 -> 40.826828 | J34: =原始输入与口径!CE34 -> 40.363672 | K34: =原始输入与口径!BZ34 -> 0 | L34: =原始输入与口径!CK34 -> 40 | M34: =原始输入与口径!BT34 -> 24 | N34: =原始输入与口径!BJ34 -> 24 | O34: =M34*AF34*AC34 -> 0.42610286 | P34: =N34*AG34*AC34 -> 0 | Q34: =IF(K34=0,0,IF(ISNUMBER(B34),K34*B34*AC34,NA())) -> 0 | R34: =IF(L34=0,0,IF(ISNUMBER(C34),L34*C34*AC34,NA())) -> 662.24535 | S34: =IF(M34=0,0,IF(ISNUMBER(D34),M34*D34*AC34,NA())) -> 42.376079 | T34: =IF(N34=0,0,IF(ISNUMBER(E34),N34*E34*AC34,NA())) -> 17.025899 | U34: =IF(O34=0,0,O34*F34) -> 73.963962 | V34: =IF(P34=0,0,-P34*G34) -> 0 | W34: =SUM(Q34:V34) -> 795.61129 | X34: =原始输入与口径!CP34 -> 795.61129 | Y34: =W34-X34 -> 0 | Z34: ="当日执行" -> 当日执行 | AA34: =IF(原始输入与口径!AW34,1,0) -> 1 | AB34: =IF(原始输入与口径!AY34,1,0) -> 1 | AC34: =原始输入与口径!$F$5 -> 0.25 | AD34: =原始输入与口径!CG34 -> 0.3125 | AE34: =原始输入与口径!BQ34 -> 0.13714286 | AF34: =IF(AA34=0,0,AJ34/(AH34*AC34)) -> 0.071017143 | AG34: =IF(AA34=0,0,AK34/(AI34*AC34)) -> 0 | AH34: =IF(ISNUMBER(原始输入与口径!T34),原始输入与口径!T34,"缺失") -> 175 | AI34: =IF(ISNUMBER(原始输入与口径!Y34),原始输入与口径!Y34,"缺失") -> 175 | AJ34: =IF(ISNUMBER(原始输入与口径!AI34),原始输入与口径!AI34,"缺失") -> 3.107 | AK34: =IF(ISNUMBER(原始输入与口径!AL34),原始输入与口径!AL34,"缺失") -> 0 | AL34: =IF(ISNUMBER(原始输入与口径!O34),原始输入与口径!O34,"缺失") -> 128 | AM34: =SUMIFS(相位SOC复算!$N$9:$N$929,相位SOC复算!$S$9:$S$929,26) -> 0.0012865424 | AN34: =SUMIFS(相位SOC复算!$Q$9:$Q$929,相位SOC复算!$S$9:$S$929,26) -> 0 | AO34: =SUMIFS(相位SOC复算!$R$9:$R$929,相位SOC复算!$S$9:$S$929,26) -> 0.42610286 | AP34: =相位SOC复算!J62 -> 40.363672 | AQ34: =AP34-J34 -> 0 | AR34: =IF(ISBLANK(原始输入与口径!M34),"",原始输入与口径!M34) -> 5.2473 | AS34: =IF(ISBLANK(原始输入与口径!L34),"",原始输入与口径!L34) -> 46234 | AT34: =IF(ISBLANK(原始输入与口径!A34),"",原始输入与口径!A34) -> 46235.135 | AU34: =IF(ISBLANK(原始输入与口径!I34),"",原始输入与口径!I34) -> 2026-08-01_22 | AV34: =IF(ISBLANK(原始输入与口径!J34),"",原始输入与口径!J34) -> 15 | AW34: =IF(ISBLANK(原始输入与口径!BB34),"",原始输入与口径!BB34) -> OK | AX34: =原始输入与口径!CI34 -> 128 | AY34: =原始输入与口径!BS34 -> 175 | AZ34: =原始输入与口径!BI34 -> 175 | BA34: =原始输入与口径!CM34 -> 40 | BB34: =原始输入与口径!BV34 -> 24 | BC34: =原始输入与口径!BL34 -> 24 | BD34: =46235 -> 46235 | BE34: =IF(K34=0,"零头寸，无结算现金",TEXT(K34,"0.000000")&" MW × "&TEXT(B34,"0.000000")&" × "&TEXT(AC34,"0.000000")&" h = "&TEXT(Q34,"0.000000")&" EUR") -> 零头寸，无结算现金 | BF34: =IF(L34=0,"零头寸，无结算现金",TEXT(L34,"0.000000")&" MW × "&TEXT(C34,"0.000000")&" × "&TEXT(AC34,"0.000000")&" h = "&TEXT(R34,"0.000000")&" EUR") -> 40.000000 MW × 66.224535 × 0.250000 h = 662.245345 EUR | BG34: =IF(M34=0,"零头寸，无结算现金",TEXT(M34,"0.000000")&" MW × "&TEXT(D34,"0.000000")&" × "&TEXT(AC34,"0.000000")&" h = "&TEXT(S34,"0.000000")&" EUR") -> 24.000000 MW × 7.062680 × 0.250000 h = 42.376079 EUR | BH34: =IF(N34=0,"零头寸，无结算现金",TEXT(N34,"0.000000")&" MW × "&TEXT(E34,"0.000000")&" × "&TEXT(AC34,"0.000000")&" h = "&TEXT(T34,"0.000000")&" EUR") -> 24.000000 MW × 2.837650 × 0.250000 h = 17.025899 EUR | BI34: =IF(O34=0,"零上调激活电量",TEXT(O34,"0.000000")&" MWh × "&TEXT(F34,"0.000000")&" = "&TEXT(U34,"0.000000")&" EUR") -> 0.426103 MWh × 173.582414 = 73.963962 EUR | BJ34: =IF(P34=0,"零下调激活电量","−("&TEXT(P34,"0.000000")&" MWh × "&TEXT(G34,"0.000000")&") = "&TEXT(V34,"0.000000")&" EUR") -> 零下调激活电量 | BK34: =TEXT(Q34,"0.000000")&" + "&TEXT(R34,"0.000000")&" + "&TEXT(S34,"0.000000")&" + "&TEXT(T34,"0.000000")&" + "&TEXT(U34,"0.000000")&" + "&TEXT(V34,"0.000000")&" = "&TEXT(W34,"0.000000")&" EUR" -> 0.000000 + 662.245345 + 42.376079 + 17.025899 + 73.963962 + 0.000000 = 795.611286 EUR
A35: =原始输入与口径!C35 -> 46235.271 | B35: =IF(ISNUMBER(原始输入与口径!H35),原始输入与口径!H35,"缺失") -> 157.71 | C35: =IF(ISNUMBER(原始输入与口径!R35),原始输入与口径!R35,"缺失") -> 66.224535 | D35: =IF(ISNUMBER(原始输入与口径!W35),原始输入与口径!W35,"缺失") -> 7.0626799 | E35: =IF(ISNUMBER(原始输入与口径!AB35),原始输入与口径!AB35,"缺失") -> 2.8376498 | F35: =IF(ISNUMBER(原始输入与口径!AG35),原始输入与口径!AG35,"缺失") -> 171.50192 | G35: =IF(ISNUMBER(原始输入与口径!AJ35),原始输入与口径!AJ35,"缺失") -> 0 | H35: ="未模拟" -> 未模拟 | I35: =原始输入与口径!CD35 -> 40.363672 | J35: =原始输入与口径!CE35 -> 39.703747 | K35: =原始输入与口径!BZ35 -> 0 | L35: =原始输入与口径!CK35 -> 40 | M35: =原始输入与口径!BT35 -> 24 | N35: =原始输入与口径!BJ35 -> 24 | O35: =M35*AF35*AC35 -> 0.60713143 | P35: =N35*AG35*AC35 -> 0 | Q35: =IF(K35=0,0,IF(ISNUMBER(B35),K35*B35*AC35,NA())) -> 0 | R35: =IF(L35=0,0,IF(ISNUMBER(C35),L35*C35*AC35,NA())) -> 662.24535 | S35: =IF(M35=0,0,IF(ISNUMBER(D35),M35*D35*AC35,NA())) -> 42.376079 | T35: =IF(N35=0,0,IF(ISNUMBER(E35),N35*E35*AC35,NA())) -> 17.025899 | U35: =IF(O35=0,0,O35*F35) -> 104.1242 | V35: =IF(P35=0,0,-P35*G35) -> 0 | W35: =SUM(Q35:V35) -> 825.77153 | X35: =原始输入与口径!CP35 -> 825.77153 | Y35: =W35-X35 -> 0 | Z35: ="当日执行" -> 当日执行 | AA35: =IF(原始输入与口径!AW35,1,0) -> 1 | AB35: =IF(原始输入与口径!AY35,1,0) -> 1 | AC35: =原始输入与口径!$F$5 -> 0.25 | AD35: =原始输入与口径!CG35 -> 0.3125 | AE35: =原始输入与口径!BQ35 -> 0.13714286 | AF35: =IF(AA35=0,0,AJ35/(AH35*AC35)) -> 0.10118857 | AG35: =IF(AA35=0,0,AK35/(AI35*AC35)) -> 0 | AH35: =IF(ISNUMBER(原始输入与口径!T35),原始输入与口径!T35,"缺失") -> 175 | AI35: =IF(ISNUMBER(原始输入与口径!Y35),原始输入与口径!Y35,"缺失") -> 175 | AJ35: =IF(ISNUMBER(原始输入与口径!AI35),原始输入与口径!AI35,"缺失") -> 4.427 | AK35: =IF(ISNUMBER(原始输入与口径!AL35),原始输入与口径!AL35,"缺失") -> 0 | AL35: =IF(ISNUMBER(原始输入与口径!O35),原始输入与口径!O35,"缺失") -> 128 | AM35: =SUMIFS(相位SOC复算!$N$9:$N$929,相位SOC复算!$S$9:$S$929,27) -> 0.0018331263 | AN35: =SUMIFS(相位SOC复算!$Q$9:$Q$929,相位SOC复算!$S$9:$S$929,27) -> 0 | AO35: =SUMIFS(相位SOC复算!$R$9:$R$929,相位SOC复算!$S$9:$S$929,27) -> 0.60713143 | AP35: =相位SOC复算!J64 -> 39.703747 | AQ35: =AP35-J35 -> 0 | AR35: =IF(ISBLANK(原始输入与口径!M35),"",原始输入与口径!M35) -> 5.2473 | AS35: =IF(ISBLANK(原始输入与口径!L35),"",原始输入与口径!L35) -> 46234 | AT35: =IF(ISBLANK(原始输入与口径!A35),"",原始输入与口径!A35) -> 46235.146 | AU35: =IF(ISBLANK(原始输入与口径!I35),"",原始输入与口径!I35) -> 2026-08-01_23 | AV35: =IF(ISBLANK(原始输入与口径!J35),"",原始输入与口径!J35) -> 15 | AW35: =IF(ISBLANK(原始输入与口径!BB35),"",原始输入与口径!BB35) -> OK | AX35: =原始输入与口径!CI35 -> 128 | AY35: =原始输入与口径!BS35 -> 175 | AZ35: =原始输入与口径!BI35 -> 175 | BA35: =原始输入与口径!CM35 -> 40 | BB35: =原始输入与口径!BV35 -> 24 | BC35: =原始输入与口径!BL35 -> 24 | BD35: =46235 -> 46235 | BE35: =IF(K35=0,"零头寸，无结算现金",TEXT(K35,"0.000000")&" MW × "&TEXT(B35,"0.000000")&" × "&TEXT(AC35,"0.000000")&" h = "&TEXT(Q35,"0.000000")&" EUR") -> 零头寸，无结算现金 | BF35: =IF(L35=0,"零头寸，无结算现金",TEXT(L35,"0.000000")&" MW × "&TEXT(C35,"0.000000")&" × "&TEXT(AC35,"0.000000")&" h = "&TEXT(R35,"0.000000")&" EUR") -> 40.000000 MW × 66.224535 × 0.250000 h = 662.245345 EUR | BG35: =IF(M35=0,"零头寸，无结算现金",TEXT(M35,"0.000000")&" MW × "&TEXT(D35,"0.000000")&" × "&TEXT(AC35,"0.000000")&" h = "&TEXT(S35,"0.000000")&" EUR") -> 24.000000 MW × 7.062680 × 0.250000 h = 42.376079 EUR | BH35: =IF(N35=0,"零头寸，无结算现金",TEXT(N35,"0.000000")&" MW × "&TEXT(E35,"0.000000")&" × "&TEXT(AC35,"0.000000")&" h = "&TEXT(T35,"0.000000")&" EUR") -> 24.000000 MW × 2.837650 × 0.250000 h = 17.025899 EUR | BI35: =IF(O35=0,"零上调激活电量",TEXT(O35,"0.000000")&" MWh × "&TEXT(F35,"0.000000")&" = "&TEXT(U35,"0.000000")&" EUR") -> 0.607131 MWh × 171.501915 = 104.124203 EUR | BJ35: =IF(P35=0,"零下调激活电量","−("&TEXT(P35,"0.000000")&" MWh × "&TEXT(G35,"0.000000")&") = "&TEXT(V35,"0.000000")&" EUR") -> 零下调激活电量 | BK35: =TEXT(Q35,"0.000000")&" + "&TEXT(R35,"0.000000")&" + "&TEXT(S35,"0.000000")&" + "&TEXT(T35,"0.000000")&" + "&TEXT(U35,"0.000000")&" + "&TEXT(V35,"0.000000")&" = "&TEXT(W35,"0.000000")&" EUR" -> 0.000000 + 662.245345 + 42.376079 + 17.025899 + 104.124203 + 0.000000 = 825.771526 EUR
A36: =原始输入与口径!C36 -> 46235.281 | B36: =IF(ISNUMBER(原始输入与口径!H36),原始输入与口径!H36,"缺失") -> 158.73 | C36: =IF(ISNUMBER(原始输入与口径!R36),原始输入与口径!R36,"缺失") -> 66.224535 | D36: =IF(ISNUMBER(原始输入与口径!W36),原始输入与口径!W36,"缺失") -> 7.0626799 | E36: =IF(ISNUMBER(原始输入与口径!AB36),原始输入与口径!AB36,"缺失") -> 2.8376498 | F36: =IF(ISNUMBER(原始输入与口径!AG36),原始输入与口径!AG36,"缺失") -> 170.3175 | G36: =IF(ISNUMBER(原始输入与口径!AJ36),原始输入与口径!AJ36,"缺失") -> 76.420254 | H36: ="未模拟" -> 未模拟 | I36: =原始输入与口径!CD36 -> 39.703747 | J36: =原始输入与口径!CE36 -> 39.536722 | K36: =原始输入与口径!BZ36 -> 0 | L36: =原始输入与口径!CK36 -> 40 | M36: =原始输入与口径!BT36 -> 24 | N36: =原始输入与口径!BJ36 -> 24 | O36: =M36*AF36*AC36 -> 0.15552 | P36: =N36*AG36*AC36 -> 0.0021942857 | Q36: =IF(K36=0,0,IF(ISNUMBER(B36),K36*B36*AC36,NA())) -> 0 | R36: =IF(L36=0,0,IF(ISNUMBER(C36),L36*C36*AC36,NA())) -> 662.24535 | S36: =IF(M36=0,0,IF(ISNUMBER(D36),M36*D36*AC36,NA())) -> 42.376079 | T36: =IF(N36=0,0,IF(ISNUMBER(E36),N36*E36*AC36,NA())) -> 17.025899 | U36: =IF(O36=0,0,O36*F36) -> 26.487777 | V36: =IF(P36=0,0,-P36*G36) -> -0.16768787 | W36: =SUM(Q36:V36) -> 747.96741 | X36: =原始输入与口径!CP36 -> 747.96741 | Y36: =W36-X36 -> 0 | Z36: ="当日执行" -> 当日执行 | AA36: =IF(原始输入与口径!AW36,1,0) -> 1 | AB36: =IF(原始输入与口径!AY36,1,0) -> 1 | AC36: =原始输入与口径!$F$5 -> 0.25 | AD36: =原始输入与口径!CG36 -> 0.3125 | AE36: =原始输入与口径!BQ36 -> 0.13714286 | AF36: =IF(AA36=0,0,AJ36/(AH36*AC36)) -> 0.02592 | AG36: =IF(AA36=0,0,AK36/(AI36*AC36)) -> 0.00036571429 | AH36: =IF(ISNUMBER(原始输入与口径!T36),原始输入与口径!T36,"缺失") -> 175 | AI36: =IF(ISNUMBER(原始输入与口径!Y36),原始输入与口径!Y36,"缺失") -> 175 | AJ36: =IF(ISNUMBER(原始输入与口径!AI36),原始输入与口径!AI36,"缺失") -> 1.134 | AK36: =IF(ISNUMBER(原始输入与口径!AL36),原始输入与口径!AL36,"缺失") -> 0.016 | AL36: =IF(ISNUMBER(原始输入与口径!O36),原始输入与口径!O36,"缺失") -> 128 | AM36: =SUMIFS(相位SOC复算!$N$9:$N$929,相位SOC复算!$S$9:$S$929,28) -> 0.00047517284 | AN36: =SUMIFS(相位SOC复算!$Q$9:$Q$929,相位SOC复算!$S$9:$S$929,28) -> 0.0021942857 | AO36: =SUMIFS(相位SOC复算!$R$9:$R$929,相位SOC复算!$S$9:$S$929,28) -> 0.15552 | AP36: =相位SOC复算!J67 -> 39.536722 | AQ36: =AP36-J36 -> 0 | AR36: =IF(ISBLANK(原始输入与口径!M36),"",原始输入与口径!M36) -> 5.2473 | AS36: =IF(ISBLANK(原始输入与口径!L36),"",原始输入与口径!L36) -> 46234 | AT36: =IF(ISBLANK(原始输入与口径!A36),"",原始输入与口径!A36) -> 46235.156 | AU36: =IF(ISBLANK(原始输入与口径!I36),"",原始输入与口径!I36) -> 2026-08-01_24 | AV36: =IF(ISBLANK(原始输入与口径!J36),"",原始输入与口径!J36) -> 15 | AW36: =IF(ISBLANK(原始输入与口径!BB36),"",原始输入与口径!BB36) -> OK | AX36: =原始输入与口径!CI36 -> 128 | AY36: =原始输入与口径!BS36 -> 175 | AZ36: =原始输入与口径!BI36 -> 175 | BA36: =原始输入与口径!CM36 -> 40 | BB36: =原始输入与口径!BV36 -> 24 | BC36: =原始输入与口径!BL36 -> 24 | BD36: =46235 -> 46235 | BE36: =IF(K36=0,"零头寸，无结算现金",TEXT(K36,"0.000000")&" MW × "&TEXT(B36,"0.000000")&" × "&TEXT(AC36,"0.000000")&" h = "&TEXT(Q36,"0.000000")&" EUR") -> 零头寸，无结算现金 | BF36: =IF(L36=0,"零头寸，无结算现金",TEXT(L36,"0.000000")&" MW × "&TEXT(C36,"0.000000")&" × "&TEXT(AC36,"0.000000")&" h = "&TEXT(R36,"0.000000")&" EUR") -> 40.000000 MW × 66.224535 × 0.250000 h = 662.245345 EUR | BG36: =IF(M36=0,"零头寸，无结算现金",TEXT(M36,"0.000000")&" MW × "&TEXT(D36,"0.000000")&" × "&TEXT(AC36,"0.000000")&" h = "&TEXT(S36,"0.000000")&" EUR") -> 24.000000 MW × 7.062680 × 0.250000 h = 42.376079 EUR | BH36: =IF(N36=0,"零头寸，无结算现金",TEXT(N36,"0.000000")&" MW × "&TEXT(E36,"0.000000")&" × "&TEXT(AC36,"0.000000")&" h = "&TEXT(T36,"0.000000")&" EUR") -> 24.000000 MW × 2.837650 × 0.250000 h = 17.025899 EUR | BI36: =IF(O36=0,"零上调激活电量",TEXT(O36,"0.000000")&" MWh × "&TEXT(F36,"0.000000")&" = "&TEXT(U36,"0.000000")&" EUR") -> 0.155520 MWh × 170.317497 = 26.487777 EUR | BJ36: =IF(P36=0,"零下调激活电量","−("&TEXT(P36,"0.000000")&" MWh × "&TEXT(G36,"0.000000")&") = "&TEXT(V36,"0.000000")&" EUR") -> −(0.002194 MWh × 76.420254) = -0.167688 EUR | BK36: =TEXT(Q36,"0.000000")&" + "&TEXT(R36,"0.000000")&" + "&TEXT(S36,"0.000000")&" + "&TEXT(T36,"0.000000")&" + "&TEXT(U36,"0.000000")&" + "&TEXT(V36,"0.000000")&" = "&TEXT(W36,"0.000000")&" EUR" -> 0.000000 + 662.245345 + 42.376079 + 17.025899 + 26.487777 + -0.167688 = 747.967413 EUR
A37: =原始输入与口径!C37 -> 46235.292 | B37: =IF(ISNUMBER(原始输入与口径!H37),原始输入与口径!H37,"缺失") -> 166.93 | C37: =IF(ISNUMBER(原始输入与口径!R37),原始输入与口径!R37,"缺失") -> 66.224535 | D37: =IF(ISNUMBER(原始输入与口径!W37),原始输入与口径!W37,"缺失") -> 6.6910602 | E37: =IF(ISNUMBER(原始输入与口径!AB37),原始输入与口径!AB37,"缺失") -> 2.6070551 | F37: =IF(ISNUMBER(原始输入与口径!AG37),原始输入与口径!AG37,"缺失") -> 227.40552 | G37: =IF(ISNUMBER(原始输入与口径!AJ37),原始输入与口径!AJ37,"缺失") -> 0 | H37: ="未模拟" -> 未模拟 | I37: =原始输入与口径!CD37 -> 39.536722 | J37: =原始输入与口径!CE37 -> 37.000474 | K37: =原始输入与口径!BZ37 -> 0 | L37: =原始输入与口径!CK37 -> 40 | M37: =原始输入与口径!BT37 -> 24 | N37: =原始输入与口径!BJ37 -> 24 | O37: =M37*AF37*AC37 -> 2.3333486 | P37: =N37*AG37*AC37 -> 0 | Q37: =IF(K37=0,0,IF(ISNUMBER(B37),K37*B37*AC37,NA())) -> 0 | R37: =IF(L37=0,0,IF(ISNUMBER(C37),L37*C37*AC37,NA())) -> 662.24535 | S37: =IF(M37=0,0,IF(ISNUMBER(D37),M37*D37*AC37,NA())) -> 40.146361 | T37: =IF(N37=0,0,IF(ISNUMBER(E37),N37*E37*AC37,NA())) -> 15.64233 | U37: =IF(O37=0,0,O37*F37) -> 530.61635 | V37: =IF(P37=0,0,-P37*G37) -> 0 | W37: =SUM(Q37:V37) -> 1248.6504 | X37: =原始输入与口径!CP37 -> 1248.6504 | Y37: =W37-X37 -> 0 | Z37: ="当日执行" -> 当日执行 | AA37: =IF(原始输入与口径!AW37,1,0) -> 1 | AB37: =IF(原始输入与口径!AY37,1,0) -> 1 | AC37: =原始输入与口径!$F$5 -> 0.25 | AD37: =原始输入与口径!CG37 -> 0.3125 | AE37: =原始输入与口径!BQ37 -> 0.13714286 | AF37: =IF(AA37=0,0,AJ37/(AH37*AC37)) -> 0.38889143 | AG37: =IF(AA37=0,0,AK37/(AI37*AC37)) -> 0 | AH37: =IF(ISNUMBER(原始输入与口径!T37),原始输入与口径!T37,"缺失") -> 175 | AI37: =IF(ISNUMBER(原始输入与口径!Y37),原始输入与口径!Y37,"缺失") -> 175 | AJ37: =IF(ISNUMBER(原始输入与口径!AI37),原始输入与口径!AI37,"缺失") -> 17.014 | AK37: =IF(ISNUMBER(原始输入与口径!AL37),原始输入与口径!AL37,"缺失") -> 0 | AL37: =IF(ISNUMBER(原始输入与口径!O37),原始输入与口径!O37,"缺失") -> 128 | AM37: =SUMIFS(相位SOC复算!$N$9:$N$929,相位SOC复算!$S$9:$S$929,29) -> 0.0070451346 | AN37: =SUMIFS(相位SOC复算!$Q$9:$Q$929,相位SOC复算!$S$9:$S$929,29) -> 0 | AO37: =SUMIFS(相位SOC复算!$R$9:$R$929,相位SOC复算!$S$9:$S$929,29) -> 2.3333486 | AP37: =相位SOC复算!J69 -> 37.000474 | AQ37: =AP37-J37 -> 0 | AR37: =IF(ISBLANK(原始输入与口径!M37),"",原始输入与口径!M37) -> 5.2473 | AS37: =IF(ISBLANK(原始输入与口径!L37),"",原始输入与口径!L37) -> 46234 | AT37: =IF(ISBLANK(原始输入与口径!A37),"",原始输入与口径!A37) -> 46235.167 | AU37: =IF(ISBLANK(原始输入与口径!I37),"",原始输入与口径!I37) -> 2026-08-01_25 | AV37: =IF(ISBLANK(原始输入与口径!J37),"",原始输入与口径!J37) -> 15 | AW37: =IF(ISBLANK(原始输入与口径!BB37),"",原始输入与口径!BB37) -> OK | AX37: =原始输入与口径!CI37 -> 128 | AY37: =原始输入与口径!BS37 -> 175 | AZ37: =原始输入与口径!BI37 -> 175 | BA37: =原始输入与口径!CM37 -> 40 | BB37: =原始输入与口径!BV37 -> 24 | BC37: =原始输入与口径!BL37 -> 24 | BD37: =46235 -> 46235 | BE37: =IF(K37=0,"零头寸，无结算现金",TEXT(K37,"0.000000")&" MW × "&TEXT(B37,"0.000000")&" × "&TEXT(AC37,"0.000000")&" h = "&TEXT(Q37,"0.000000")&" EUR") -> 零头寸，无结算现金 | BF37: =IF(L37=0,"零头寸，无结算现金",TEXT(L37,"0.000000")&" MW × "&TEXT(C37,"0.000000")&" × "&TEXT(AC37,"0.000000")&" h = "&TEXT(R37,"0.000000")&" EUR") -> 40.000000 MW × 66.224535 × 0.250000 h = 662.245345 EUR | BG37: =IF(M37=0,"零头寸，无结算现金",TEXT(M37,"0.000000")&" MW × "&TEXT(D37,"0.000000")&" × "&TEXT(AC37,"0.000000")&" h = "&TEXT(S37,"0.000000")&" EUR") -> 24.000000 MW × 6.691060 × 0.250000 h = 40.146361 EUR | BH37: =IF(N37=0,"零头寸，无结算现金",TEXT(N37,"0.000000")&" MW × "&TEXT(E37,"0.000000")&" × "&TEXT(AC37,"0.000000")&" h = "&TEXT(T37,"0.000000")&" EUR") -> 24.000000 MW × 2.607055 × 0.250000 h = 15.642330 EUR | BI37: =IF(O37=0,"零上调激活电量",TEXT(O37,"0.000000")&" MWh × "&TEXT(F37,"0.000000")&" = "&TEXT(U37,"0.000000")&" EUR") -> 2.333349 MWh × 227.405523 = 530.616352 EUR | BJ37: =IF(P37=0,"零下调激活电量","−("&TEXT(P37,"0.000000")&" MWh × "&TEXT(G37,"0.000000")&") = "&TEXT(V37,"0.000000")&" EUR") -> 零下调激活电量 | BK37: =TEXT(Q37,"0.000000")&" + "&TEXT(R37,"0.000000")&" + "&TEXT(S37,"0.000000")&" + "&TEXT(T37,"0.000000")&" + "&TEXT(U37,"0.000000")&" + "&TEXT(V37,"0.000000")&" = "&TEXT(W37,"0.000000")&" EUR" -> 0.000000 + 662.245345 + 40.146361 + 15.642330 + 530.616352 + 0.000000 = 1248.650388 EUR
A38: =原始输入与口径!C38 -> 46235.302 | B38: =IF(ISNUMBER(原始输入与口径!H38),原始输入与口径!H38,"缺失") -> 163.13 | C38: =IF(ISNUMBER(原始输入与口径!R38),原始输入与口径!R38,"缺失") -> 66.224535 | D38: =IF(ISNUMBER(原始输入与口径!W38),原始输入与口径!W38,"缺失") -> 6.6910602 | E38: =IF(ISNUMBER(原始输入与口径!AB38),原始输入与口径!AB38,"缺失") -> 2.6070551 | F38: =IF(ISNUMBER(原始输入与口径!AG38),原始输入与口径!AG38,"缺失") -> 182.10889 | G38: =IF(ISNUMBER(原始输入与口径!AJ38),原始输入与口径!AJ38,"缺失") -> 0 | H38: ="未模拟" -> 未模拟 | I38: =原始输入与口径!CD38 -> 37.000474 | J38: =原始输入与口径!CE38 -> 35.771107 | K38: =原始输入与口径!BZ38 -> 0 | L38: =原始输入与口径!CK38 -> 40 | M38: =原始输入与口径!BT38 -> 24 | N38: =原始输入与口径!BJ38 -> 24 | O38: =M38*AF38*AC38 -> 1.1310171 | P38: =N38*AG38*AC38 -> 0 | Q38: =IF(K38=0,0,IF(ISNUMBER(B38),K38*B38*AC38,NA())) -> 0 | R38: =IF(L38=0,0,IF(ISNUMBER(C38),L38*C38*AC38,NA())) -> 662.24535 | S38: =IF(M38=0,0,IF(ISNUMBER(D38),M38*D38*AC38,NA())) -> 40.146361 | T38: =IF(N38=0,0,IF(ISNUMBER(E38),N38*E38*AC38,NA())) -> 15.64233 | U38: =IF(O38=0,0,O38*F38) -> 205.96828 | V38: =IF(P38=0,0,-P38*G38) -> 0 | W38: =SUM(Q38:V38) -> 924.00232 | X38: =原始输入与口径!CP38 -> 924.00232 | Y38: =W38-X38 -> 0 | Z38: ="当日执行" -> 当日执行 | AA38: =IF(原始输入与口径!AW38,1,0) -> 1 | AB38: =IF(原始输入与口径!AY38,1,0) -> 1 | AC38: =原始输入与口径!$F$5 -> 0.25 | AD38: =原始输入与口径!CG38 -> 0.3125 | AE38: =原始输入与口径!BQ38 -> 0.13714286 | AF38: =IF(AA38=0,0,AJ38/(AH38*AC38)) -> 0.18850286 | AG38: =IF(AA38=0,0,AK38/(AI38*AC38)) -> 0 | AH38: =IF(ISNUMBER(原始输入与口径!T38),原始输入与口径!T38,"缺失") -> 175 | AI38: =IF(ISNUMBER(原始输入与口径!Y38),原始输入与口径!Y38,"缺失") -> 175 | AJ38: =IF(ISNUMBER(原始输入与口径!AI38),原始输入与口径!AI38,"缺失") -> 8.247 | AK38: =IF(ISNUMBER(原始输入与口径!AL38),原始输入与口径!AL38,"缺失") -> 0 | AL38: =IF(ISNUMBER(原始输入与口径!O38),原始输入与口径!O38,"缺失") -> 128 | AM38: =SUMIFS(相位SOC复算!$N$9:$N$929,相位SOC复算!$S$9:$S$929,30) -> 0.0034149068 | AN38: =SUMIFS(相位SOC复算!$Q$9:$Q$929,相位SOC复算!$S$9:$S$929,30) -> 0 | AO38: =SUMIFS(相位SOC复算!$R$9:$R$929,相位SOC复算!$S$9:$S$929,30) -> 1.1310171 | AP38: =相位SOC复算!J71 -> 35.771107 | AQ38: =AP38-J38 -> 0 | AR38: =IF(ISBLANK(原始输入与口径!M38),"",原始输入与口径!M38) -> 5.2473 | AS38: =IF(ISBLANK(原始输入与口径!L38),"",原始输入与口径!L38) -> 46234 | AT38: =IF(ISBLANK(原始输入与口径!A38),"",原始输入与口径!A38) -> 46235.177 | AU38: =IF(ISBLANK(原始输入与口径!I38),"",原始输入与口径!I38) -> 2026-08-01_26 | AV38: =IF(ISBLANK(原始输入与口径!J38),"",原始输入与口径!J38) -> 15 | AW38: =IF(ISBLANK(原始输入与口径!BB38),"",原始输入与口径!BB38) -> OK | AX38: =原始输入与口径!CI38 -> 128 | AY38: =原始输入与口径!BS38 -> 175 | AZ38: =原始输入与口径!BI38 -> 175 | BA38: =原始输入与口径!CM38 -> 40 | BB38: =原始输入与口径!BV38 -> 24 | BC38: =原始输入与口径!BL38 -> 24 | BD38: =46235 -> 46235 | BE38: =IF(K38=0,"零头寸，无结算现金",TEXT(K38,"0.000000")&" MW × "&TEXT(B38,"0.000000")&" × "&TEXT(AC38,"0.000000")&" h = "&TEXT(Q38,"0.000000")&" EUR") -> 零头寸，无结算现金 | BF38: =IF(L38=0,"零头寸，无结算现金",TEXT(L38,"0.000000")&" MW × "&TEXT(C38,"0.000000")&" × "&TEXT(AC38,"0.000000")&" h = "&TEXT(R38,"0.000000")&" EUR") -> 40.000000 MW × 66.224535 × 0.250000 h = 662.245345 EUR | BG38: =IF(M38=0,"零头寸，无结算现金",TEXT(M38,"0.000000")&" MW × "&TEXT(D38,"0.000000")&" × "&TEXT(AC38,"0.000000")&" h = "&TEXT(S38,"0.000000")&" EUR") -> 24.000000 MW × 6.691060 × 0.250000 h = 40.146361 EUR | BH38: =IF(N38=0,"零头寸，无结算现金",TEXT(N38,"0.000000")&" MW × "&TEXT(E38,"0.000000")&" × "&TEXT(AC38,"0.000000")&" h = "&TEXT(T38,"0.000000")&" EUR") -> 24.000000 MW × 2.607055 × 0.250000 h = 15.642330 EUR | BI38: =IF(O38=0,"零上调激活电量",TEXT(O38,"0.000000")&" MWh × "&TEXT(F38,"0.000000")&" = "&TEXT(U38,"0.000000")&" EUR") -> 1.131017 MWh × 182.108894 = 205.968281 EUR | BJ38: =IF(P38=0,"零下调激活电量","−("&TEXT(P38,"0.000000")&" MWh × "&TEXT(G38,"0.000000")&") = "&TEXT(V38,"0.000000")&" EUR") -> 零下调激活电量 | BK38: =TEXT(Q38,"0.000000")&" + "&TEXT(R38,"0.000000")&" + "&TEXT(S38,"0.000000")&" + "&TEXT(T38,"0.000000")&" + "&TEXT(U38,"0.000000")&" + "&TEXT(V38,"0.000000")&" = "&TEXT(W38,"0.000000")&" EUR" -> 0.000000 + 662.245345 + 40.146361 + 15.642330 + 205.968281 + 0.000000 = 924.002318 EUR
A39: =原始输入与口径!C39 -> 46235.312 | B39: =IF(ISNUMBER(原始输入与口径!H39),原始输入与口径!H39,"缺失") -> 152.09 | C39: =IF(ISNUMBER(原始输入与口径!R39),原始输入与口径!R39,"缺失") -> 66.224535 | D39: =IF(ISNUMBER(原始输入与口径!W39),原始输入与口径!W39,"缺失") -> 6.6910602 | E39: =IF(ISNUMBER(原始输入与口径!AB39),原始输入与口径!AB39,"缺失") -> 2.6070551 | F39: =IF(ISNUMBER(原始输入与口径!AG39),原始输入与口径!AG39,"缺失") -> 174.24123 | G39: =IF(ISNUMBER(原始输入与口径!AJ39),原始输入与口径!AJ39,"缺失") -> 0 | H39: ="未模拟" -> 未模拟 | I39: =原始输入与口径!CD39 -> 35.771107 | J39: =原始输入与口径!CE39 -> 35.347902 | K39: =原始输入与口径!BZ39 -> 0 | L39: =原始输入与口径!CK39 -> 40 | M39: =原始输入与口径!BT39 -> 24 | N39: =原始输入与口径!BJ39 -> 24 | O39: =M39*AF39*AC39 -> 0.38934857 | P39: =N39*AG39*AC39 -> 0 | Q39: =IF(K39=0,0,IF(ISNUMBER(B39),K39*B39*AC39,NA())) -> 0 | R39: =IF(L39=0,0,IF(ISNUMBER(C39),L39*C39*AC39,NA())) -> 662.24535 | S39: =IF(M39=0,0,IF(ISNUMBER(D39),M39*D39*AC39,NA())) -> 40.146361 | T39: =IF(N39=0,0,IF(ISNUMBER(E39),N39*E39*AC39,NA())) -> 15.64233 | U39: =IF(O39=0,0,O39*F39) -> 67.840574 | V39: =IF(P39=0,0,-P39*G39) -> 0 | W39: =SUM(Q39:V39) -> 785.87461 | X39: =原始输入与口径!CP39 -> 785.87461 | Y39: =W39-X39 -> 0 | Z39: ="当日执行" -> 当日执行 | AA39: =IF(原始输入与口径!AW39,1,0) -> 1 | AB39: =IF(原始输入与口径!AY39,1,0) -> 1 | AC39: =原始输入与口径!$F$5 -> 0.25 | AD39: =原始输入与口径!CG39 -> 0.3125 | AE39: =原始输入与口径!BQ39 -> 0.13714286 | AF39: =IF(AA39=0,0,AJ39/(AH39*AC39)) -> 0.064891429 | AG39: =IF(AA39=0,0,AK39/(AI39*AC39)) -> 0 | AH39: =IF(ISNUMBER(原始输入与口径!T39),原始输入与口径!T39,"缺失") -> 175 | AI39: =IF(ISNUMBER(原始输入与口径!Y39),原始输入与口径!Y39,"缺失") -> 175 | AJ39: =IF(ISNUMBER(原始输入与口径!AI39),原始输入与口径!AI39,"缺失") -> 2.839 | AK39: =IF(ISNUMBER(原始输入与口径!AL39),原始输入与口径!AL39,"缺失") -> 0 | AL39: =IF(ISNUMBER(原始输入与口径!O39),原始输入与口径!O39,"缺失") -> 128 | AM39: =SUMIFS(相位SOC复算!$N$9:$N$929,相位SOC复算!$S$9:$S$929,31) -> 0.0011755694 | AN39: =SUMIFS(相位SOC复算!$Q$9:$Q$929,相位SOC复算!$S$9:$S$929,31) -> 0 | AO39: =SUMIFS(相位SOC复算!$R$9:$R$929,相位SOC复算!$S$9:$S$929,31) -> 0.38934857 | AP39: =相位SOC复算!J73 -> 35.347902 | AQ39: =AP39-J39 -> 0 | AR39: =IF(ISBLANK(原始输入与口径!M39),"",原始输入与口径!M39) -> 5.2473 | AS39: =IF(ISBLANK(原始输入与口径!L39),"",原始输入与口径!L39) -> 46234 | AT39: =IF(ISBLANK(原始输入与口径!A39),"",原始输入与口径!A39) -> 46235.188 | AU39: =IF(ISBLANK(原始输入与口径!I39),"",原始输入与口径!I39) -> 2026-08-01_27 | AV39: =IF(ISBLANK(原始输入与口径!J39),"",原始输入与口径!J39) -> 15 | AW39: =IF(ISBLANK(原始输入与口径!BB39),"",原始输入与口径!BB39) -> OK | AX39: =原始输入与口径!CI39 -> 128 | AY39: =原始输入与口径!BS39 -> 175 | AZ39: =原始输入与口径!BI39 -> 175 | BA39: =原始输入与口径!CM39 -> 40 | BB39: =原始输入与口径!BV39 -> 24 | BC39: =原始输入与口径!BL39 -> 24 | BD39: =46235 -> 46235 | BE39: =IF(K39=0,"零头寸，无结算现金",TEXT(K39,"0.000000")&" MW × "&TEXT(B39,"0.000000")&" × "&TEXT(AC39,"0.000000")&" h = "&TEXT(Q39,"0.000000")&" EUR") -> 零头寸，无结算现金 | BF39: =IF(L39=0,"零头寸，无结算现金",TEXT(L39,"0.000000")&" MW × "&TEXT(C39,"0.000000")&" × "&TEXT(AC39,"0.000000")&" h = "&TEXT(R39,"0.000000")&" EUR") -> 40.000000 MW × 66.224535 × 0.250000 h = 662.245345 EUR | BG39: =IF(M39=0,"零头寸，无结算现金",TEXT(M39,"0.000000")&" MW × "&TEXT(D39,"0.000000")&" × "&TEXT(AC39,"0.000000")&" h = "&TEXT(S39,"0.000000")&" EUR") -> 24.000000 MW × 6.691060 × 0.250000 h = 40.146361 EUR | BH39: =IF(N39=0,"零头寸，无结算现金",TEXT(N39,"0.000000")&" MW × "&TEXT(E39,"0.000000")&" × "&TEXT(AC39,"0.000000")&" h = "&TEXT(T39,"0.000000")&" EUR") -> 24.000000 MW × 2.607055 × 0.250000 h = 15.642330 EUR | BI39: =IF(O39=0,"零上调激活电量",TEXT(O39,"0.000000")&" MWh × "&TEXT(F39,"0.000000")&" = "&TEXT(U39,"0.000000")&" EUR") -> 0.389349 MWh × 174.241229 = 67.840574 EUR | BJ39: =IF(P39=0,"零下调激活电量","−("&TEXT(P39,"0.000000")&" MWh × "&TEXT(G39,"0.000000")&") = "&TEXT(V39,"0.000000")&" EUR") -> 零下调激活电量 | BK39: =TEXT(Q39,"0.000000")&" + "&TEXT(R39,"0.000000")&" + "&TEXT(S39,"0.000000")&" + "&TEXT(T39,"0.000000")&" + "&TEXT(U39,"0.000000")&" + "&TEXT(V39,"0.000000")&" = "&TEXT(W39,"0.000000")&" EUR" -> 0.000000 + 662.245345 + 40.146361 + 15.642330 + 67.840574 + 0.000000 = 785.874610 EUR
A40: =原始输入与口径!C40 -> 46235.323 | B40: =IF(ISNUMBER(原始输入与口径!H40),原始输入与口径!H40,"缺失") -> 149.8 | C40: =IF(ISNUMBER(原始输入与口径!R40),原始输入与口径!R40,"缺失") -> 66.224535 | D40: =IF(ISNUMBER(原始输入与口径!W40),原始输入与口径!W40,"缺失") -> 6.6910602 | E40: =IF(ISNUMBER(原始输入与口径!AB40),原始输入与口径!AB40,"缺失") -> 2.6070551 | F40: =IF(ISNUMBER(原始输入与口径!AG40),原始输入与口径!AG40,"缺失") -> 171.40396 | G40: =IF(ISNUMBER(原始输入与口径!AJ40),原始输入与口径!AJ40,"缺失") -> 76.420254 | H40: ="未模拟" -> 未模拟 | I40: =原始输入与口径!CD40 -> 35.347902 | J40: =原始输入与口径!CE40 -> 35.046629 | K40: =原始输入与口径!BZ40 -> 0 | L40: =原始输入与口径!CK40 -> 40 | M40: =原始输入与口径!BT40 -> 24 | N40: =原始输入与口径!BJ40 -> 24 | O40: =M40*AF40*AC40 -> 0.32859429 | P40: =N40*AG40*AC40 -> 0.060754286 | Q40: =IF(K40=0,0,IF(ISNUMBER(B40),K40*B40*AC40,NA())) -> 0 | R40: =IF(L40=0,0,IF(ISNUMBER(C40),L40*C40*AC40,NA())) -> 662.24535 | S40: =IF(M40=0,0,IF(ISNUMBER(D40),M40*D40*AC40,NA())) -> 40.146361 | T40: =IF(N40=0,0,IF(ISNUMBER(E40),N40*E40*AC40,NA())) -> 15.64233 | U40: =IF(O40=0,0,O40*F40) -> 56.322362 | V40: =IF(P40=0,0,-P40*G40) -> -4.642858 | W40: =SUM(Q40:V40) -> 769.71354 | X40: =原始输入与口径!CP40 -> 769.71354 | Y40: =W40-X40 -> 0 | Z40: ="当日执行" -> 当日执行 | AA40: =IF(原始输入与口径!AW40,1,0) -> 1 | AB40: =IF(原始输入与口径!AY40,1,0) -> 1 | AC40: =原始输入与口径!$F$5 -> 0.25 | AD40: =原始输入与口径!CG40 -> 0.3125 | AE40: =原始输入与口径!BQ40 -> 0.13714286 | AF40: =IF(AA40=0,0,AJ40/(AH40*AC40)) -> 0.054765714 | AG40: =IF(AA40=0,0,AK40/(AI40*AC40)) -> 0.010125714 | AH40: =IF(ISNUMBER(原始输入与口径!T40),原始输入与口径!T40,"缺失") -> 175 | AI40: =IF(ISNUMBER(原始输入与口径!Y40),原始输入与口径!Y40,"缺失") -> 175 | AJ40: =IF(ISNUMBER(原始输入与口径!AI40),原始输入与口径!AI40,"缺失") -> 2.396 | AK40: =IF(ISNUMBER(原始输入与口径!AL40),原始输入与口径!AL40,"缺失") -> 0.443 | AL40: =IF(ISNUMBER(原始输入与口径!O40),原始输入与口径!O40,"缺失") -> 128 | AM40: =SUMIFS(相位SOC复算!$N$9:$N$929,相位SOC复算!$S$9:$S$929,32) -> 0.0011473935 | AN40: =SUMIFS(相位SOC复算!$Q$9:$Q$929,相位SOC复算!$S$9:$S$929,32) -> 0.060754286 | AO40: =SUMIFS(相位SOC复算!$R$9:$R$929,相位SOC复算!$S$9:$S$929,32) -> 0.32859429 | AP40: =相位SOC复算!J76 -> 35.046629 | AQ40: =AP40-J40 -> 0 | AR40: =IF(ISBLANK(原始输入与口径!M40),"",原始输入与口径!M40) -> 5.2473 | AS40: =IF(ISBLANK(原始输入与口径!L40),"",原始输入与口径!L40) -> 46234 | AT40: =IF(ISBLANK(原始输入与口径!A40),"",原始输入与口径!A40) -> 46235.198 | AU40: =IF(ISBLANK(原始输入与口径!I40),"",原始输入与口径!I40) -> 2026-08-01_28 | AV40: =IF(ISBLANK(原始输入与口径!J40),"",原始输入与口径!J40) -> 15 | AW40: =IF(ISBLANK(原始输入与口径!BB40),"",原始输入与口径!BB40) -> OK | AX40: =原始输入与口径!CI40 -> 128 | AY40: =原始输入与口径!BS40 -> 175 | AZ40: =原始输入与口径!BI40 -> 175 | BA40: =原始输入与口径!CM40 -> 40 | BB40: =原始输入与口径!BV40 -> 24 | BC40: =原始输入与口径!BL40 -> 24 | BD40: =46235 -> 46235 | BE40: =IF(K40=0,"零头寸，无结算现金",TEXT(K40,"0.000000")&" MW × "&TEXT(B40,"0.000000")&" × "&TEXT(AC40,"0.000000")&" h = "&TEXT(Q40,"0.000000")&" EUR") -> 零头寸，无结算现金 | BF40: =IF(L40=0,"零头寸，无结算现金",TEXT(L40,"0.000000")&" MW × "&TEXT(C40,"0.000000")&" × "&TEXT(AC40,"0.000000")&" h = "&TEXT(R40,"0.000000")&" EUR") -> 40.000000 MW × 66.224535 × 0.250000 h = 662.245345 EUR | BG40: =IF(M40=0,"零头寸，无结算现金",TEXT(M40,"0.000000")&" MW × "&TEXT(D40,"0.000000")&" × "&TEXT(AC40,"0.000000")&" h = "&TEXT(S40,"0.000000")&" EUR") -> 24.000000 MW × 6.691060 × 0.250000 h = 40.146361 EUR | BH40: =IF(N40=0,"零头寸，无结算现金",TEXT(N40,"0.000000")&" MW × "&TEXT(E40,"0.000000")&" × "&TEXT(AC40,"0.000000")&" h = "&TEXT(T40,"0.000000")&" EUR") -> 24.000000 MW × 2.607055 × 0.250000 h = 15.642330 EUR | BI40: =IF(O40=0,"零上调激活电量",TEXT(O40,"0.000000")&" MWh × "&TEXT(F40,"0.000000")&" = "&TEXT(U40,"0.000000")&" EUR") -> 0.328594 MWh × 171.403960 = 56.322362 EUR | BJ40: =IF(P40=0,"零下调激活电量","−("&TEXT(P40,"0.000000")&" MWh × "&TEXT(G40,"0.000000")&") = "&TEXT(V40,"0.000000")&" EUR") -> −(0.060754 MWh × 76.420254) = -4.642858 EUR | BK40: =TEXT(Q40,"0.000000")&" + "&TEXT(R40,"0.000000")&" + "&TEXT(S40,"0.000000")&" + "&TEXT(T40,"0.000000")&" + "&TEXT(U40,"0.000000")&" + "&TEXT(V40,"0.000000")&" = "&TEXT(W40,"0.000000")&" EUR" -> 0.000000 + 662.245345 + 40.146361 + 15.642330 + 56.322362 + -4.642858 = 769.713540 EUR
A41: =原始输入与口径!C41 -> 46235.333 | B41: =IF(ISNUMBER(原始输入与口径!H41),原始输入与口径!H41,"缺失") -> 162.96 | C41: =IF(ISNUMBER(原始输入与口径!R41),原始输入与口径!R41,"缺失") -> 66.224535 | D41: =IF(ISNUMBER(原始输入与口径!W41),原始输入与口径!W41,"缺失") -> 6.7863473 | E41: =IF(ISNUMBER(原始输入与口径!AB41),原始输入与口径!AB41,"缺失") -> 2.6280182 | F41: =IF(ISNUMBER(原始输入与口径!AG41),原始输入与口径!AG41,"缺失") -> 201.87296 | G41: =IF(ISNUMBER(原始输入与口径!AJ41),原始输入与口径!AJ41,"缺失") -> 0 | H41: ="未模拟" -> 未模拟 | I41: =原始输入与口径!CD41 -> 35.046629 | J41: =原始输入与口径!CE41 -> 33.125436 | K41: =原始输入与口径!BZ41 -> 0 | L41: =原始输入与口径!CK41 -> 40 | M41: =原始输入与口径!BT41 -> 24 | N41: =原始输入与口径!BJ41 -> 24 | O41: =M41*AF41*AC41 -> 1.7674971 | P41: =N41*AG41*AC41 -> 0 | Q41: =IF(K41=0,0,IF(ISNUMBER(B41),K41*B41*AC41,NA())) -> 0 | R41: =IF(L41=0,0,IF(ISNUMBER(C41),L41*C41*AC41,NA())) -> 662.24535 | S41: =IF(M41=0,0,IF(ISNUMBER(D41),M41*D41*AC41,NA())) -> 40.718084 | T41: =IF(N41=0,0,IF(ISNUMBER(E41),N41*E41*AC41,NA())) -> 15.768109 | U41: =IF(O41=0,0,O41*F41) -> 356.80989 | V41: =IF(P41=0,0,-P41*G41) -> 0 | W41: =SUM(Q41:V41) -> 1075.5414 | X41: =原始输入与口径!CP41 -> 1075.5414 | Y41: =W41-X41 -> 0 | Z41: ="当日执行" -> 当日执行 | AA41: =IF(原始输入与口径!AW41,1,0) -> 1 | AB41: =IF(原始输入与口径!AY41,1,0) -> 1 | AC41: =原始输入与口径!$F$5 -> 0.25 | AD41: =原始输入与口径!CG41 -> 0.3125 | AE41: =原始输入与口径!BQ41 -> 0.13714286 | AF41: =IF(AA41=0,0,AJ41/(AH41*AC41)) -> 0.29458286 | AG41: =IF(AA41=0,0,AK41/(AI41*AC41)) -> 0 | AH41: =IF(ISNUMBER(原始输入与口径!T41),原始输入与口径!T41,"缺失") -> 175 | AI41: =IF(ISNUMBER(原始输入与口径!Y41),原始输入与口径!Y41,"缺失") -> 175 | AJ41: =IF(ISNUMBER(原始输入与口径!AI41),原始输入与口径!AI41,"缺失") -> 12.888 | AK41: =IF(ISNUMBER(原始输入与口径!AL41),原始输入与口径!AL41,"缺失") -> 0 | AL41: =IF(ISNUMBER(原始输入与口径!O41),原始输入与口径!O41,"缺失") -> 91.904 | AM41: =SUMIFS(相位SOC复算!$N$9:$N$929,相位SOC复算!$S$9:$S$929,33) -> 0.005336646 | AN41: =SUMIFS(相位SOC复算!$Q$9:$Q$929,相位SOC复算!$S$9:$S$929,33) -> 0 | AO41: =SUMIFS(相位SOC复算!$R$9:$R$929,相位SOC复算!$S$9:$S$929,33) -> 1.7674971 | AP41: =相位SOC复算!J78 -> 33.125436 | AQ41: =AP41-J41 -> 0 | AR41: =IF(ISBLANK(原始输入与口径!M41),"",原始输入与口径!M41) -> 5.2473 | AS41: =IF(ISBLANK(原始输入与口径!L41),"",原始输入与口径!L41) -> 46234 | AT41: =IF(ISBLANK(原始输入与口径!A41),"",原始输入与口径!A41) -> 46235.208 | AU41: =IF(ISBLANK(原始输入与口径!I41),"",原始输入与口径!I41) -> 2026-08-01_29 | AV41: =IF(ISBLANK(原始输入与口径!J41),"",原始输入与口径!J41) -> 15 | AW41: =IF(ISBLANK(原始输入与口径!BB41),"",原始输入与口径!BB41) -> OK | AX41: =原始输入与口径!CI41 -> 128 | AY41: =原始输入与口径!BS41 -> 175 | AZ41: =原始输入与口径!BI41 -> 175 | BA41: =原始输入与口径!CM41 -> 40 | BB41: =原始输入与口径!BV41 -> 24 | BC41: =原始输入与口径!BL41 -> 24 | BD41: =46235 -> 46235 | BE41: =IF(K41=0,"零头寸，无结算现金",TEXT(K41,"0.000000")&" MW × "&TEXT(B41,"0.000000")&" × "&TEXT(AC41,"0.000000")&" h = "&TEXT(Q41,"0.000000")&" EUR") -> 零头寸，无结算现金 | BF41: =IF(L41=0,"零头寸，无结算现金",TEXT(L41,"0.000000")&" MW × "&TEXT(C41,"0.000000")&" × "&TEXT(AC41,"0.000000")&" h = "&TEXT(R41,"0.000000")&" EUR") -> 40.000000 MW × 66.224535 × 0.250000 h = 662.245345 EUR | BG41: =IF(M41=0,"零头寸，无结算现金",TEXT(M41,"0.000000")&" MW × "&TEXT(D41,"0.000000")&" × "&TEXT(AC41,"0.000000")&" h = "&TEXT(S41,"0.000000")&" EUR") -> 24.000000 MW × 6.786347 × 0.250000 h = 40.718084 EUR | BH41: =IF(N41=0,"零头寸，无结算现金",TEXT(N41,"0.000000")&" MW × "&TEXT(E41,"0.000000")&" × "&TEXT(AC41,"0.000000")&" h = "&TEXT(T41,"0.000000")&" EUR") -> 24.000000 MW × 2.628018 × 0.250000 h = 15.768109 EUR | BI41: =IF(O41=0,"零上调激活电量",TEXT(O41,"0.000000")&" MWh × "&TEXT(F41,"0.000000")&" = "&TEXT(U41,"0.000000")&" EUR") -> 1.767497 MWh × 201.872963 = 356.809886 EUR | BJ41: =IF(P41=0,"零下调激活电量","−("&TEXT(P41,"0.000000")&" MWh × "&TEXT(G41,"0.000000")&") = "&TEXT(V41,"0.000000")&" EUR") -> 零下调激活电量 | BK41: =TEXT(Q41,"0.000000")&" + "&TEXT(R41,"0.000000")&" + "&TEXT(S41,"0.000000")&" + "&TEXT(T41,"0.000000")&" + "&TEXT(U41,"0.000000")&" + "&TEXT(V41,"0.000000")&" = "&TEXT(W41,"0.000000")&" EUR" -> 0.000000 + 662.245345 + 40.718084 + 15.768109 + 356.809886 + 0.000000 = 1075.541424 EUR
A42: =原始输入与口径!C42 -> 46235.344 | B42: =IF(ISNUMBER(原始输入与口径!H42),原始输入与口径!H42,"缺失") -> 147 | C42: =IF(ISNUMBER(原始输入与口径!R42),原始输入与口径!R42,"缺失") -> 66.224535 | D42: =IF(ISNUMBER(原始输入与口径!W42),原始输入与口径!W42,"缺失") -> 6.7863473 | E42: =IF(ISNUMBER(原始输入与口径!AB42),原始输入与口径!AB42,"缺失") -> 2.6280182 | F42: =IF(ISNUMBER(原始输入与口径!AG42),原始输入与口径!AG42,"缺失") -> 210.56334 | G42: =IF(ISNUMBER(原始输入与口径!AJ42),原始输入与口径!AJ42,"缺失") -> 0 | H42: ="未模拟" -> 未模拟 | I42: =原始输入与口径!CD42 -> 33.125436 | J42: =原始输入与口径!CE42 -> 31.952447 | K42: =原始输入与口径!BZ42 -> -1.1947284 | L42: =原始输入与口径!CK42 -> 40 | M42: =原始输入与口径!BT42 -> 24 | N42: =原始输入与口径!BJ42 -> 24 | O42: =M42*AF42*AC42 -> 1.3422171 | P42: =N42*AG42*AC42 -> 0 | Q42: =IF(K42=0,0,IF(ISNUMBER(B42),K42*B42*AC42,NA())) -> -43.906268 | R42: =IF(L42=0,0,IF(ISNUMBER(C42),L42*C42*AC42,NA())) -> 662.24535 | S42: =IF(M42=0,0,IF(ISNUMBER(D42),M42*D42*AC42,NA())) -> 40.718084 | T42: =IF(N42=0,0,IF(ISNUMBER(E42),N42*E42*AC42,NA())) -> 15.768109 | U42: =IF(O42=0,0,O42*F42) -> 282.62172 | V42: =IF(P42=0,0,-P42*G42) -> 0 | W42: =SUM(Q42:V42) -> 957.44699 | X42: =原始输入与口径!CP42 -> 957.44699 | Y42: =W42-X42 -> 0 | Z42: ="当日执行" -> 当日执行 | AA42: =IF(原始输入与口径!AW42,1,0) -> 1 | AB42: =IF(原始输入与口径!AY42,1,0) -> 1 | AC42: =原始输入与口径!$F$5 -> 0.25 | AD42: =原始输入与口径!CG42 -> 0.3125 | AE42: =原始输入与口径!BQ42 -> 0.13714286 | AF42: =IF(AA42=0,0,AJ42/(AH42*AC42)) -> 0.22370286 | AG42: =IF(AA42=0,0,AK42/(AI42*AC42)) -> 0 | AH42: =IF(ISNUMBER(原始输入与口径!T42),原始输入与口径!T42,"缺失") -> 175 | AI42: =IF(ISNUMBER(原始输入与口径!Y42),原始输入与口径!Y42,"缺失") -> 175 | AJ42: =IF(ISNUMBER(原始输入与口径!AI42),原始输入与口径!AI42,"缺失") -> 9.787 | AK42: =IF(ISNUMBER(原始输入与口径!AL42),原始输入与口径!AL42,"缺失") -> 0 | AL42: =IF(ISNUMBER(原始输入与口径!O42),原始输入与口径!O42,"缺失") -> 91.904 | AM42: =SUMIFS(相位SOC复算!$N$9:$N$929,相位SOC复算!$S$9:$S$929,34) -> 0.0044433953 | AN42: =SUMIFS(相位SOC复算!$Q$9:$Q$929,相位SOC复算!$S$9:$S$929,34) -> 0.23186605 | AO42: =SUMIFS(相位SOC复算!$R$9:$R$929,相位SOC复算!$S$9:$S$929,34) -> 1.2754011 | AP42: =相位SOC复算!J80 -> 31.952447 | AQ42: =AP42-J42 -> 0 | AR42: =IF(ISBLANK(原始输入与口径!M42),"",原始输入与口径!M42) -> 5.2473 | AS42: =IF(ISBLANK(原始输入与口径!L42),"",原始输入与口径!L42) -> 46234 | AT42: =IF(ISBLANK(原始输入与口径!A42),"",原始输入与口径!A42) -> 46235.219 | AU42: =IF(ISBLANK(原始输入与口径!I42),"",原始输入与口径!I42) -> 2026-08-01_30 | AV42: =IF(ISBLANK(原始输入与口径!J42),"",原始输入与口径!J42) -> 15 | AW42: =IF(ISBLANK(原始输入与口径!BB42),"",原始输入与口径!BB42) -> OK | AX42: =原始输入与口径!CI42 -> 128 | AY42: =原始输入与口径!BS42 -> 175 | AZ42: =原始输入与口径!BI42 -> 175 | BA42: =原始输入与口径!CM42 -> 40 | BB42: =原始输入与口径!BV42 -> 24 | BC42: =原始输入与口径!BL42 -> 24 | BD42: =46235 -> 46235 | BE42: =IF(K42=0,"零头寸，无结算现金",TEXT(K42,"0.000000")&" MW × "&TEXT(B42,"0.000000")&" × "&TEXT(AC42,"0.000000")&" h = "&TEXT(Q42,"0.000000")&" EUR") -> -1.194728 MW × 147.000000 × 0.250000 h = -43.906268 EUR | BF42: =IF(L42=0,"零头寸，无结算现金",TEXT(L42,"0.000000")&" MW × "&TEXT(C42,"0.000000")&" × "&TEXT(AC42,"0.000000")&" h = "&TEXT(R42,"0.000000")&" EUR") -> 40.000000 MW × 66.224535 × 0.250000 h = 662.245345 EUR | BG42: =IF(M42=0,"零头寸，无结算现金",TEXT(M42,"0.000000")&" MW × "&TEXT(D42,"0.000000")&" × "&TEXT(AC42,"0.000000")&" h = "&TEXT(S42,"0.000000")&" EUR") -> 24.000000 MW × 6.786347 × 0.250000 h = 40.718084 EUR | BH42: =IF(N42=0,"零头寸，无结算现金",TEXT(N42,"0.000000")&" MW × "&TEXT(E42,"0.000000")&" × "&TEXT(AC42,"0.000000")&" h = "&TEXT(T42,"0.000000")&" EUR") -> 24.000000 MW × 2.628018 × 0.250000 h = 15.768109 EUR | BI42: =IF(O42=0,"零上调激活电量",TEXT(O42,"0.000000")&" MWh × "&TEXT(F42,"0.000000")&" = "&TEXT(U42,"0.000000")&" EUR") -> 1.342217 MWh × 210.563337 = 282.621721 EUR | BJ42: =IF(P42=0,"零下调激活电量","−("&TEXT(P42,"0.000000")&" MWh × "&TEXT(G42,"0.000000")&") = "&TEXT(V42,"0.000000")&" EUR") -> 零下调激活电量 | BK42: =TEXT(Q42,"0.000000")&" + "&TEXT(R42,"0.000000")&" + "&TEXT(S42,"0.000000")&" + "&TEXT(T42,"0.000000")&" + "&TEXT(U42,"0.000000")&" + "&TEXT(V42,"0.000000")&" = "&TEXT(W42,"0.000000")&" EUR" -> -43.906268 + 662.245345 + 40.718084 + 15.768109 + 282.621721 + 0.000000 = 957.446992 EUR
A43: =原始输入与口径!C43 -> 46235.354 | B43: =IF(ISNUMBER(原始输入与口径!H43),原始输入与口径!H43,"缺失") -> 141.73 | C43: =IF(ISNUMBER(原始输入与口径!R43),原始输入与口径!R43,"缺失") -> 66.224535 | D43: =IF(ISNUMBER(原始输入与口径!W43),原始输入与口径!W43,"缺失") -> 6.7863473 | E43: =IF(ISNUMBER(原始输入与口径!AB43),原始输入与口径!AB43,"缺失") -> 2.6280182 | F43: =IF(ISNUMBER(原始输入与口径!AG43),原始输入与口径!AG43,"缺失") -> 169.09306 | G43: =IF(ISNUMBER(原始输入与口径!AJ43),原始输入与口径!AJ43,"缺失") -> 0 | H43: ="未模拟" -> 未模拟 | I43: =原始输入与口径!CD43 -> 31.952447 | J43: =原始输入与口径!CE43 -> 31.73913 | K43: =原始输入与口径!BZ43 -> 0 | L43: =原始输入与口径!CK43 -> 40 | M43: =原始输入与口径!BT43 -> 24 | N43: =原始输入与口径!BJ43 -> 24 | O43: =M43*AF43*AC43 -> 0.19625143 | P43: =N43*AG43*AC43 -> 0 | Q43: =IF(K43=0,0,IF(ISNUMBER(B43),K43*B43*AC43,NA())) -> 0 | R43: =IF(L43=0,0,IF(ISNUMBER(C43),L43*C43*AC43,NA())) -> 662.24535 | S43: =IF(M43=0,0,IF(ISNUMBER(D43),M43*D43*AC43,NA())) -> 40.718084 | T43: =IF(N43=0,0,IF(ISNUMBER(E43),N43*E43*AC43,NA())) -> 15.768109 | U43: =IF(O43=0,0,O43*F43) -> 33.184754 | V43: =IF(P43=0,0,-P43*G43) -> 0 | W43: =SUM(Q43:V43) -> 751.91629 | X43: =原始输入与口径!CP43 -> 751.91629 | Y43: =W43-X43 -> 0 | Z43: ="当日执行" -> 当日执行 | AA43: =IF(原始输入与口径!AW43,1,0) -> 1 | AB43: =IF(原始输入与口径!AY43,1,0) -> 1 | AC43: =原始输入与口径!$F$5 -> 0.25 | AD43: =原始输入与口径!CG43 -> 0.3125 | AE43: =原始输入与口径!BQ43 -> 0.13714286 | AF43: =IF(AA43=0,0,AJ43/(AH43*AC43)) -> 0.032708571 | AG43: =IF(AA43=0,0,AK43/(AI43*AC43)) -> 0 | AH43: =IF(ISNUMBER(原始输入与口径!T43),原始输入与口径!T43,"缺失") -> 175 | AI43: =IF(ISNUMBER(原始输入与口径!Y43),原始输入与口径!Y43,"缺失") -> 175 | AJ43: =IF(ISNUMBER(原始输入与口径!AI43),原始输入与口径!AI43,"缺失") -> 1.431 | AK43: =IF(ISNUMBER(原始输入与口径!AL43),原始输入与口径!AL43,"缺失") -> 0 | AL43: =IF(ISNUMBER(原始输入与口径!O43),原始输入与口径!O43,"缺失") -> 91.904 | AM43: =SUMIFS(相位SOC复算!$N$9:$N$929,相位SOC复算!$S$9:$S$929,35) -> 0.00059254658 | AN43: =SUMIFS(相位SOC复算!$Q$9:$Q$929,相位SOC复算!$S$9:$S$929,35) -> 0 | AO43: =SUMIFS(相位SOC复算!$R$9:$R$929,相位SOC复算!$S$9:$S$929,35) -> 0.19625143 | AP43: =相位SOC复算!J82 -> 31.73913 | AQ43: =AP43-J43 -> 0 | AR43: =IF(ISBLANK(原始输入与口径!M43),"",原始输入与口径!M43) -> 5.2473 | AS43: =IF(ISBLANK(原始输入与口径!L43),"",原始输入与口径!L43) -> 46234 | AT43: =IF(ISBLANK(原始输入与口径!A43),"",原始输入与口径!A43) -> 46235.229 | AU43: =IF(ISBLANK(原始输入与口径!I43),"",原始输入与口径!I43) -> 2026-08-01_31 | AV43: =IF(ISBLANK(原始输入与口径!J43),"",原始输入与口径!J43) -> 15 | AW43: =IF(ISBLANK(原始输入与口径!BB43),"",原始输入与口径!BB43) -> OK | AX43: =原始输入与口径!CI43 -> 128 | AY43: =原始输入与口径!BS43 -> 175 | AZ43: =原始输入与口径!BI43 -> 175 | BA43: =原始输入与口径!CM43 -> 40 | BB43: =原始输入与口径!BV43 -> 24 | BC43: =原始输入与口径!BL43 -> 24 | BD43: =46235 -> 46235 | BE43: =IF(K43=0,"零头寸，无结算现金",TEXT(K43,"0.000000")&" MW × "&TEXT(B43,"0.000000")&" × "&TEXT(AC43,"0.000000")&" h = "&TEXT(Q43,"0.000000")&" EUR") -> 零头寸，无结算现金 | BF43: =IF(L43=0,"零头寸，无结算现金",TEXT(L43,"0.000000")&" MW × "&TEXT(C43,"0.000000")&" × "&TEXT(AC43,"0.000000")&" h = "&TEXT(R43,"0.000000")&" EUR") -> 40.000000 MW × 66.224535 × 0.250000 h = 662.245345 EUR | BG43: =IF(M43=0,"零头寸，无结算现金",TEXT(M43,"0.000000")&" MW × "&TEXT(D43,"0.000000")&" × "&TEXT(AC43,"0.000000")&" h = "&TEXT(S43,"0.000000")&" EUR") -> 24.000000 MW × 6.786347 × 0.250000 h = 40.718084 EUR | BH43: =IF(N43=0,"零头寸，无结算现金",TEXT(N43,"0.000000")&" MW × "&TEXT(E43,"0.000000")&" × "&TEXT(AC43,"0.000000")&" h = "&TEXT(T43,"0.000000")&" EUR") -> 24.000000 MW × 2.628018 × 0.250000 h = 15.768109 EUR | BI43: =IF(O43=0,"零上调激活电量",TEXT(O43,"0.000000")&" MWh × "&TEXT(F43,"0.000000")&" = "&TEXT(U43,"0.000000")&" EUR") -> 0.196251 MWh × 169.093057 = 33.184754 EUR | BJ43: =IF(P43=0,"零下调激活电量","−("&TEXT(P43,"0.000000")&" MWh × "&TEXT(G43,"0.000000")&") = "&TEXT(V43,"0.000000")&" EUR") -> 零下调激活电量 | BK43: =TEXT(Q43,"0.000000")&" + "&TEXT(R43,"0.000000")&" + "&TEXT(S43,"0.000000")&" + "&TEXT(T43,"0.000000")&" + "&TEXT(U43,"0.000000")&" + "&TEXT(V43,"0.000000")&" = "&TEXT(W43,"0.000000")&" EUR" -> 0.000000 + 662.245345 + 40.718084 + 15.768109 + 33.184754 + 0.000000 = 751.916292 EUR
A44: =原始输入与口径!C44 -> 46235.365 | B44: =IF(ISNUMBER(原始输入与口径!H44),原始输入与口径!H44,"缺失") -> 134 | C44: =IF(ISNUMBER(原始输入与口径!R44),原始输入与口径!R44,"缺失") -> 66.224535 | D44: =IF(ISNUMBER(原始输入与口径!W44),原始输入与口径!W44,"缺失") -> 6.7863473 | E44: =IF(ISNUMBER(原始输入与口径!AB44),原始输入与口径!AB44,"缺失") -> 2.6280182 | F44: =IF(ISNUMBER(原始输入与口径!AG44),原始输入与口径!AG44,"缺失") -> 156.11057 | G44: =IF(ISNUMBER(原始输入与口径!AJ44),原始输入与口径!AJ44,"缺失") -> 74.098489 | H44: ="未模拟" -> 未模拟 | I44: =原始输入与口径!CD44 -> 31.73913 | J44: =原始输入与口径!CE44 -> 40.239047 | K44: =原始输入与口径!BZ44 -> -36 | L44: =原始输入与口径!CK44 -> 40 | M44: =原始输入与口径!BT44 -> 24 | N44: =原始输入与口径!BJ44 -> 24 | O44: =M44*AF44*AC44 -> 0.012068571 | P44: =N44*AG44*AC44 -> 0.25110857 | Q44: =IF(K44=0,0,IF(ISNUMBER(B44),K44*B44*AC44,NA())) -> -1206 | R44: =IF(L44=0,0,IF(ISNUMBER(C44),L44*C44*AC44,NA())) -> 662.24535 | S44: =IF(M44=0,0,IF(ISNUMBER(D44),M44*D44*AC44,NA())) -> 40.718084 | T44: =IF(N44=0,0,IF(ISNUMBER(E44),N44*E44*AC44,NA())) -> 15.768109 | U44: =IF(O44=0,0,O44*F44) -> 1.8840316 | V44: =IF(P44=0,0,-P44*G44) -> -18.606766 | W44: =SUM(Q44:V44) -> -503.9912 | X44: =原始输入与口径!CP44 -> -503.9912 | Y44: =W44-X44 -> 0 | Z44: ="当日执行" -> 当日执行 | AA44: =IF(原始输入与口径!AW44,1,0) -> 1 | AB44: =IF(原始输入与口径!AY44,1,0) -> 1 | AC44: =原始输入与口径!$F$5 -> 0.25 | AD44: =原始输入与口径!CG44 -> 0.3125 | AE44: =原始输入与口径!BQ44 -> 0.13714286 | AF44: =IF(AA44=0,0,AJ44/(AH44*AC44)) -> 0.0020114286 | AG44: =IF(AA44=0,0,AK44/(AI44*AC44)) -> 0.041851429 | AH44: =IF(ISNUMBER(原始输入与口径!T44),原始输入与口径!T44,"缺失") -> 175 | AI44: =IF(ISNUMBER(原始输入与口径!Y44),原始输入与口径!Y44,"缺失") -> 175 | AJ44: =IF(ISNUMBER(原始输入与口径!AI44),原始输入与口径!AI44,"缺失") -> 0.088 | AK44: =IF(ISNUMBER(原始输入与口径!AL44),原始输入与口径!AL44,"缺失") -> 1.831 | AL44: =IF(ISNUMBER(原始输入与口径!O44),原始输入与口径!O44,"缺失") -> 91.904 | AM44: =SUMIFS(相位SOC复算!$N$9:$N$929,相位SOC复算!$S$9:$S$929,36) -> 0.02361088 | AN44: =SUMIFS(相位SOC复算!$Q$9:$Q$929,相位SOC复算!$S$9:$S$929,36) -> 9.23904 | AO44: =SUMIFS(相位SOC复算!$R$9:$R$929,相位SOC复算!$S$9:$S$929,36) -> 0 | AP44: =相位SOC复算!J85 -> 40.239047 | AQ44: =AP44-J44 -> 0 | AR44: =IF(ISBLANK(原始输入与口径!M44),"",原始输入与口径!M44) -> 5.2473 | AS44: =IF(ISBLANK(原始输入与口径!L44),"",原始输入与口径!L44) -> 46234 | AT44: =IF(ISBLANK(原始输入与口径!A44),"",原始输入与口径!A44) -> 46235.24 | AU44: =IF(ISBLANK(原始输入与口径!I44),"",原始输入与口径!I44) -> 2026-08-01_32 | AV44: =IF(ISBLANK(原始输入与口径!J44),"",原始输入与口径!J44) -> 15 | AW44: =IF(ISBLANK(原始输入与口径!BB44),"",原始输入与口径!BB44) -> OK | AX44: =原始输入与口径!CI44 -> 128 | AY44: =原始输入与口径!BS44 -> 175 | AZ44: =原始输入与口径!BI44 -> 175 | BA44: =原始输入与口径!CM44 -> 40 | BB44: =原始输入与口径!BV44 -> 24 | BC44: =原始输入与口径!BL44 -> 24 | BD44: =46235 -> 46235 | BE44: =IF(K44=0,"零头寸，无结算现金",TEXT(K44,"0.000000")&" MW × "&TEXT(B44,"0.000000")&" × "&TEXT(AC44,"0.000000")&" h = "&TEXT(Q44,"0.000000")&" EUR") -> -36.000000 MW × 134.000000 × 0.250000 h = -1206.000000 EUR | BF44: =IF(L44=0,"零头寸，无结算现金",TEXT(L44,"0.000000")&" MW × "&TEXT(C44,"0.000000")&" × "&TEXT(AC44,"0.000000")&" h = "&TEXT(R44,"0.000000")&" EUR") -> 40.000000 MW × 66.224535 × 0.250000 h = 662.245345 EUR | BG44: =IF(M44=0,"零头寸，无结算现金",TEXT(M44,"0.000000")&" MW × "&TEXT(D44,"0.000000")&" × "&TEXT(AC44,"0.000000")&" h = "&TEXT(S44,"0.000000")&" EUR") -> 24.000000 MW × 6.786347 × 0.250000 h = 40.718084 EUR | BH44: =IF(N44=0,"零头寸，无结算现金",TEXT(N44,"0.000000")&" MW × "&TEXT(E44,"0.000000")&" × "&TEXT(AC44,"0.000000")&" h = "&TEXT(T44,"0.000000")&" EUR") -> 24.000000 MW × 2.628018 × 0.250000 h = 15.768109 EUR | BI44: =IF(O44=0,"零上调激活电量",TEXT(O44,"0.000000")&" MWh × "&TEXT(F44,"0.000000")&" = "&TEXT(U44,"0.000000")&" EUR") -> 0.012069 MWh × 156.110571 = 1.884032 EUR | BJ44: =IF(P44=0,"零下调激活电量","−("&TEXT(P44,"0.000000")&" MWh × "&TEXT(G44,"0.000000")&") = "&TEXT(V44,"0.000000")&" EUR") -> −(0.251109 MWh × 74.098489) = -18.606766 EUR | BK44: =TEXT(Q44,"0.000000")&" + "&TEXT(R44,"0.000000")&" + "&TEXT(S44,"0.000000")&" + "&TEXT(T44,"0.000000")&" + "&TEXT(U44,"0.000000")&" + "&TEXT(V44,"0.000000")&" = "&TEXT(W44,"0.000000")&" EUR" -> -1206.000000 + 662.245345 + 40.718084 + 15.768109 + 1.884032 + -18.606766 = -503.991196 EUR
A45: =原始输入与口径!C45 -> 46235.375 | B45: =IF(ISNUMBER(原始输入与口径!H45),原始输入与口径!H45,"缺失") -> 160.86 | C45: =IF(ISNUMBER(原始输入与口径!R45),原始输入与口径!R45,"缺失") -> 66.224535 | D45: =IF(ISNUMBER(原始输入与口径!W45),原始输入与口径!W45,"缺失") -> 7.2056105 | E45: =IF(ISNUMBER(原始输入与口径!AB45),原始输入与口径!AB45,"缺失") -> 2.3250052 | F45: =IF(ISNUMBER(原始输入与口径!AG45),原始输入与口径!AG45,"缺失") -> 164.5269 | G45: =IF(ISNUMBER(原始输入与口径!AJ45),原始输入与口径!AJ45,"缺失") -> 76.22968 | H45: ="未模拟" -> 未模拟 | I45: =原始输入与口径!CD45 -> 40.239047 | J45: =原始输入与口径!CE45 -> 31.848099 | K45: =原始输入与口径!BZ45 -> 29.164951 | L45: =原始输入与口径!CK45 -> 40 | M45: =原始输入与口径!BT45 -> 24 | N45: =原始输入与口径!BJ45 -> 0 | O45: =M45*AF45*AC45 -> 0.42843429 | P45: =N45*AG45*AC45 -> 0 | Q45: =IF(K45=0,0,IF(ISNUMBER(B45),K45*B45*AC45,NA())) -> 1172.8685 | R45: =IF(L45=0,0,IF(ISNUMBER(C45),L45*C45*AC45,NA())) -> 662.24535 | S45: =IF(M45=0,0,IF(ISNUMBER(D45),M45*D45*AC45,NA())) -> 43.233663 | T45: =IF(N45=0,0,IF(ISNUMBER(E45),N45*E45*AC45,NA())) -> 0 | U45: =IF(O45=0,0,O45*F45) -> 70.488965 | V45: =IF(P45=0,0,-P45*G45) -> 0 | W45: =SUM(Q45:V45) -> 1948.8365 | X45: =原始输入与口径!CP45 -> 1948.8365 | Y45: =W45-X45 -> 0 | Z45: ="当日执行" -> 当日执行 | AA45: =IF(原始输入与口径!AW45,1,0) -> 1 | AB45: =IF(原始输入与口径!AY45,1,0) -> 1 | AC45: =原始输入与口径!$F$5 -> 0.25 | AD45: =原始输入与口径!CG45 -> 0.3125 | AE45: =原始输入与口径!BQ45 -> 0.13714286 | AF45: =IF(AA45=0,0,AJ45/(AH45*AC45)) -> 0.071405714 | AG45: =IF(AA45=0,0,AK45/(AI45*AC45)) -> 0.0059885714 | AH45: =IF(ISNUMBER(原始输入与口径!T45),原始输入与口径!T45,"缺失") -> 175 | AI45: =IF(ISNUMBER(原始输入与口径!Y45),原始输入与口径!Y45,"缺失") -> 175 | AJ45: =IF(ISNUMBER(原始输入与口径!AI45),原始输入与口径!AI45,"缺失") -> 3.124 | AK45: =IF(ISNUMBER(原始输入与口径!AL45),原始输入与口径!AL45,"缺失") -> 0.262 | AL45: =IF(ISNUMBER(原始输入与口径!O45),原始输入与口径!O45,"缺失") -> 91.904 | AM45: =SUMIFS(相位SOC复算!$N$9:$N$929,相位SOC复算!$S$9:$S$929,37) -> 0.023308188 | AN45: =SUMIFS(相位SOC复算!$Q$9:$Q$929,相位SOC复算!$S$9:$S$929,37) -> 0 | AO45: =SUMIFS(相位SOC复算!$R$9:$R$929,相位SOC复算!$S$9:$S$929,37) -> 7.719672 | AP45: =相位SOC复算!J88 -> 31.848099 | AQ45: =AP45-J45 -> 0 | AR45: =IF(ISBLANK(原始输入与口径!M45),"",原始输入与口径!M45) -> 5.2473 | AS45: =IF(ISBLANK(原始输入与口径!L45),"",原始输入与口径!L45) -> 46234 | AT45: =IF(ISBLANK(原始输入与口径!A45),"",原始输入与口径!A45) -> 46235.25 | AU45: =IF(ISBLANK(原始输入与口径!I45),"",原始输入与口径!I45) -> 2026-08-01_33 | AV45: =IF(ISBLANK(原始输入与口径!J45),"",原始输入与口径!J45) -> 15 | AW45: =IF(ISBLANK(原始输入与口径!BB45),"",原始输入与口径!BB45) -> OK | AX45: =原始输入与口径!CI45 -> 128 | AY45: =原始输入与口径!BS45 -> 175 | AZ45: =原始输入与口径!BI45 -> 175 | BA45: =原始输入与口径!CM45 -> 40 | BB45: =原始输入与口径!BV45 -> 24 | BC45: =原始输入与口径!BL45 -> 24 | BD45: =46235 -> 46235 | BE45: =IF(K45=0,"零头寸，无结算现金",TEXT(K45,"0.000000")&" MW × "&TEXT(B45,"0.000000")&" × "&TEXT(AC45,"0.000000")&" h = "&TEXT(Q45,"0.000000")&" EUR") -> 29.164951 MW × 160.860000 × 0.250000 h = 1172.868503 EUR | BF45: =IF(L45=0,"零头寸，无结算现金",TEXT(L45,"0.000000")&" MW × "&TEXT(C45,"0.000000")&" × "&TEXT(AC45,"0.000000")&" h = "&TEXT(R45,"0.000000")&" EUR") -> 40.000000 MW × 66.224535 × 0.250000 h = 662.245345 EUR | BG45: =IF(M45=0,"零头寸，无结算现金",TEXT(M45,"0.000000")&" MW × "&TEXT(D45,"0.000000")&" × "&TEXT(AC45,"0.000000")&" h = "&TEXT(S45,"0.000000")&" EUR") -> 24.000000 MW × 7.205611 × 0.250000 h = 43.233663 EUR | BH45: =IF(N45=0,"零头寸，无结算现金",TEXT(N45,"0.000000")&" MW × "&TEXT(E45,"0.000000")&" × "&TEXT(AC45,"0.000000")&" h = "&TEXT(T45,"0.000000")&" EUR") -> 零头寸，无结算现金 | BI45: =IF(O45=0,"零上调激活电量",TEXT(O45,"0.000000")&" MWh × "&TEXT(F45,"0.000000")&" = "&TEXT(U45,"0.000000")&" EUR") -> 0.428434 MWh × 164.526900 = 70.488965 EUR | BJ45: =IF(P45=0,"零下调激活电量","−("&TEXT(P45,"0.000000")&" MWh × "&TEXT(G45,"0.000000")&") = "&TEXT(V45,"0.000000")&" EUR") -> 零下调激活电量 | BK45: =TEXT(Q45,"0.000000")&" + "&TEXT(R45,"0.000000")&" + "&TEXT(S45,"0.000000")&" + "&TEXT(T45,"0.000000")&" + "&TEXT(U45,"0.000000")&" + "&TEXT(V45,"0.000000")&" = "&TEXT(W45,"0.000000")&" EUR" -> 1172.868503 + 662.245345 + 43.233663 + 0.000000 + 70.488965 + 0.000000 = 1948.836476 EUR
A46: =原始输入与口径!C46 -> 46235.385 | B46: =IF(ISNUMBER(原始输入与口径!H46),原始输入与口径!H46,"缺失") -> 143.7 | C46: =IF(ISNUMBER(原始输入与口径!R46),原始输入与口径!R46,"缺失") -> 66.224535 | D46: =IF(ISNUMBER(原始输入与口径!W46),原始输入与口径!W46,"缺失") -> 7.2056105 | E46: =IF(ISNUMBER(原始输入与口径!AB46),原始输入与口径!AB46,"缺失") -> 2.3250052 | F46: =IF(ISNUMBER(原始输入与口径!AG46),原始输入与口径!AG46,"缺失") -> 133.21137 | G46: =IF(ISNUMBER(原始输入与口径!AJ46),原始输入与口径!AJ46,"缺失") -> 76.22968 | H46: ="未模拟" -> 未模拟 | I46: =原始输入与口径!CD46 -> 31.848099 | J46: =原始输入与口径!CE46 -> 31.834534 | K46: =原始输入与口径!BZ46 -> 0 | L46: =原始输入与口径!CK46 -> 40 | M46: =原始输入与口径!BT46 -> 24 | N46: =原始输入与口径!BJ46 -> 0 | O46: =M46*AF46*AC46 -> 0.01248 | P46: =N46*AG46*AC46 -> 0 | Q46: =IF(K46=0,0,IF(ISNUMBER(B46),K46*B46*AC46,NA())) -> 0 | R46: =IF(L46=0,0,IF(ISNUMBER(C46),L46*C46*AC46,NA())) -> 662.24535 | S46: =IF(M46=0,0,IF(ISNUMBER(D46),M46*D46*AC46,NA())) -> 43.233663 | T46: =IF(N46=0,0,IF(ISNUMBER(E46),N46*E46*AC46,NA())) -> 0 | U46: =IF(O46=0,0,O46*F46) -> 1.6624778 | V46: =IF(P46=0,0,-P46*G46) -> 0 | W46: =SUM(Q46:V46) -> 707.14149 | X46: =原始输入与口径!CP46 -> 707.14149 | Y46: =W46-X46 -> 0 | Z46: ="当日执行" -> 当日执行 | AA46: =IF(原始输入与口径!AW46,1,0) -> 1 | AB46: =IF(原始输入与口径!AY46,1,0) -> 1 | AC46: =原始输入与口径!$F$5 -> 0.25 | AD46: =原始输入与口径!CG46 -> 0.3125 | AE46: =原始输入与口径!BQ46 -> 0.13714286 | AF46: =IF(AA46=0,0,AJ46/(AH46*AC46)) -> 0.00208 | AG46: =IF(AA46=0,0,AK46/(AI46*AC46)) -> 0.0024457143 | AH46: =IF(ISNUMBER(原始输入与口径!T46),原始输入与口径!T46,"缺失") -> 175 | AI46: =IF(ISNUMBER(原始输入与口径!Y46),原始输入与口径!Y46,"缺失") -> 175 | AJ46: =IF(ISNUMBER(原始输入与口径!AI46),原始输入与口径!AI46,"缺失") -> 0.091 | AK46: =IF(ISNUMBER(原始输入与口径!AL46),原始输入与口径!AL46,"缺失") -> 0.107 | AL46: =IF(ISNUMBER(原始输入与口径!O46),原始输入与口径!O46,"缺失") -> 91.904 | AM46: =SUMIFS(相位SOC复算!$N$9:$N$929,相位SOC复算!$S$9:$S$929,38) -> 3.7681159e-05 | AN46: =SUMIFS(相位SOC复算!$Q$9:$Q$929,相位SOC复算!$S$9:$S$929,38) -> 0 | AO46: =SUMIFS(相位SOC复算!$R$9:$R$929,相位SOC复算!$S$9:$S$929,38) -> 0.01248 | AP46: =相位SOC复算!J91 -> 31.834534 | AQ46: =AP46-J46 -> 0 | AR46: =IF(ISBLANK(原始输入与口径!M46),"",原始输入与口径!M46) -> 5.2473 | AS46: =IF(ISBLANK(原始输入与口径!L46),"",原始输入与口径!L46) -> 46234 | AT46: =IF(ISBLANK(原始输入与口径!A46),"",原始输入与口径!A46) -> 46235.26 | AU46: =IF(ISBLANK(原始输入与口径!I46),"",原始输入与口径!I46) -> 2026-08-01_34 | AV46: =IF(ISBLANK(原始输入与口径!J46),"",原始输入与口径!J46) -> 15 | AW46: =IF(ISBLANK(原始输入与口径!BB46),"",原始输入与口径!BB46) -> OK | AX46: =原始输入与口径!CI46 -> 128 | AY46: =原始输入与口径!BS46 -> 175 | AZ46: =原始输入与口径!BI46 -> 175 | BA46: =原始输入与口径!CM46 -> 40 | BB46: =原始输入与口径!BV46 -> 24 | BC46: =原始输入与口径!BL46 -> 24 | BD46: =46235 -> 46235 | BE46: =IF(K46=0,"零头寸，无结算现金",TEXT(K46,"0.000000")&" MW × "&TEXT(B46,"0.000000")&" × "&TEXT(AC46,"0.000000")&" h = "&TEXT(Q46,"0.000000")&" EUR") -> 零头寸，无结算现金 | BF46: =IF(L46=0,"零头寸，无结算现金",TEXT(L46,"0.000000")&" MW × "&TEXT(C46,"0.000000")&" × "&TEXT(AC46,"0.000000")&" h = "&TEXT(R46,"0.000000")&" EUR") -> 40.000000 MW × 66.224535 × 0.250000 h = 662.245345 EUR | BG46: =IF(M46=0,"零头寸，无结算现金",TEXT(M46,"0.000000")&" MW × "&TEXT(D46,"0.000000")&" × "&TEXT(AC46,"0.000000")&" h = "&TEXT(S46,"0.000000")&" EUR") -> 24.000000 MW × 7.205611 × 0.250000 h = 43.233663 EUR | BH46: =IF(N46=0,"零头寸，无结算现金",TEXT(N46,"0.000000")&" MW × "&TEXT(E46,"0.000000")&" × "&TEXT(AC46,"0.000000")&" h = "&TEXT(T46,"0.000000")&" EUR") -> 零头寸，无结算现金 | BI46: =IF(O46=0,"零上调激活电量",TEXT(O46,"0.000000")&" MWh × "&TEXT(F46,"0.000000")&" = "&TEXT(U46,"0.000000")&" EUR") -> 0.012480 MWh × 133.211366 = 1.662478 EUR | BJ46: =IF(P46=0,"零下调激活电量","−("&TEXT(P46,"0.000000")&" MWh × "&TEXT(G46,"0.000000")&") = "&TEXT(V46,"0.000000")&" EUR") -> 零下调激活电量 | BK46: =TEXT(Q46,"0.000000")&" + "&TEXT(R46,"0.000000")&" + "&TEXT(S46,"0.000000")&" + "&TEXT(T46,"0.000000")&" + "&TEXT(U46,"0.000000")&" + "&TEXT(V46,"0.000000")&" = "&TEXT(W46,"0.000000")&" EUR" -> 0.000000 + 662.245345 + 43.233663 + 0.000000 + 1.662478 + 0.000000 = 707.141486 EUR
A47: =原始输入与口径!C47 -> 46235.396 | B47: =IF(ISNUMBER(原始输入与口径!H47),原始输入与口径!H47,"缺失") -> 133.18 | C47: =IF(ISNUMBER(原始输入与口径!R47),原始输入与口径!R47,"缺失") -> 66.224535 | D47: =IF(ISNUMBER(原始输入与口径!W47),原始输入与口径!W47,"缺失") -> 7.2056105 | E47: =IF(ISNUMBER(原始输入与口径!AB47),原始输入与口径!AB47,"缺失") -> 2.3250052 | F47: =IF(ISNUMBER(原始输入与口径!AG47),原始输入与口径!AG47,"缺失") -> 133.21137 | G47: =IF(ISNUMBER(原始输入与口径!AJ47),原始输入与口径!AJ47,"缺失") -> 76.22968 | H47: ="未模拟" -> 未模拟 | I47: =原始输入与口径!CD47 -> 31.834534 | J47: =原始输入与口径!CE47 -> 31.73913 | K47: =原始输入与口径!BZ47 -> 0 | L47: =原始输入与口径!CK47 -> 40 | M47: =原始输入与口径!BT47 -> 24 | N47: =原始输入与口径!BJ47 -> 0 | O47: =M47*AF47*AC47 -> 0.087771429 | P47: =N47*AG47*AC47 -> 0 | Q47: =IF(K47=0,0,IF(ISNUMBER(B47),K47*B47*AC47,NA())) -> 0 | R47: =IF(L47=0,0,IF(ISNUMBER(C47),L47*C47*AC47,NA())) -> 662.24535 | S47: =IF(M47=0,0,IF(ISNUMBER(D47),M47*D47*AC47,NA())) -> 43.233663 | T47: =IF(N47=0,0,IF(ISNUMBER(E47),N47*E47*AC47,NA())) -> 0 | U47: =IF(O47=0,0,O47*F47) -> 11.692152 | V47: =IF(P47=0,0,-P47*G47) -> 0 | W47: =SUM(Q47:V47) -> 717.17116 | X47: =原始输入与口径!CP47 -> 717.17116 | Y47: =W47-X47 -> 0 | Z47: ="当日执行" -> 当日执行 | AA47: =IF(原始输入与口径!AW47,1,0) -> 1 | AB47: =IF(原始输入与口径!AY47,1,0) -> 1 | AC47: =原始输入与口径!$F$5 -> 0.25 | AD47: =原始输入与口径!CG47 -> 0.3125 | AE47: =原始输入与口径!BQ47 -> 0.13714286 | AF47: =IF(AA47=0,0,AJ47/(AH47*AC47)) -> 0.014628571 | AG47: =IF(AA47=0,0,AK47/(AI47*AC47)) -> 6.8571429e-05 | AH47: =IF(ISNUMBER(原始输入与口径!T47),原始输入与口径!T47,"缺失") -> 175 | AI47: =IF(ISNUMBER(原始输入与口径!Y47),原始输入与口径!Y47,"缺失") -> 175 | AJ47: =IF(ISNUMBER(原始输入与口径!AI47),原始输入与口径!AI47,"缺失") -> 0.64 | AK47: =IF(ISNUMBER(原始输入与口径!AL47),原始输入与口径!AL47,"缺失") -> 0.003 | AL47: =IF(ISNUMBER(原始输入与口径!O47),原始输入与口径!O47,"缺失") -> 91.904 | AM47: =SUMIFS(相位SOC复算!$N$9:$N$929,相位SOC复算!$S$9:$S$929,39) -> 0.00026501035 | AN47: =SUMIFS(相位SOC复算!$Q$9:$Q$929,相位SOC复算!$S$9:$S$929,39) -> 0 | AO47: =SUMIFS(相位SOC复算!$R$9:$R$929,相位SOC复算!$S$9:$S$929,39) -> 0.087771429 | AP47: =相位SOC复算!J94 -> 31.73913 | AQ47: =AP47-J47 -> 0 | AR47: =IF(ISBLANK(原始输入与口径!M47),"",原始输入与口径!M47) -> 5.2473 | AS47: =IF(ISBLANK(原始输入与口径!L47),"",原始输入与口径!L47) -> 46234 | AT47: =IF(ISBLANK(原始输入与口径!A47),"",原始输入与口径!A47) -> 46235.271 | AU47: =IF(ISBLANK(原始输入与口径!I47),"",原始输入与口径!I47) -> 2026-08-01_35 | AV47: =IF(ISBLANK(原始输入与口径!J47),"",原始输入与口径!J47) -> 15 | AW47: =IF(ISBLANK(原始输入与口径!BB47),"",原始输入与口径!BB47) -> OK | AX47: =原始输入与口径!CI47 -> 128 | AY47: =原始输入与口径!BS47 -> 175 | AZ47: =原始输入与口径!BI47 -> 175 | BA47: =原始输入与口径!CM47 -> 40 | BB47: =原始输入与口径!BV47 -> 24 | BC47: =原始输入与口径!BL47 -> 24 | BD47: =46235 -> 46235 | BE47: =IF(K47=0,"零头寸，无结算现金",TEXT(K47,"0.000000")&" MW × "&TEXT(B47,"0.000000")&" × "&TEXT(AC47,"0.000000")&" h = "&TEXT(Q47,"0.000000")&" EUR") -> 零头寸，无结算现金 | BF47: =IF(L47=0,"零头寸，无结算现金",TEXT(L47,"0.000000")&" MW × "&TEXT(C47,"0.000000")&" × "&TEXT(AC47,"0.000000")&" h = "&TEXT(R47,"0.000000")&" EUR") -> 40.000000 MW × 66.224535 × 0.250000 h = 662.245345 EUR | BG47: =IF(M47=0,"零头寸，无结算现金",TEXT(M47,"0.000000")&" MW × "&TEXT(D47,"0.000000")&" × "&TEXT(AC47,"0.000000")&" h = "&TEXT(S47,"0.000000")&" EUR") -> 24.000000 MW × 7.205611 × 0.250000 h = 43.233663 EUR | BH47: =IF(N47=0,"零头寸，无结算现金",TEXT(N47,"0.000000")&" MW × "&TEXT(E47,"0.000000")&" × "&TEXT(AC47,"0.000000")&" h = "&TEXT(T47,"0.000000")&" EUR") -> 零头寸，无结算现金 | BI47: =IF(O47=0,"零上调激活电量",TEXT(O47,"0.000000")&" MWh × "&TEXT(F47,"0.000000")&" = "&TEXT(U47,"0.000000")&" EUR") -> 0.087771 MWh × 133.211366 = 11.692152 EUR | BJ47: =IF(P47=0,"零下调激活电量","−("&TEXT(P47,"0.000000")&" MWh × "&TEXT(G47,"0.000000")&") = "&TEXT(V47,"0.000000")&" EUR") -> 零下调激活电量 | BK47: =TEXT(Q47,"0.000000")&" + "&TEXT(R47,"0.000000")&" + "&TEXT(S47,"0.000000")&" + "&TEXT(T47,"0.000000")&" + "&TEXT(U47,"0.000000")&" + "&TEXT(V47,"0.000000")&" = "&TEXT(W47,"0.000000")&" EUR" -> 0.000000 + 662.245345 + 43.233663 + 0.000000 + 11.692152 + 0.000000 = 717.171160 EUR
A48: =原始输入与口径!C48 -> 46235.406 | B48: =IF(ISNUMBER(原始输入与口径!H48),原始输入与口径!H48,"缺失") -> 13.07 | C48: =IF(ISNUMBER(原始输入与口径!R48),原始输入与口径!R48,"缺失") -> 66.224535 | D48: =IF(ISNUMBER(原始输入与口径!W48),原始输入与口径!W48,"缺失") -> 7.2056105 | E48: =IF(ISNUMBER(原始输入与口径!AB48),原始输入与口径!AB48,"缺失") -> 2.3250052 | F48: =IF(ISNUMBER(原始输入与口径!AG48),原始输入与口径!AG48,"缺失") -> 133.21137 | G48: =IF(ISNUMBER(原始输入与口径!AJ48),原始输入与口径!AJ48,"缺失") -> 69.015875 | H48: ="未模拟" -> 未模拟 | I48: =原始输入与口径!CD48 -> 31.73913 | J48: =原始输入与口径!CE48 -> 45.437436 | K48: =原始输入与口径!BZ48 -> -60 | L48: =原始输入与口径!CK48 -> 40 | M48: =原始输入与口径!BT48 -> 24 | N48: =原始输入与口径!BJ48 -> 0 | O48: =M48*AF48*AC48 -> 0.11053714 | P48: =N48*AG48*AC48 -> 0 | Q48: =IF(K48=0,0,IF(ISNUMBER(B48),K48*B48*AC48,NA())) -> -196.05 | R48: =IF(L48=0,0,IF(ISNUMBER(C48),L48*C48*AC48,NA())) -> 662.24535 | S48: =IF(M48=0,0,IF(ISNUMBER(D48),M48*D48*AC48,NA())) -> 43.233663 | T48: =IF(N48=0,0,IF(ISNUMBER(E48),N48*E48*AC48,NA())) -> 0 | U48: =IF(O48=0,0,O48*F48) -> 14.724804 | V48: =IF(P48=0,0,-P48*G48) -> 0 | W48: =SUM(Q48:V48) -> 524.15381 | X48: =原始输入与口径!CP48 -> 524.15381 | Y48: =W48-X48 -> 0 | Z48: ="当日执行" -> 当日执行 | AA48: =IF(原始输入与口径!AW48,1,0) -> 1 | AB48: =IF(原始输入与口径!AY48,1,0) -> 1 | AC48: =原始输入与口径!$F$5 -> 0.25 | AD48: =原始输入与口径!CG48 -> 0.3125 | AE48: =原始输入与口径!BQ48 -> 0.13714286 | AF48: =IF(AA48=0,0,AJ48/(AH48*AC48)) -> 0.018422857 | AG48: =IF(AA48=0,0,AK48/(AI48*AC48)) -> 0.034971429 | AH48: =IF(ISNUMBER(原始输入与口径!T48),原始输入与口径!T48,"缺失") -> 175 | AI48: =IF(ISNUMBER(原始输入与口径!Y48),原始输入与口径!Y48,"缺失") -> 175 | AJ48: =IF(ISNUMBER(原始输入与口径!AI48),原始输入与口径!AI48,"缺失") -> 0.806 | AK48: =IF(ISNUMBER(原始输入与口径!AL48),原始输入与口径!AL48,"缺失") -> 1.53 | AL48: =IF(ISNUMBER(原始输入与口径!O48),原始输入与口径!O48,"缺失") -> 91.904 | AM48: =SUMIFS(相位SOC复算!$N$9:$N$929,相位SOC复算!$S$9:$S$929,40) -> 0.03805085 | AN48: =SUMIFS(相位SOC复算!$Q$9:$Q$929,相位SOC复算!$S$9:$S$929,40) -> 14.889463 | AO48: =SUMIFS(相位SOC复算!$R$9:$R$929,相位SOC复算!$S$9:$S$929,40) -> 0 | AP48: =相位SOC复算!J97 -> 45.437436 | AQ48: =AP48-J48 -> 0 | AR48: =IF(ISBLANK(原始输入与口径!M48),"",原始输入与口径!M48) -> 5.2473 | AS48: =IF(ISBLANK(原始输入与口径!L48),"",原始输入与口径!L48) -> 46234 | AT48: =IF(ISBLANK(原始输入与口径!A48),"",原始输入与口径!A48) -> 46235.281 | AU48: =IF(ISBLANK(原始输入与口径!I48),"",原始输入与口径!I48) -> 2026-08-01_36 | AV48: =IF(ISBLANK(原始输入与口径!J48),"",原始输入与口径!J48) -> 15 | AW48: =IF(ISBLANK(原始输入与口径!BB48),"",原始输入与口径!BB48) -> OK | AX48: =原始输入与口径!CI48 -> 128 | AY48: =原始输入与口径!BS48 -> 175 | AZ48: =原始输入与口径!BI48 -> 175 | BA48: =原始输入与口径!CM48 -> 40 | BB48: =原始输入与口径!BV48 -> 24 | BC48: =原始输入与口径!BL48 -> 24 | BD48: =46235 -> 46235 | BE48: =IF(K48=0,"零头寸，无结算现金",TEXT(K48,"0.000000")&" MW × "&TEXT(B48,"0.000000")&" × "&TEXT(AC48,"0.000000")&" h = "&TEXT(Q48,"0.000000")&" EUR") -> -60.000000 MW × 13.070000 × 0.250000 h = -196.050000 EUR | BF48: =IF(L48=0,"零头寸，无结算现金",TEXT(L48,"0.000000")&" MW × "&TEXT(C48,"0.000000")&" × "&TEXT(AC48,"0.000000")&" h = "&TEXT(R48,"0.000000")&" EUR") -> 40.000000 MW × 66.224535 × 0.250000 h = 662.245345 EUR | BG48: =IF(M48=0,"零头寸，无结算现金",TEXT(M48,"0.000000")&" MW × "&TEXT(D48,"0.000000")&" × "&TEXT(AC48,"0.000000")&" h = "&TEXT(S48,"0.000000")&" EUR") -> 24.000000 MW × 7.205611 × 0.250000 h = 43.233663 EUR | BH48: =IF(N48=0,"零头寸，无结算现金",TEXT(N48,"0.000000")&" MW × "&TEXT(E48,"0.000000")&" × "&TEXT(AC48,"0.000000")&" h = "&TEXT(T48,"0.000000")&" EUR") -> 零头寸，无结算现金 | BI48: =IF(O48=0,"零上调激活电量",TEXT(O48,"0.000000")&" MWh × "&TEXT(F48,"0.000000")&" = "&TEXT(U48,"0.000000")&" EUR") -> 0.110537 MWh × 133.211366 = 14.724804 EUR | BJ48: =IF(P48=0,"零下调激活电量","−("&TEXT(P48,"0.000000")&" MWh × "&TEXT(G48,"0.000000")&") = "&TEXT(V48,"0.000000")&" EUR") -> 零下调激活电量 | BK48: =TEXT(Q48,"0.000000")&" + "&TEXT(R48,"0.000000")&" + "&TEXT(S48,"0.000000")&" + "&TEXT(T48,"0.000000")&" + "&TEXT(U48,"0.000000")&" + "&TEXT(V48,"0.000000")&" = "&TEXT(W48,"0.000000")&" EUR" -> -196.050000 + 662.245345 + 43.233663 + 0.000000 + 14.724804 + 0.000000 = 524.153812 EUR
A49: =原始输入与口径!C49 -> 46235.417 | B49: =IF(ISNUMBER(原始输入与口径!H49),原始输入与口径!H49,"缺失") -> 145.41 | C49: =IF(ISNUMBER(原始输入与口径!R49),原始输入与口径!R49,"缺失") -> 66.224535 | D49: =IF(ISNUMBER(原始输入与口径!W49),原始输入与口径!W49,"缺失") -> 5.2655651 | E49: =IF(ISNUMBER(原始输入与口径!AB49),原始输入与口径!AB49,"缺失") -> 3.0015437 | F49: =IF(ISNUMBER(原始输入与口径!AG49),原始输入与口径!AG49,"缺失") -> 133.30303 | G49: =IF(ISNUMBER(原始输入与口径!AJ49),原始输入与口径!AJ49,"缺失") -> 76.22968 | H49: ="未模拟" -> 未模拟 | I49: =原始输入与口径!CD49 -> 45.437436 | J49: =原始输入与口径!CE49 -> 32.850393 | K49: =原始输入与口径!BZ49 -> 46 | L49: =原始输入与口径!CK49 -> 40 | M49: =原始输入与口径!BT49 -> 14 | N49: =原始输入与口径!BJ49 -> 0 | O49: =M49*AF49*AC49 -> 0.08008 | P49: =N49*AG49*AC49 -> 0 | Q49: =IF(K49=0,0,IF(ISNUMBER(B49),K49*B49*AC49,NA())) -> 1672.215 | R49: =IF(L49=0,0,IF(ISNUMBER(C49),L49*C49*AC49,NA())) -> 662.24535 | S49: =IF(M49=0,0,IF(ISNUMBER(D49),M49*D49*AC49,NA())) -> 18.429478 | T49: =IF(N49=0,0,IF(ISNUMBER(E49),N49*E49*AC49,NA())) -> 0 | U49: =IF(O49=0,0,O49*F49) -> 10.674907 | V49: =IF(P49=0,0,-P49*G49) -> 0 | W49: =SUM(Q49:V49) -> 2363.5647 | X49: =原始输入与口径!CP49 -> 2363.5647 | Y49: =W49-X49 -> 0 | Z49: ="当日执行" -> 当日执行 | AA49: =IF(原始输入与口径!AW49,1,0) -> 1 | AB49: =IF(原始输入与口径!AY49,1,0) -> 1 | AC49: =原始输入与口径!$F$5 -> 0.25 | AD49: =原始输入与口径!CG49 -> 0.3125 | AE49: =原始输入与口径!BQ49 -> 0.13714286 | AF49: =IF(AA49=0,0,AJ49/(AH49*AC49)) -> 0.02288 | AG49: =IF(AA49=0,0,AK49/(AI49*AC49)) -> 0.012777143 | AH49: =IF(ISNUMBER(原始输入与口径!T49),原始输入与口径!T49,"缺失") -> 175 | AI49: =IF(ISNUMBER(原始输入与口径!Y49),原始输入与口径!Y49,"缺失") -> 175 | AJ49: =IF(ISNUMBER(原始输入与口径!AI49),原始输入与口径!AI49,"缺失") -> 1.001 | AK49: =IF(ISNUMBER(原始输入与口径!AL49),原始输入与口径!AL49,"缺失") -> 0.559 | AL49: =IF(ISNUMBER(原始输入与口径!O49),原始输入与口径!O49,"缺失") -> 91.904 | AM49: =SUMIFS(相位SOC复算!$N$9:$N$929,相位SOC复算!$S$9:$S$929,41) -> 0.03496401 | AN49: =SUMIFS(相位SOC复算!$Q$9:$Q$929,相位SOC复算!$S$9:$S$929,41) -> 0 | AO49: =SUMIFS(相位SOC复算!$R$9:$R$929,相位SOC复算!$S$9:$S$929,41) -> 11.58008 | AP49: =相位SOC复算!J100 -> 32.850393 | AQ49: =AP49-J49 -> 0 | AR49: =IF(ISBLANK(原始输入与口径!M49),"",原始输入与口径!M49) -> 5.2473 | AS49: =IF(ISBLANK(原始输入与口径!L49),"",原始输入与口径!L49) -> 46234 | AT49: =IF(ISBLANK(原始输入与口径!A49),"",原始输入与口径!A49) -> 46235.292 | AU49: =IF(ISBLANK(原始输入与口径!I49),"",原始输入与口径!I49) -> 2026-08-01_37 | AV49: =IF(ISBLANK(原始输入与口径!J49),"",原始输入与口径!J49) -> 15 | AW49: =IF(ISBLANK(原始输入与口径!BB49),"",原始输入与口径!BB49) -> OK | AX49: =原始输入与口径!CI49 -> 128 | AY49: =原始输入与口径!BS49 -> 175 | AZ49: =原始输入与口径!BI49 -> 175 | BA49: =原始输入与口径!CM49 -> 40 | BB49: =原始输入与口径!BV49 -> 24 | BC49: =原始输入与口径!BL49 -> 24 | BD49: =46235 -> 46235 | BE49: =IF(K49=0,"零头寸，无结算现金",TEXT(K49,"0.000000")&" MW × "&TEXT(B49,"0.000000")&" × "&TEXT(AC49,"0.000000")&" h = "&TEXT(Q49,"0.000000")&" EUR") -> 46.000000 MW × 145.410000 × 0.250000 h = 1672.215000 EUR | BF49: =IF(L49=0,"零头寸，无结算现金",TEXT(L49,"0.000000")&" MW × "&TEXT(C49,"0.000000")&" × "&TEXT(AC49,"0.000000")&" h = "&TEXT(R49,"0.000000")&" EUR") -> 40.000000 MW × 66.224535 × 0.250000 h = 662.245345 EUR | BG49: =IF(M49=0,"零头寸，无结算现金",TEXT(M49,"0.000000")&" MW × "&TEXT(D49,"0.000000")&" × "&TEXT(AC49,"0.000000")&" h = "&TEXT(S49,"0.000000")&" EUR") -> 14.000000 MW × 5.265565 × 0.250000 h = 18.429478 EUR | BH49: =IF(N49=0,"零头寸，无结算现金",TEXT(N49,"0.000000")&" MW × "&TEXT(E49,"0.000000")&" × "&TEXT(AC49,"0.000000")&" h = "&TEXT(T49,"0.000000")&" EUR") -> 零头寸，无结算现金 | BI49: =IF(O49=0,"零上调激活电量",TEXT(O49,"0.000000")&" MWh × "&TEXT(F49,"0.000000")&" = "&TEXT(U49,"0.000000")&" EUR") -> 0.080080 MWh × 133.303032 = 10.674907 EUR | BJ49: =IF(P49=0,"零下调激活电量","−("&TEXT(P49,"0.000000")&" MWh × "&TEXT(G49,"0.000000")&") = "&TEXT(V49,"0.000000")&" EUR") -> 零下调激活电量 | BK49: =TEXT(Q49,"0.000000")&" + "&TEXT(R49,"0.000000")&" + "&TEXT(S49,"0.000000")&" + "&TEXT(T49,"0.000000")&" + "&TEXT(U49,"0.000000")&" + "&TEXT(V49,"0.000000")&" = "&TEXT(W49,"0.000000")&" EUR" -> 1672.215000 + 662.245345 + 18.429478 + 0.000000 + 10.674907 + 0.000000 = 2363.564730 EUR
A50: =原始输入与口径!C50 -> 46235.427 | B50: =IF(ISNUMBER(原始输入与口径!H50),原始输入与口径!H50,"缺失") -> 66.07 | C50: =IF(ISNUMBER(原始输入与口径!R50),原始输入与口径!R50,"缺失") -> 66.224535 | D50: =IF(ISNUMBER(原始输入与口径!W50),原始输入与口径!W50,"缺失") -> 5.2655651 | E50: =IF(ISNUMBER(原始输入与口径!AB50),原始输入与口径!AB50,"缺失") -> 3.0015437 | F50: =IF(ISNUMBER(原始输入与口径!AG50),原始输入与口径!AG50,"缺失") -> 176.61979 | G50: =IF(ISNUMBER(原始输入与口径!AJ50),原始输入与口径!AJ50,"缺失") -> 0 | H50: ="未模拟" -> 未模拟 | I50: =原始输入与口径!CD50 -> 32.850393 | J50: =原始输入与口径!CE50 -> 32.158302 | K50: =原始输入与口径!BZ50 -> -2.7359899 | L50: =原始输入与口径!CK50 -> 40 | M50: =原始输入与口径!BT50 -> 14 | N50: =原始输入与口径!BJ50 -> 0 | O50: =M50*AF50*AC50 -> 1.25328 | P50: =N50*AG50*AC50 -> 0 | Q50: =IF(K50=0,0,IF(ISNUMBER(B50),K50*B50*AC50,NA())) -> -45.191713 | R50: =IF(L50=0,0,IF(ISNUMBER(C50),L50*C50*AC50,NA())) -> 662.24535 | S50: =IF(M50=0,0,IF(ISNUMBER(D50),M50*D50*AC50,NA())) -> 18.429478 | T50: =IF(N50=0,0,IF(ISNUMBER(E50),N50*E50*AC50,NA())) -> 0 | U50: =IF(O50=0,0,O50*F50) -> 221.35404 | V50: =IF(P50=0,0,-P50*G50) -> 0 | W50: =SUM(Q50:V50) -> 856.83715 | X50: =原始输入与口径!CP50 -> 856.83715 | Y50: =W50-X50 -> 0 | Z50: ="当日执行" -> 当日执行 | AA50: =IF(原始输入与口径!AW50,1,0) -> 1 | AB50: =IF(原始输入与口径!AY50,1,0) -> 1 | AC50: =原始输入与口径!$F$5 -> 0.25 | AD50: =原始输入与口径!CG50 -> 0.3125 | AE50: =原始输入与口径!BQ50 -> 0.13714286 | AF50: =IF(AA50=0,0,AJ50/(AH50*AC50)) -> 0.35808 | AG50: =IF(AA50=0,0,AK50/(AI50*AC50)) -> 0 | AH50: =IF(ISNUMBER(原始输入与口径!T50),原始输入与口径!T50,"缺失") -> 175 | AI50: =IF(ISNUMBER(原始输入与口径!Y50),原始输入与口径!Y50,"缺失") -> 175 | AJ50: =IF(ISNUMBER(原始输入与口径!AI50),原始输入与口径!AI50,"缺失") -> 15.666 | AK50: =IF(ISNUMBER(原始输入与口径!AL50),原始输入与口径!AL50,"缺失") -> 0 | AL50: =IF(ISNUMBER(原始输入与口径!O50),原始输入与口径!O50,"缺失") -> 91.904 | AM50: =SUMIFS(相位SOC复算!$N$9:$N$929,相位SOC复算!$S$9:$S$929,42) -> 0.0041666197 | AN50: =SUMIFS(相位SOC复算!$Q$9:$Q$929,相位SOC复算!$S$9:$S$929,42) -> 0.43907166 | AO50: =SUMIFS(相位SOC复算!$R$9:$R$929,相位SOC复算!$S$9:$S$929,42) -> 1.0083542 | AP50: =相位SOC复算!J102 -> 32.158302 | AQ50: =AP50-J50 -> 0 | AR50: =IF(ISBLANK(原始输入与口径!M50),"",原始输入与口径!M50) -> 5.2473 | AS50: =IF(ISBLANK(原始输入与口径!L50),"",原始输入与口径!L50) -> 46234 | AT50: =IF(ISBLANK(原始输入与口径!A50),"",原始输入与口径!A50) -> 46235.302 | AU50: =IF(ISBLANK(原始输入与口径!I50),"",原始输入与口径!I50) -> 2026-08-01_38 | AV50: =IF(ISBLANK(原始输入与口径!J50),"",原始输入与口径!J50) -> 15 | AW50: =IF(ISBLANK(原始输入与口径!BB50),"",原始输入与口径!BB50) -> OK | AX50: =原始输入与口径!CI50 -> 128 | AY50: =原始输入与口径!BS50 -> 175 | AZ50: =原始输入与口径!BI50 -> 175 | BA50: =原始输入与口径!CM50 -> 40 | BB50: =原始输入与口径!BV50 -> 24 | BC50: =原始输入与口径!BL50 -> 24 | BD50: =46235 -> 46235 | BE50: =IF(K50=0,"零头寸，无结算现金",TEXT(K50,"0.000000")&" MW × "&TEXT(B50,"0.000000")&" × "&TEXT(AC50,"0.000000")&" h = "&TEXT(Q50,"0.000000")&" EUR") -> -2.735990 MW × 66.070000 × 0.250000 h = -45.191713 EUR | BF50: =IF(L50=0,"零头寸，无结算现金",TEXT(L50,"0.000000")&" MW × "&TEXT(C50,"0.000000")&" × "&TEXT(AC50,"0.000000")&" h = "&TEXT(R50,"0.000000")&" EUR") -> 40.000000 MW × 66.224535 × 0.250000 h = 662.245345 EUR | BG50: =IF(M50=0,"零头寸，无结算现金",TEXT(M50,"0.000000")&" MW × "&TEXT(D50,"0.000000")&" × "&TEXT(AC50,"0.000000")&" h = "&TEXT(S50,"0.000000")&" EUR") -> 14.000000 MW × 5.265565 × 0.250000 h = 18.429478 EUR | BH50: =IF(N50=0,"零头寸，无结算现金",TEXT(N50,"0.000000")&" MW × "&TEXT(E50,"0.000000")&" × "&TEXT(AC50,"0.000000")&" h = "&TEXT(T50,"0.000000")&" EUR") -> 零头寸，无结算现金 | BI50: =IF(O50=0,"零上调激活电量",TEXT(O50,"0.000000")&" MWh × "&TEXT(F50,"0.000000")&" = "&TEXT(U50,"0.000000")&" EUR") -> 1.253280 MWh × 176.619785 = 221.354045 EUR | BJ50: =IF(P50=0,"零下调激活电量","−("&TEXT(P50,"0.000000")&" MWh × "&TEXT(G50,"0.000000")&") = "&TEXT(V50,"0.000000")&" EUR") -> 零下调激活电量 | BK50: =TEXT(Q50,"0.000000")&" + "&TEXT(R50,"0.000000")&" + "&TEXT(S50,"0.000000")&" + "&TEXT(T50,"0.000000")&" + "&TEXT(U50,"0.000000")&" + "&TEXT(V50,"0.000000")&" = "&TEXT(W50,"0.000000")&" EUR" -> -45.191713 + 662.245345 + 18.429478 + 0.000000 + 221.354045 + 0.000000 = 856.837155 EUR
A51: =原始输入与口径!C51 -> 46235.438 | B51: =IF(ISNUMBER(原始输入与口径!H51),原始输入与口径!H51,"缺失") -> 13.26 | C51: =IF(ISNUMBER(原始输入与口径!R51),原始输入与口径!R51,"缺失") -> 66.224535 | D51: =IF(ISNUMBER(原始输入与口径!W51),原始输入与口径!W51,"缺失") -> 5.2655651 | E51: =IF(ISNUMBER(原始输入与口径!AB51),原始输入与口径!AB51,"缺失") -> 3.0015437 | F51: =IF(ISNUMBER(原始输入与口径!AG51),原始输入与口径!AG51,"缺失") -> 145.50321 | G51: =IF(ISNUMBER(原始输入与口径!AJ51),原始输入与口径!AJ51,"缺失") -> 0 | H51: ="未模拟" -> 未模拟 | I51: =原始输入与口径!CD51 -> 32.158302 | J51: =原始输入与口径!CE51 -> 45.491015 | K51: =原始输入与口径!BZ51 -> -60 | L51: =原始输入与口径!CK51 -> 40 | M51: =原始输入与口径!BT51 -> 14 | N51: =原始输入与口径!BJ51 -> 0 | O51: =M51*AF51*AC51 -> 0.50792 | P51: =N51*AG51*AC51 -> 0 | Q51: =IF(K51=0,0,IF(ISNUMBER(B51),K51*B51*AC51,NA())) -> -198.9 | R51: =IF(L51=0,0,IF(ISNUMBER(C51),L51*C51*AC51,NA())) -> 662.24535 | S51: =IF(M51=0,0,IF(ISNUMBER(D51),M51*D51*AC51,NA())) -> 18.429478 | T51: =IF(N51=0,0,IF(ISNUMBER(E51),N51*E51*AC51,NA())) -> 0 | U51: =IF(O51=0,0,O51*F51) -> 73.903991 | V51: =IF(P51=0,0,-P51*G51) -> 0 | W51: =SUM(Q51:V51) -> 555.67881 | X51: =原始输入与口径!CP51 -> 555.67881 | Y51: =W51-X51 -> 0 | Z51: ="当日执行" -> 当日执行 | AA51: =IF(原始输入与口径!AW51,1,0) -> 1 | AB51: =IF(原始输入与口径!AY51,1,0) -> 1 | AC51: =原始输入与口径!$F$5 -> 0.25 | AD51: =原始输入与口径!CG51 -> 0.3125 | AE51: =原始输入与口径!BQ51 -> 0.13714286 | AF51: =IF(AA51=0,0,AJ51/(AH51*AC51)) -> 0.14512 | AG51: =IF(AA51=0,0,AK51/(AI51*AC51)) -> 0 | AH51: =IF(ISNUMBER(原始输入与口径!T51),原始输入与口径!T51,"缺失") -> 175 | AI51: =IF(ISNUMBER(原始输入与口径!Y51),原始输入与口径!Y51,"缺失") -> 175 | AJ51: =IF(ISNUMBER(原始输入与口径!AI51),原始输入与口径!AI51,"缺失") -> 6.349 | AK51: =IF(ISNUMBER(原始输入与口径!AL51),原始输入与口径!AL51,"缺失") -> 0 | AL51: =IF(ISNUMBER(原始输入与口径!O51),原始输入与口径!O51,"缺失") -> 91.904 | AM51: =SUMIFS(相位SOC复算!$N$9:$N$929,相位SOC复算!$S$9:$S$929,43) -> 0.037035316 | AN51: =SUMIFS(相位SOC复算!$Q$9:$Q$929,相位SOC复算!$S$9:$S$929,43) -> 14.49208 | AO51: =SUMIFS(相位SOC复算!$R$9:$R$929,相位SOC复算!$S$9:$S$929,43) -> 0 | AP51: =相位SOC复算!J104 -> 45.491015 | AQ51: =AP51-J51 -> 0 | AR51: =IF(ISBLANK(原始输入与口径!M51),"",原始输入与口径!M51) -> 5.2473 | AS51: =IF(ISBLANK(原始输入与口径!L51),"",原始输入与口径!L51) -> 46234 | AT51: =IF(ISBLANK(原始输入与口径!A51),"",原始输入与口径!A51) -> 46235.312 | AU51: =IF(ISBLANK(原始输入与口径!I51),"",原始输入与口径!I51) -> 2026-08-01_39 | AV51: =IF(ISBLANK(原始输入与口径!J51),"",原始输入与口径!J51) -> 15 | AW51: =IF(ISBLANK(原始输入与口径!BB51),"",原始输入与口径!BB51) -> OK | AX51: =原始输入与口径!CI51 -> 128 | AY51: =原始输入与口径!BS51 -> 175 | AZ51: =原始输入与口径!BI51 -> 175 | BA51: =原始输入与口径!CM51 -> 40 | BB51: =原始输入与口径!BV51 -> 24 | BC51: =原始输入与口径!BL51 -> 24 | BD51: =46235 -> 46235 | BE51: =IF(K51=0,"零头寸，无结算现金",TEXT(K51,"0.000000")&" MW × "&TEXT(B51,"0.000000")&" × "&TEXT(AC51,"0.000000")&" h = "&TEXT(Q51,"0.000000")&" EUR") -> -60.000000 MW × 13.260000 × 0.250000 h = -198.900000 EUR | BF51: =IF(L51=0,"零头寸，无结算现金",TEXT(L51,"0.000000")&" MW × "&TEXT(C51,"0.000000")&" × "&TEXT(AC51,"0.000000")&" h = "&TEXT(R51,"0.000000")&" EUR") -> 40.000000 MW × 66.224535 × 0.250000 h = 662.245345 EUR | BG51: =IF(M51=0,"零头寸，无结算现金",TEXT(M51,"0.000000")&" MW × "&TEXT(D51,"0.000000")&" × "&TEXT(AC51,"0.000000")&" h = "&TEXT(S51,"0.000000")&" EUR") -> 14.000000 MW × 5.265565 × 0.250000 h = 18.429478 EUR | BH51: =IF(N51=0,"零头寸，无结算现金",TEXT(N51,"0.000000")&" MW × "&TEXT(E51,"0.000000")&" × "&TEXT(AC51,"0.000000")&" h = "&TEXT(T51,"0.000000")&" EUR") -> 零头寸，无结算现金 | BI51: =IF(O51=0,"零上调激活电量",TEXT(O51,"0.000000")&" MWh × "&TEXT(F51,"0.000000")&" = "&TEXT(U51,"0.000000")&" EUR") -> 0.507920 MWh × 145.503211 = 73.903991 EUR | BJ51: =IF(P51=0,"零下调激活电量","−("&TEXT(P51,"0.000000")&" MWh × "&TEXT(G51,"0.000000")&") = "&TEXT(V51,"0.000000")&" EUR") -> 零下调激活电量 | BK51: =TEXT(Q51,"0.000000")&" + "&TEXT(R51,"0.000000")&" + "&TEXT(S51,"0.000000")&" + "&TEXT(T51,"0.000000")&" + "&TEXT(U51,"0.000000")&" + "&TEXT(V51,"0.000000")&" = "&TEXT(W51,"0.000000")&" EUR" -> -198.900000 + 662.245345 + 18.429478 + 0.000000 + 73.903991 + 0.000000 = 555.678814 EUR
A52: =原始输入与口径!C52 -> 46235.448 | B52: =IF(ISNUMBER(原始输入与口径!H52),原始输入与口径!H52,"缺失") -> 14.62 | C52: =IF(ISNUMBER(原始输入与口径!R52),原始输入与口径!R52,"缺失") -> 66.224535 | D52: =IF(ISNUMBER(原始输入与口径!W52),原始输入与口径!W52,"缺失") -> 5.2655651 | E52: =IF(ISNUMBER(原始输入与口径!AB52),原始输入与口径!AB52,"缺失") -> 3.0015437 | F52: =IF(ISNUMBER(原始输入与口径!AG52),原始输入与口径!AG52,"缺失") -> 133.21137 | G52: =IF(ISNUMBER(原始输入与口径!AJ52),原始输入与口径!AJ52,"缺失") -> 76.22968 | H52: ="未模拟" -> 未模拟 | I52: =原始输入与口径!CD52 -> 45.491015 | J52: =原始输入与口径!CE52 -> 59.284097 | K52: =原始输入与口径!BZ52 -> -60 | L52: =原始输入与口径!CK52 -> 40 | M52: =原始输入与口径!BT52 -> 14 | N52: =原始输入与口径!BJ52 -> 0 | O52: =M52*AF52*AC52 -> 0.00752 | P52: =N52*AG52*AC52 -> 0 | Q52: =IF(K52=0,0,IF(ISNUMBER(B52),K52*B52*AC52,NA())) -> -219.3 | R52: =IF(L52=0,0,IF(ISNUMBER(C52),L52*C52*AC52,NA())) -> 662.24535 | S52: =IF(M52=0,0,IF(ISNUMBER(D52),M52*D52*AC52,NA())) -> 18.429478 | T52: =IF(N52=0,0,IF(ISNUMBER(E52),N52*E52*AC52,NA())) -> 0 | U52: =IF(O52=0,0,O52*F52) -> 1.0017495 | V52: =IF(P52=0,0,-P52*G52) -> 0 | W52: =SUM(Q52:V52) -> 462.37657 | X52: =原始输入与口径!CP52 -> 462.37657 | Y52: =W52-X52 -> 0 | Z52: ="当日执行" -> 当日执行 | AA52: =IF(原始输入与口径!AW52,1,0) -> 1 | AB52: =IF(原始输入与口径!AY52,1,0) -> 1 | AC52: =原始输入与口径!$F$5 -> 0.25 | AD52: =原始输入与口径!CG52 -> 0.3125 | AE52: =原始输入与口径!BQ52 -> 0.13714286 | AF52: =IF(AA52=0,0,AJ52/(AH52*AC52)) -> 0.0021485714 | AG52: =IF(AA52=0,0,AK52/(AI52*AC52)) -> 0.0028342857 | AH52: =IF(ISNUMBER(原始输入与口径!T52),原始输入与口径!T52,"缺失") -> 175 | AI52: =IF(ISNUMBER(原始输入与口径!Y52),原始输入与口径!Y52,"缺失") -> 175 | AJ52: =IF(ISNUMBER(原始输入与口径!AI52),原始输入与口径!AI52,"缺失") -> 0.094 | AK52: =IF(ISNUMBER(原始输入与口径!AL52),原始输入与口径!AL52,"缺失") -> 0.124 | AL52: =IF(ISNUMBER(原始输入与口径!O52),原始输入与口径!O52,"缺失") -> 91.904 | AM52: =SUMIFS(相位SOC复算!$N$9:$N$929,相位SOC复算!$S$9:$S$929,44) -> 0.038314116 | AN52: =SUMIFS(相位SOC复算!$Q$9:$Q$929,相位SOC复算!$S$9:$S$929,44) -> 14.99248 | AO52: =SUMIFS(相位SOC复算!$R$9:$R$929,相位SOC复算!$S$9:$S$929,44) -> 0 | AP52: =相位SOC复算!J107 -> 59.284097 | AQ52: =AP52-J52 -> 0 | AR52: =IF(ISBLANK(原始输入与口径!M52),"",原始输入与口径!M52) -> 5.2473 | AS52: =IF(ISBLANK(原始输入与口径!L52),"",原始输入与口径!L52) -> 46234 | AT52: =IF(ISBLANK(原始输入与口径!A52),"",原始输入与口径!A52) -> 46235.323 | AU52: =IF(ISBLANK(原始输入与口径!I52),"",原始输入与口径!I52) -> 2026-08-01_40 | AV52: =IF(ISBLANK(原始输入与口径!J52),"",原始输入与口径!J52) -> 15 | AW52: =IF(ISBLANK(原始输入与口径!BB52),"",原始输入与口径!BB52) -> OK | AX52: =原始输入与口径!CI52 -> 128 | AY52: =原始输入与口径!BS52 -> 175 | AZ52: =原始输入与口径!BI52 -> 175 | BA52: =原始输入与口径!CM52 -> 40 | BB52: =原始输入与口径!BV52 -> 24 | BC52: =原始输入与口径!BL52 -> 24 | BD52: =46235 -> 46235 | BE52: =IF(K52=0,"零头寸，无结算现金",TEXT(K52,"0.000000")&" MW × "&TEXT(B52,"0.000000")&" × "&TEXT(AC52,"0.000000")&" h = "&TEXT(Q52,"0.000000")&" EUR") -> -60.000000 MW × 14.620000 × 0.250000 h = -219.300000 EUR | BF52: =IF(L52=0,"零头寸，无结算现金",TEXT(L52,"0.000000")&" MW × "&TEXT(C52,"0.000000")&" × "&TEXT(AC52,"0.000000")&" h = "&TEXT(R52,"0.000000")&" EUR") -> 40.000000 MW × 66.224535 × 0.250000 h = 662.245345 EUR | BG52: =IF(M52=0,"零头寸，无结算现金",TEXT(M52,"0.000000")&" MW × "&TEXT(D52,"0.000000")&" × "&TEXT(AC52,"0.000000")&" h = "&TEXT(S52,"0.000000")&" EUR") -> 14.000000 MW × 5.265565 × 0.250000 h = 18.429478 EUR | BH52: =IF(N52=0,"零头寸，无结算现金",TEXT(N52,"0.000000")&" MW × "&TEXT(E52,"0.000000")&" × "&TEXT(AC52,"0.000000")&" h = "&TEXT(T52,"0.000000")&" EUR") -> 零头寸，无结算现金 | BI52: =IF(O52=0,"零上调激活电量",TEXT(O52,"0.000000")&" MWh × "&TEXT(F52,"0.000000")&" = "&TEXT(U52,"0.000000")&" EUR") -> 0.007520 MWh × 133.211366 = 1.001749 EUR | BJ52: =IF(P52=0,"零下调激活电量","−("&TEXT(P52,"0.000000")&" MWh × "&TEXT(G52,"0.000000")&") = "&TEXT(V52,"0.000000")&" EUR") -> 零下调激活电量 | BK52: =TEXT(Q52,"0.000000")&" + "&TEXT(R52,"0.000000")&" + "&TEXT(S52,"0.000000")&" + "&TEXT(T52,"0.000000")&" + "&TEXT(U52,"0.000000")&" + "&TEXT(V52,"0.000000")&" = "&TEXT(W52,"0.000000")&" EUR" -> -219.300000 + 662.245345 + 18.429478 + 0.000000 + 1.001749 + 0.000000 = 462.376573 EUR
A53: =原始输入与口径!C53 -> 46235.458 | B53: =IF(ISNUMBER(原始输入与口径!H53),原始输入与口径!H53,"缺失") -> 121.44 | C53: =IF(ISNUMBER(原始输入与口径!R53),原始输入与口径!R53,"缺失") -> 66.224535 | D53: =IF(ISNUMBER(原始输入与口径!W53),原始输入与口径!W53,"缺失") -> 5.177901 | E53: =IF(ISNUMBER(原始输入与口径!AB53),原始输入与口径!AB53,"缺失") -> 3.0072609 | F53: =IF(ISNUMBER(原始输入与口径!AG53),原始输入与口径!AG53,"缺失") -> 133.34877 | G53: =IF(ISNUMBER(原始输入与口径!AJ53),原始输入与口径!AJ53,"缺失") -> 76.22968 | H53: ="未模拟" -> 未模拟 | I53: =原始输入与口径!CD53 -> 59.284097 | J53: =原始输入与口径!CE53 -> 42.983774 | K53: =原始输入与口径!BZ53 -> 60 | L53: =原始输入与口径!CK53 -> 40 | M53: =原始输入与口径!BT53 -> 0 | N53: =原始输入与口径!BJ53 -> 24 | O53: =M53*AF53*AC53 -> 0 | P53: =N53*AG53*AC53 -> 0.0037028571 | Q53: =IF(K53=0,0,IF(ISNUMBER(B53),K53*B53*AC53,NA())) -> 1821.6 | R53: =IF(L53=0,0,IF(ISNUMBER(C53),L53*C53*AC53,NA())) -> 662.24535 | S53: =IF(M53=0,0,IF(ISNUMBER(D53),M53*D53*AC53,NA())) -> 0 | T53: =IF(N53=0,0,IF(ISNUMBER(E53),N53*E53*AC53,NA())) -> 18.043565 | U53: =IF(O53=0,0,O53*F53) -> 0 | V53: =IF(P53=0,0,-P53*G53) -> -0.28226762 | W53: =SUM(Q53:V53) -> 2501.6066 | X53: =原始输入与口径!CP53 -> 2501.6066 | Y53: =W53-X53 -> 0 | Z53: ="当日执行" -> 当日执行 | AA53: =IF(原始输入与口径!AW53,1,0) -> 1 | AB53: =IF(原始输入与口径!AY53,1,0) -> 1 | AC53: =原始输入与口径!$F$5 -> 0.25 | AD53: =原始输入与口径!CG53 -> 0.3125 | AE53: =原始输入与口径!BQ53 -> 0.13714286 | AF53: =IF(AA53=0,0,AJ53/(AH53*AC53)) -> 0.0688 | AG53: =IF(AA53=0,0,AK53/(AI53*AC53)) -> 0.00061714286 | AH53: =IF(ISNUMBER(原始输入与口径!T53),原始输入与口径!T53,"缺失") -> 175 | AI53: =IF(ISNUMBER(原始输入与口径!Y53),原始输入与口径!Y53,"缺失") -> 175 | AJ53: =IF(ISNUMBER(原始输入与口径!AI53),原始输入与口径!AI53,"缺失") -> 3.01 | AK53: =IF(ISNUMBER(原始输入与口径!AL53),原始输入与口径!AL53,"缺失") -> 0.027 | AL53: =IF(ISNUMBER(原始输入与口径!O53),原始输入与口径!O53,"缺失") -> 91.904 | AM53: =SUMIFS(相位SOC复算!$N$9:$N$929,相位SOC复算!$S$9:$S$929,45) -> 0.045278675 | AN53: =SUMIFS(相位SOC复算!$Q$9:$Q$929,相位SOC复算!$S$9:$S$929,45) -> 0 | AO53: =SUMIFS(相位SOC复算!$R$9:$R$929,相位SOC复算!$S$9:$S$929,45) -> 14.996297 | AP53: =相位SOC复算!J110 -> 42.983774 | AQ53: =AP53-J53 -> 0 | AR53: =IF(ISBLANK(原始输入与口径!M53),"",原始输入与口径!M53) -> 5.2473 | AS53: =IF(ISBLANK(原始输入与口径!L53),"",原始输入与口径!L53) -> 46234 | AT53: =IF(ISBLANK(原始输入与口径!A53),"",原始输入与口径!A53) -> 46235.333 | AU53: =IF(ISBLANK(原始输入与口径!I53),"",原始输入与口径!I53) -> 2026-08-01_41 | AV53: =IF(ISBLANK(原始输入与口径!J53),"",原始输入与口径!J53) -> 15 | AW53: =IF(ISBLANK(原始输入与口径!BB53),"",原始输入与口径!BB53) -> OK | AX53: =原始输入与口径!CI53 -> 128 | AY53: =原始输入与口径!BS53 -> 175 | AZ53: =原始输入与口径!BI53 -> 175 | BA53: =原始输入与口径!CM53 -> 40 | BB53: =原始输入与口径!BV53 -> 24 | BC53: =原始输入与口径!BL53 -> 24 | BD53: =46235 -> 46235 | BE53: =IF(K53=0,"零头寸，无结算现金",TEXT(K53,"0.000000")&" MW × "&TEXT(B53,"0.000000")&" × "&TEXT(AC53,"0.000000")&" h = "&TEXT(Q53,"0.000000")&" EUR") -> 60.000000 MW × 121.440000 × 0.250000 h = 1821.600000 EUR | BF53: =IF(L53=0,"零头寸，无结算现金",TEXT(L53,"0.000000")&" MW × "&TEXT(C53,"0.000000")&" × "&TEXT(AC53,"0.000000")&" h = "&TEXT(R53,"0.000000")&" EUR") -> 40.000000 MW × 66.224535 × 0.250000 h = 662.245345 EUR | BG53: =IF(M53=0,"零头寸，无结算现金",TEXT(M53,"0.000000")&" MW × "&TEXT(D53,"0.000000")&" × "&TEXT(AC53,"0.000000")&" h = "&TEXT(S53,"0.000000")&" EUR") -> 零头寸，无结算现金 | BH53: =IF(N53=0,"零头寸，无结算现金",TEXT(N53,"0.000000")&" MW × "&TEXT(E53,"0.000000")&" × "&TEXT(AC53,"0.000000")&" h = "&TEXT(T53,"0.000000")&" EUR") -> 24.000000 MW × 3.007261 × 0.250000 h = 18.043565 EUR | BI53: =IF(O53=0,"零上调激活电量",TEXT(O53,"0.000000")&" MWh × "&TEXT(F53,"0.000000")&" = "&TEXT(U53,"0.000000")&" EUR") -> 零上调激活电量 | BJ53: =IF(P53=0,"零下调激活电量","−("&TEXT(P53,"0.000000")&" MWh × "&TEXT(G53,"0.000000")&") = "&TEXT(V53,"0.000000")&" EUR") -> −(0.003703 MWh × 76.229680) = -0.282268 EUR | BK53: =TEXT(Q53,"0.000000")&" + "&TEXT(R53,"0.000000")&" + "&TEXT(S53,"0.000000")&" + "&TEXT(T53,"0.000000")&" + "&TEXT(U53,"0.000000")&" + "&TEXT(V53,"0.000000")&" = "&TEXT(W53,"0.000000")&" EUR" -> 1821.600000 + 662.245345 + 0.000000 + 18.043565 + 0.000000 + -0.282268 = 2501.606643 EUR
